Workbook

Sheet README
A1: TITLE | B1: THE STOCK ELEPHANT -- Part III: Seven-Actor SFC Toy Model
A3: PURPOSE | B3: This spreadsheet implements a Stock-Flow Consistent (SFC) balance sheet model for seven actors in the international dollar circuit. Every inter-actor flow is enforced by formula. The SFC_CHECK sheet verifies that all accounting identities hold across all years.
A5: YEAR MAPPING | B5: Y0=2016 (baseline), Y1=2017, Y2=2018, Y3=2019, Y4=2020 (COVID), Y5=2021, Y6=2022 (basis trade surge), Y7=2023 (QDLP reopens), Y8=2024, Y9=2025, Y10+=Stress scenario. NOTE: In the published article, only Y0..Y10+ labels are used. No calendar dates appear in the publication.
A7: NAMING CONVENTIONS | B7: AmeriCo = reserve currency issuer (US analog). JapanCo = surplus accumulator (China analog). JapCBCo = JapanCo central bank sub-account. JapY = JapanCo domestic currency (CNY analog). JapInv = JapanCo outward investment projects (BRI analog). CommodityCo = commodity-exporting sovereign (Gulf/EM analog, generic). GlobalBankCo = large international bank. RepoCo = repo desk / FICC member. HedgeCo = basis trade vehicle (Cayman-registered). FedCo = AmeriCo central bank / absorber of last resort.
A9: UNITS | B9: All values in stylized $B (billions). Toy model -- ratios matter, not absolute scale. Real-world order-of-magnitude calibration noted in ASSUMPTIONS sheet.
A11: COLOR CODING | B11: BLUE TEXT = hardcoded input (change these for scenarios). BLACK TEXT = formula (do not hardcode). GREEN TEXT = cross-sheet reference. GREEN BACKGROUND = asset rows. ORANGE BACKGROUND = liability rows. PURPLE BACKGROUND = derivative / off-balance-sheet rows. YELLOW BACKGROUND = equity / net worth rows. BLUE BACKGROUND = fractional measure rows. RED BACKGROUND = stress scenario rows.
A13: SFC IDENTITIES | B13: The following identities must hold at every year column. They are verified in SFC_CHECK sheet. Any red cell in SFC_CHECK indicates a model error.
A14: Identity 1 | B14: JapanCo deposit at GlobalBankCo = GlobalBankCo liability to JapanCo
A15: Identity 2 | B15: CommodityCo deposit at GlobalBankCo = GlobalBankCo liability to CommodityCo
A16: Identity 3 | B16: GlobalBankCo repo to RepoCo = RepoCo repo payable to GlobalBankCo
A17: Identity 4 | B17: RepoCo repo to HedgeCo = HedgeCo repo payable to RepoCo
A18: Identity 5 | B18: HedgeCo long cash Treasury = Treasury held via repo chain (= RepoCo repo to HedgeCo)
... A28: PUBLICATION NOTE | B28: Internal working document. Publication version uses Y0..Y10+ labels only, removes CommodityCo name, removes JapCBCo/JapY/JapInv labels, and presents fractional measure formulas without estimated values. Editorial decision on what to publish made at end of drafting.
A30: PART IV EXTENSION
A31: New sheets added for Part IV -- AmeriCo Internal Sector Decomposition
A32: AmeriCo (existing) is the aggregate. Five new sheets decompose it internally.
A33: HouseholdCo | B33: Wage income, pension assets (FinServCo LPs), housing equity, consumer debt
A34: ManuCo | B34: Physical productive base -- plant, equipment, tradeable output, wage bill
A35: ProdServiceCo | B35: Technology / software / IP -- real TFP gains, equity-funded, low debt
A36: FinServCo | B36: Pension funds + insurance -- LP in HedgeCo, long-duration Treasuries, equity portfolio. FISIM income measured as GDP but not productive output.
A37: AmeriBankCo | B37: Regulated bank intermediary -- SLR-constrained, routes FedCo reserves to FinServCo via repo. The valve.
A38: GovCo | B38: Already exists. Treasury issuer, fiscal flows.
A40: INTERNAL SFC IDENTITIES (rows 12-17 in SFC_CHECK)
A41: Identity 12 | B41: ManuCo wages + ProdServiceCo wages + FinServCo wages = HouseholdCo wage income
A42: Identity 13 | B42: HouseholdCo deposits + ManuCo deposits + ProdServiceCo deposits = AmeriBankCo deposit liabilities (domestic)
A43: Identity 14 | B43: AmeriBankCo repo to FinServCo = FinServCo repo payable to AmeriBankCo
A44: Identity 15 | B44: GovCo domestic bonds = HouseholdCo pension Treasury + AmeriBankCo Treasury + FinServCo direct Treasury
A45: Identity 16 | B45: FedCo new reserves = AmeriBankCo reserve assets (each absorption episode)
A46: Identity 17 | B46: FinServCo LP stake in HedgeCo = HedgeCo equity base (ASSUMPTIONS r43)
A48: THESIS (no behavioral assumptions required)
B49: FedCo absorbs -> AmeriBankCo reserves up -> SLR routes to FinServCo repo -> discount rate falls -> ProdServiceCo equity rises (DCF identity) -> ManuCo investment crowded out (return differential) -> ManuCo wage bill shrinks -> HouseholdCo wage share falls. Every step is accounting or pricing identity.
A51: SFC INTEGRITY FIX (applied)
A52: RepoCo row 4 (Treasury asset) removed. RepoCo holds repo loan (cash claim) only. Treasury lives on HedgeCo balance sheet.
A53: Identity 18 added to SFC_CHECK: Treasury conservation. Every GovCo bond in exactly one on-balance-sheet location.
A54: Identity 18a: RepoCo on-BS Treasury = 0. Identity 18b: ClearCo on-BS Treasury = 0 (novation = memorandum only).
A55: Rule enforced: Bond ownership is unique. Repo creates claims, not duplicate assets.
A57: REVISION LOG — Reviewer fixes applied
A58: FIX 1 — Calibration triangle | B58: hedge_multiplier: 1.3→1.76 (Barth-Beltran cash/CFTC futures). novation fraction: 0.25→0.771 (TVR=22.9%).
A60: FIX 2 — κ divergence equation | B60: Explicit inequality in MEASURES: accumulation_rate vs TFP_growth. Falsification condition: κ converges only if TFP > (CA_deficit/K_real). At 7% TFP: still diverges. Part V anchor.
A62: FIX 3 — Selling sensitivity weights | B62: Seller chain now weighted simultaneous (interior solution), not purely sequential (corner solution). FS weight=0.50, AB=0.25, Official=0.25. Priority preserved, overlap allowed.
A64: FIX 4 — Duration mix toggle | B64: ASSUMPTIONS: duration_mix [0=bills, 1=bonds]. When Treasury shifts to bills, basis trade collateral compresses. BTAR_adjusted = BTAR × duration_mix. Effective Part IV mechanic.
A66: FIX 5 — Gate as conditional brake | B66: Gate is NOT automatic cascade trigger. Gate = brake (stabilizing). Cascade fires only when illiquidity ratio > 5 AND PC default shock simultaneously. Single-period gate = brake.
A68: FIX 6 — TVR dynamic qualifier | B68: TVR calibrated at 22.9% (Barth-Beltran 2025). Note added: varies with collateral velocity and novation intensity.
A70: FIX 7 — Scenario 5 joint stress | B70: CONTAGION S5: Hormuz + Blue Owl + Tariff firing simultaneously. 9-step cascade. Non-sequential selling → interior solution → faster yield move. April 2026 calibration.
A72: FIX 8 — Commodity stress recalibration | B72: CommodityCo commodity_price_shock Y10+: -50%→-70% (Hormuz calibration: largest disruption in history, 2.5% global energy supply). Both receivables and import costs hit simultaneously.
A74: V2 REVISION (May 2026)
A75: FIX 1 -- AmeriBankCo deposit wiring | B75: AmeriBankCo r11 (HH deposit liability) was wired to HouseholdCo r8 (HH direct TSY) instead of r7 (Deposits at AmeriBankCo). Fixed. Restores SFC Identity 13.
A76: FIX 2 -- Identity 14 check | B76: SFC_CHECK r22 was comparing AmeriBankCo r5 against FinServCo r12 (pension obligations) when it should compare against FinServCo r14 (repo payable). The model was correct; the check formula had a typo.
A77: FIX 3 -- Diagnostic relabeling | B77: SFC_CHECK rows 30, 41, 48, 52 are diagnostic measures, not identity violations. Relabeled with DIAG prefix.
A78: FIX 4 -- FIMA known issue | B78: Identity 41 flagged as known issue. FedCo and JapanCo FIMA computed on different bases.
A79: FIX 5 -- Comment cell types | B79: Four pre-existing cells (GovCo B17, MEASURES B28/B59/B62) had notes-column text incorrectly stored as formulas. Excel rejected these on open. Now stored as plain text.
A80: SCOPE NOTE | B80: Published Part IV and Part IVb are unaffected. Macro routing chain identities and gauge measures all hold in v1 and v2.
A81: VERIFICATION REQUIREMENT | B81: Open in Excel with iterative calculation enabled: File > Options > Formulas > Enable iterative calculation. Set max iterations 100, max change 0.001.

Sheet ASSUMPTIONS
A1: ASSUMPTIONS -- All hardcoded inputs (blue). Change here; formulas flow through.
A2: Account / Line Item | B2: Notes / Source | C2: Y0 | D2: Y1 | E2: Y2 | F2: Y3 | G2: Y4 | H2: Y5 | I2: Y6 | J2: Y7 | K2: Y8 | L2: Y9 | M2: Y10+ Stress
A3: AMERICО ASSUMPTIONS
A4: Productive capital K_real ($B) | B4: Stylized. Real-world US fixed capital ~$60T; toy model ratios matter not scale. | C4: 300 | D4: 310 | E4: 325 | F4: 340 | G4: 330 | H4: 345 | I4: 365 | J4: 380 | K4: 400 | L4: 415 | M4: 400
A5: GDP (Y_productive, $B) | B5: Toy model GDP. FISIM-adjusted -- financial sector value-add excluded. | C5: 280 | D5: 287 | E5: 294 | F5: 302 | G5: 288 | H5: 300 | I5: 308 | J5: 315 | K5: 320 | L5: 318 | M5: 300
A6: CA deficit per year ($B) | B6: Real-world US CA deficit: ~$1T/yr by 2024. Toy model scaled. | C6: 40 | D6: 45 | E6: 50 | F6: 55 | G6: 60 | H6: 65 | I6: 80 | J6: 90 | K6: 100 | L6: 110 | M6: 120
A7: NIIP Y0 starting value ($B) | B7: Only Y0 is input. Subsequent years formula: prior year + CA deficit. | C7: -80 | D7: 0 | E7: 0 | F7: 0 | G7: 0 | H7: 0 | I7: 0 | J7: 0 | K7: 0 | L7: 0 | M7: 0
A8: Official reserve liabilities Y0 ($B) | B8: Real-world: $7.5T official reserves globally. Toy model scaled. | C8: 100 | D8: 0 | E8: 0 | F8: 0 | G8: 0 | H8: 0 | I8: 0 | J8: 0 | K8: 0 | L8: 0 | M8: 0
A9: Reserve growth rate (% per year) | B9: Flat since 2015 peak. Real-world PBOC reserves ~$3.1T, stable. | C9: 0.015 | D9: 0.015 | E9: 0.01 | F9: 0.005 | G9: 0 | H9: -0.005 | I9: -0.003 | J9: 0.002 | K9: 0.005 | L9: 0.003 | M9: 0
A11: JAPANCO ASSUMPTIONS
A12: CA surplus per year ($B) | B12: SUPERSEDED by JapanCo endogenous CA = export_rev - oil_import_bill. See JapanCo trade flows rows. Two-phase Hormuz structure is now endogenous. | C12: 200 | D12: 210 | E12: 350 | F12: 420 | G12: 310 | H12: 350 | I12: 420 | J12: 250 | K12: 500 | L12: 600 | M12: 550
A13: PBOC (JapCBCo) reserve accumulation rate (% of surplus) | B13: Most surplus NOT going to official reserves since 2015. Setser routing gap. | C13: 0.05 | D13: 0.05 | E13: 0.05 | F13: 0.03 | G13: 0.02 | H13: 0.02 | I13: 0.01 | J13: 0.02 | K13: 0.01 | L13: 0.01 | M13: 0.01
A14: GlobalBankCo deposit rate (% of routing gap) | B14: State rerouting channel. BIS LBS code G proxy (loans+deposits, inseparable). | C14: 0.08 | D14: 0.09 | E14: 0.1 | F14: 0.1 | G14: 0.12 | H14: 0.13 | I14: 0.18 | J14: 0.15 | K14: 0.15 | L14: 0.14 | M14: 0.12
A15: JapInv project lending per year ($B) | B15: JapanCo outward project lending (BRI analog). | C15: 8 | D15: 10 | E15: 15 | F15: 18 | G15: 15 | H15: 15 | I15: 14 | J15: 14 | K15: 14 | L15: 12 | M15: 12
A16: Private channel open? (1=yes, 0=no) | B16: QDLP: halted Jul 2015 (pre-Y0), reinstated Apr 2018 (Y2), halted again ~Y4, QDLP expansion Sep 2023 (Y7). | C16: 0 | D16: 0 | E16: 1 | F16: 1 | G16: 0 | H16: 0 | I16: 0 | J16: 1 | K16: 1 | L16: 1 | M16: 1
A17: Private channel flow (% of surplus, if open) | B17: QDII quota: $159.7B. Small relative to total routing gap. | C17: 0 | D17: 0 | E17: 0.05 | F17: 0.05 | G17: 0 | H17: 0 | I17: 0 | J17: 0.03 | K17: 0.04 | L17: 0.05 | M17: 0.05
A19: COMMODITYCO ASSUMPTIONS
A20: Commodity receivables Y0 ($B) | B20: Oil/gas/minerals export receivables. Volatile. | C20: 60 | D20: 0 | E20: 0 | F20: 0 | G20: 0 | H20: 0 | I20: 0 | J20: 0 | K20: 0 | L20: 0 | M20: 0
A21: Commodity price change (% per year) | B21: Hormuz calibration: -70% Y10+ (largest disruption in history, 2.5% global energy supply, simultaneous with receivables collapse and import cost spike). | C21: 0.05 | D21: -0.1 | E21: 0.05 | F21: 0.1 | G21: -0.45 | H21: 0.3 | I21: 0.2 | J21: 0.05 | K21: 0.1 | L21: -0.05 | M21: -0.7
A22: GlobalBankCo deposit Y0 ($B) | B22: Dollar liquid buffer. First withdrawal target under stress. | C22: 45 | D22: 0 | E22: 0 | F22: 0 | G22: 0 | H22: 0 | I22: 0 | J22: 0 | K22: 0 | L22: 0 | M22: 0
A23: Deposit growth rate (% per year, ex-stress) | B23: Y10+ stress: CLC breach forces -45% withdrawal. | C23: 0.03 | D23: 0.04 | E23: 0.04 | F23: 0.03 | G23: -0.06 | H23: 0.08 | I23: 0.06 | J23: 0.05 | K23: 0.05 | L23: 0.02 | M23: -0.45
A24: Direct Treasury Y0 ($B) | B24: TIC-visible sovereign Treasury holdings. | C24: 20 | D24: 0 | E24: 0 | F24: 0 | G24: 0 | H24: 0 | I24: 0 | J24: 0 | K24: 0 | L24: 0 | M24: 0
A25: Treasury growth rate (% per year, ex-stress) | B25: Y10+ stress: forced sale alongside deposit withdrawal. | C25: 0.02 | D25: 0.03 | E25: 0.03 | F25: 0.02 | G25: -0.04 | H25: 0.06 | I25: 0.05 | J25: 0.04 | K25: 0.04 | L25: 0.02 | M25: -0.47
A26: Gold reserves Y0 ($B) | C26: 25 | D26: 0 | E26: 0 | F26: 0 | G26: 0 | H26: 0 | I26: 0 | J26: 0 | K26: 0 | L26: 0 | M26: 0
A27: Gold growth rate (% per year, normal)
A28: Gold liquidation fraction (stress year Y10+) | C28: 0 | D28: 0 | E28: 0 | F28: 0 | G28: 0 | H28: 0 | I28: 0 | J28: 0 | K28: 0 | L28: 0 | M28: 0.6
A29: Gold proceeds routed to GBC deposit (% of proceeds) | C29: 0 | D29: 0 | E29: 0 | F29: 0 | G29: 0 | H29: 0 | I29: 0 | J29: 0 | K29: 0 | L29: 0 | M29: 0.8
A30: GLOBALBANKCO ASSUMPTIONS
A31: Other loans and advances Y0 ($B) | C31: 25 | D31: 0 | E31: 0 | F31: 0 | G31: 0 | H31: 0 | I31: 0 | J31: 0 | K31: 0 | L31: 0 | M31: 0
A32: Other loans growth rate | C32: 0.03 | D32: 0.04 | E32: 0.04 | F32: -0.05 | G32: 0.05 | H32: 0.04 | I32: 0.04 | J32: 0.03 | K32: 0.02 | L32: -0.1 | M32: -0.15
A33: SLR minimum (%) | B33: US GSIB SLR minimum 5%. Perera (Feb 2026): SLR reform Nov 2025 changes denominator. | C33: 0.05 | D33: 0.05 | E33: 0.05 | F33: 0.05 | G33: 0.05 | H33: 0.05 | I33: 0.05 | J33: 0.05 | K33: 0.05 | L33: 0.05 | M33: 0.05
A34: SLR constraint threshold (constrained if below, %)
A35: Repo spread (GlobalBankCo to RepoCo, bps) | B35: Stylized. Repo spread widens in stress. | C35: 5 | D35: 5 | E35: 5 | F35: 5 | G35: 8 | H35: 8 | I35: 6 | J35: 6 | K35: 6 | L35: 6 | M35: 6
A37: REPOCO ASSUMPTIONS
A38: Repo spread (RepoCo to HedgeCo, bps)
A39: FICC novation fraction (% of repo book off-balance-sheet) | B39: Barth-Beltran: TVR=22.9% → novation fraction=1-0.229=0.771. TVR varies with collateral velocity and novation intensity (calibrated at 2025 Barth-Beltran vintage). | C39: 0.771 | D39: 0.3 | E39: 0.35 | F39: 0.4 | G39: 0.5 | H39: 0.55 | I39: 0.7 | J39: 0.72 | K39: 0.75 | L39: 0.76 | M39: 0.76
A41: HEDGECO ASSUMPTIONS | B41: Barth-Beltran calibration: $1.85T cash / $1.05T CFTC futures = 1.76x. Was 1.3 (uncalibrated). | C41: 1.76 | D41: 1.3 | E41: 1.3 | F41: 1.3 | G41: 1.3 | H41: 1.3 | I41: 1.3 | J41: 1.3 | K41: 1.3 | L41: 1.3 | M41: 1.3
A42: Futures short notional as multiple of cash long
A43: HedgeCo equity ($B) | B43: Equity base. Leverage = gross exposure / equity. | C43: 10 | D43: 10 | E43: 10 | F43: 10 | G43: 10 | H43: 10 | I43: 10 | J43: 10 | K43: 10 | L43: 10 | M43: 10
A45: FEDCO ASSUMPTIONS
A46: Treasury holdings Y0 ($B) | B46: Real-world: Fed peaked $5.7T Treasuries Apr 2022. QT since. | C46: 64 | D46: 0 | E46: 0 | F46: 0 | G46: 0 | H46: 0 | I46: 0 | J46: 0 | K46: 0 | L46: 0 | M46: 0
A47: Treasury QE/QT per year ($B, positive=QE, negative=QT) | B47: Y4/2020: emergency QE. Y5-Y9: QT. Y10+ stress: emergency absorption. | C47: 8 | D47: 15 | E47: 15 | F47: 20 | G47: 80 | H47: -8 | I47: -20 | J47: -25 | K47: -15 | L47: -8 | M47: 0
A48: GDP ceiling for BS expansion (%) | B48: Stylized ceiling. At 38-40% GDP: productive base constraint binding. Part II hard threshold. Perera (Feb 2026). | C48: 1.3 | D48: 1.3 | E48: 1.3 | F48: 1.3 | G48: 1.3 | H48: 1.3 | I48: 1.3 | J48: 1.3 | K48: 1.3 | L48: 1.3 | M48: 1.3
A49: Stress absorption (Y10+ Treasury purchase, $B) | B49: Emergency purchase to stabilize yield spike from HedgeCo unwind. Range $150B-$1,450B depending on unwind scale. $400B = partial. | C49: 0 | D49: 0 | E49: 0 | F49: 0 | G49: 0 | H49: 0 | I49: 0 | J49: 0 | K49: 0 | L49: 0 | M49: 45
A51: GOVCO ASSUMPTIONS
A52: GovCo bonds outstanding Y0 ($B) | C52: 380 | D52: 380 | E52: 380 | F52: 380 | G52: 380 | H52: 380 | I52: 380 | J52: 380 | K52: 380 | L52: 380 | M52: 380
A53: Domestic holder share of bonds (%) | C53: 0.6 | D53: 0.6 | E53: 0.6 | F53: 0.6 | G53: 0.6 | H53: 0.6 | I53: 0.6 | J53: 0.6 | K53: 0.6 | L53: 0.6 | M53: 0.6
A54: Interest rate on GovCo bonds (%) | C54: 0.04 | D54: 0.04 | E54: 0.04 | F54: 0.04 | G54: 0.04 | H54: 0.04 | I54: 0.04 | J54: 0.04 | K54: 0.04 | L54: 0.04 | M54: 0.04
A55: Tax revenue Y0 ($B) | C55: 260 | D55: 260 | E55: 260 | F55: 260 | G55: 260 | H55: 260 | I55: 260 | J55: 260 | K55: 260 | L55: 260 | M55: 260
A56: Govt spending Y0 ($B) | C56: 300 | D56: 300 | E56: 300 | F56: 300 | G56: 300 | H56: 300 | I56: 300 | J56: 300 | K56: 300 | L56: 300 | M56: 300
A58: INTERNAL SECTOR ASSUMPTIONS (Part IV)
A59: ManuCo wage bill Y0 ($B) | B59: Stylized. Real-world US mfg wages ~$900B. Declining share of GDP. | C59: 80 | D59: 79 | E59: 78 | F59: 77 | G59: 70 | H59: 72 | I59: 73 | J59: 72 | K59: 71 | L59: 69 | M59: 65
A60: ManuCo wage growth rate | B60: Declining as capital routes to FinServCo not ManuCo. | C60: 0 | D60: -0.01 | E60: -0.01 | F60: -0.01 | G60: -0.09 | H60: 0.03 | I60: 0.01 | J60: -0.01 | K60: -0.01 | L60: -0.03 | M60: -0.06
A61: ProdServiceCo wage bill Y0 ($B) | B61: Growing. Tech sector wages rising as equity-funded investment expands. | C61: 60 | D61: 63 | E61: 67 | F61: 72 | G61: 68 | H61: 78 | I61: 88 | J61: 96 | K61: 105 | L61: 112 | M61: 108
A62: ProdServiceCo wage growth rate | B62: Positive. TFP gains + equity funding sustain investment. | C62: 0 | D62: 0.05 | E62: 0.06 | F62: 0.07 | G62: -0.06 | H62: 0.15 | I62: 0.13 | J62: 0.09 | K62: 0.09 | L62: 0.07 | M62: -0.04
A63: FinServCo wage bill Y0 ($B) | B63: Growing as FISIM income expands with each absorption cycle. | C63: 20 | D63: 21 | E63: 22 | F63: 24 | G63: 22 | H63: 25 | I63: 28 | J63: 30 | K63: 33 | L63: 35 | M63: 32
A64: FinServCo wage growth rate | B64: Grows with each FedCo absorption episode -- FISIM income up. | C64: 0 | D64: 0.05 | E64: 0.05 | F64: 0.09 | G64: -0.08 | H64: 0.14 | I64: 0.12 | J64: 0.07 | K64: 0.1 | L64: 0.06 | M64: -0.09
A65: ManuCo investment share of GDP (%) | B65: Real-world: mfg investment ~8% GDP 2019, declining. | C65: 0.1 | D65: 0.098 | E65: 0.096 | F65: 0.094 | G65: 0.085 | H65: 0.088 | I65: 0.086 | J65: 0.084 | K65: 0.082 | L65: 0.08 | M65: 0.075
A66: ProdServiceCo P/E ratio (equity valuation multiple) | B66: Rises as FedCo discount rate suppressed. Falls in stress. | C66: 22 | D66: 24 | E66: 26 | F66: 28 | G66: 24 | H66: 35 | I66: 38 | J66: 32 | K66: 30 | L66: 28 | M66: 18
A67: FinServCo LP stake in HedgeCo (% of HedgeCo equity) | B67: Pension funds as LPs. Stress = LP losses. | C67: 0.3 | D67: 0.3 | E67: 0.32 | F67: 0.32 | G67: 0.3 | H67: 0.35 | I67: 0.38 | J67: 0.4 | K67: 0.4 | L67: 0.4 | M67: 0.4
A68: AmeriBankCo domestic repo to FinServCo Y0 ($B) | B68: FedCo reserves -> AmeriBankCo -> repo -> FinServCo. SLR valve. | C68: 50 | D68: 0 | E68: 0 | F68: 0 | G68: 0 | H68: 0 | I68: 0 | J68: 0 | K68: 0 | L68: 0 | M68: 0
A69: AmeriBankCo domestic repo growth rate | B69: Grows with each FedCo reserve creation episode. | C69: 0 | D69: 0.06 | E69: 0.07 | F69: 0.08 | G69: 0.25 | H69: 0.2 | I69: 0.15 | J69: 0.1 | K69: 0.08 | L69: 0.05 | M69: 0.15
A70: HedgeCo TSY Y0 anchor ($B) -- for FinServCo seller formula | B70: Fixed Y0 reference. FinServCo TSY shrinks by (HedgeCo_current - this). | C70: =GlobalBankCo!C4 -> 80 | D70: =GlobalBankCo!C4 -> 80 | E70: =GlobalBankCo!C4 -> 80 | F70: =GlobalBankCo!C4 -> 80 | G70: =GlobalBankCo!C4 -> 80 | H70: =GlobalBankCo!C4 -> 80 | I70: =GlobalBankCo!C4 -> 80 | J70: =GlobalBankCo!C4 -> 80 | K70: =GlobalBankCo!C4 -> 80 | L70: =GlobalBankCo!C4 -> 80 | M70: =GlobalBankCo!C4 -> 80
A71: HouseholdCo direct equity in ProdServiceCo (fraction of HH net worth) | B71: HH direct equity holdings (401k, retail). ~20% of net worth. | C71: 0.2 | D71: 0.2 | E71: 0.2 | F71: 0.2 | G71: 0.2 | H71: 0.2 | I71: 0.2 | J71: 0.2 | K71: 0.2 | L71: 0.2 | M71: 0.2
A74: PRIVATE CREDIT PARAMETERS
A75: PrivCred Y0 ($B) — FinServCo loans to ProdServiceCo | B75: Illiquid 5-7yr. Real-world Blue Owl flagship ~$36B. Toy model scaled. | C75: 20 | D75: 22 | E75: 25 | F75: 28 | G75: 30 | H75: 35 | I75: 40 | J75: 45 | K75: 50 | L75: 55 | M75: 50
A76: PrivCred growth rate (annual) | B76: Grows as AmeriBankCo routes reserves to FinServCo. | C76: 0 | D76: 0.1 | E76: 0.14 | F76: 0.12 | G76: 0.17 | H76: 0.14 | I76: 0.14 | J76: 0.11 | K76: 0.1 | L76: 0.1 | M76: -0.09
A77: Callable fraction of pension obligations | B77: Blue Owl: 22% requested Q1 2026. Grows as liquidity concerns rise. | C77: 0.05 | D77: 0.05 | E77: 0.06 | F77: 0.06 | G77: 0.1 | H77: 0.08 | I77: 0.08 | J77: 0.1 | K77: 0.12 | L77: 0.15 | M77: 0.22
A78: ProdServiceCo default shock (% of PrivCred book, stress only) | B78: Exogenous shock. AI/software stress. Y10+: 15% of PC book defaults. | C78: 0 | D78: 0 | E78: 0 | F78: 0 | G78: 0 | H78: 0 | I78: 0 | J78: 0 | K78: 0 | L78: 0 | M78: 0.15
A80: SELLER CHAIN PARAMETERS
A81: GovCo bonds Y0 anchor (for reallocation delta tracking) | B81: Fixed reference for reallocation. = ASSUMPTIONS!C52. Reallocation = within-year ownership transfer. | C81: =ASSUMPTIONS!C52 -> 380 | D81: =ASSUMPTIONS!C52 -> 380 | E81: =ASSUMPTIONS!C52 -> 380 | F81: =ASSUMPTIONS!C52 -> 380 | G81: =ASSUMPTIONS!C52 -> 380 | H81: =ASSUMPTIONS!C52 -> 380 | I81: =ASSUMPTIONS!C52 -> 380 | J81: =ASSUMPTIONS!C52 -> 380 | K81: =ASSUMPTIONS!C52 -> 380 | L81: =ASSUMPTIONS!C52 -> 380 | M81: =ASSUMPTIONS!C52 -> 380
A83: SELLING SENSITIVITY WEIGHTS (Point 1 fix — interior solution)
A84: FinServCo selling weight (yield-sensitive — duration mismatch) | B84: Most sensitive. Pension duration mismatch fires first on yield spike. Weight ∝ sensitivity × balance sheet stress. | C84: 0.5 | D84: 0.5 | E84: 0.5 | F84: 0.5 | G84: 0.5 | H84: 0.5 | I84: 0.5 | J84: 0.5 | K84: 0.5 | L84: 0.5 | M84: 0.5
A85: AmeriBankCo selling weight (medium — LCR buffer management) | B85: Sells as LCR buffer erodes. Constrained by SLR. Medium sensitivity. | C85: 0.25 | D85: 0.25 | E85: 0.25 | F85: 0.25 | G85: 0.25 | H85: 0.25 | I85: 0.25 | J85: 0.25 | K85: 0.25 | L85: 0.25 | M85: 0.25
A86: Official sector selling weight (least sensitive — political + reserve mgmt) | B86: Sells last. Political constraints on reserve drawdown. Coordination costs. | C86: 0.25 | D86: 0.25 | E86: 0.25 | F86: 0.25 | G86: 0.25 | H86: 0.25 | I86: 0.25 | J86: 0.25 | K86: 0.25 | L86: 0.25 | M86: 0.25
A87: Yield spike sensitivity (bps per $100B net selling) | B87: Price impact function. Higher = more stress per unit of selling. | C87: 8 | D87: 8 | E87: 8 | F87: 8 | G87: 8 | H87: 8 | I87: 8 | J87: 8 | K87: 8 | L87: 8 | M87: 12
A89: DURATION MIX PARAMETERS (GovCo bill-vs-bond toggle)
A90: Duration mix [0=bill-heavy, 1=bond-heavy] | B90: Treasury issuance composition. 0=pure bills (no basis trade collateral). 1=pure bonds (full basis trade collateral). Currently bond-heavy. Stress: Treasury might shift to bills. | C90: 1 | D90: 1 | E90: 1 | F90: 1 | G90: 1 | H90: 1 | I90: 1 | J90: 1 | K90: 1 | L90: 0.6 | M90: 0.4
A91: Effective collateral supply = HedgeCo_position × duration_mix | B91: Amount of bond collateral available for basis trade. Falls when Treasury shifts to bills. Compresses HedgeCo spread and BTAR. | C91: =HedgeCo!C4*ASSUMPTIONS!C90 -> 80 | D91: =HedgeCo!D4*ASSUMPTIONS!D90 -> 104.555 | E91: =HedgeCo!E4*ASSUMPTIONS!E90 -> 145.9503 | F91: =HedgeCo!F4*ASSUMPTIONS!F90 -> 196.90748 | G91: =HedgeCo!G4*ASSUMPTIONS!G90 -> 242.17 | H91: =HedgeCo!H4*ASSUMPTIONS!H90 -> 305.06014 | I91: =HedgeCo!I4*ASSUMPTIONS!I90 -> 437.86861 | J91: =HedgeCo!J4*ASSUMPTIONS!J90 -> 573.64709 | ... M91: =HedgeCo!M4*ASSUMPTIONS!M90 -> 409.03294
A93: PRICE FEEDBACK LOOP PARAMETERS
A94: Base yield (%) — Treasury 10yr at Y0 | B94: Baseline yield. Price feedback = yield - base_yield when selling occurs. | C94: 0.042 | D94: 0.042 | E94: 0.042 | F94: 0.042 | G94: 0.042 | H94: 0.042 | I94: 0.042 | J94: 0.042 | K94: 0.042 | L94: 0.055 | M94: 0.075
A95: Yield sensitivity (bps per unit net selling / absorption) | B95: yield = base + sensitivity × (net_selling / absorption_cap). 8bps per $100B net selling / $150B absorption = 0.053 per unit. | C95: 0.053 | D95: 0.053 | E95: 0.053 | F95: 0.053 | G95: 0.053 | H95: 0.053 | I95: 0.053 | J95: 0.053 | K95: 0.053 | L95: 0.053 | M95: 0.053
A96: FinServCo selling elasticity to yield | B96: How much FinServCo increases selling per unit yield rise. High: pension duration mismatch amplifies urgency. | C96: 2 | D96: 2 | E96: 2 | F96: 2 | G96: 2 | H96: 2 | I96: 2 | J96: 2 | K96: 2 | L96: 2 | M96: 2
A97: AmeriBankCo selling elasticity to yield | B97: Medium: LCR buffer management is yield-sensitive but constrained by regulatory floor. | C97: 1 | D97: 1 | E97: 1 | F97: 1 | G97: 1 | H97: 1 | I97: 1 | J97: 1 | K97: 1 | L97: 1 | M97: 1
A98: Official sector selling elasticity to yield | B98: Low: political constraints, coordination costs, reserve management mandates slow response. | C98: 0.3 | D98: 0.3 | E98: 0.3 | F98: 0.3 | G98: 0.3 | H98: 0.3 | I98: 0.3 | J98: 0.3 | K98: 0.3 | L98: 0.3 | M98: 0.3
A99: Yield threshold for GovCo bill shift (%) | B99: When yield > threshold, GovCo shifts issuance to bills (shorter duration, less basis trade collateral). | C99: 0.055 | D99: 0.055 | E99: 0.055 | F99: 0.055 | G99: 0.055 | H99: 0.055 | I99: 0.055 | J99: 0.055 | K99: 0.055 | L99: 0.055 | M99: 0.055
A100: Duration mix when yield > threshold [0=bills, 1=bonds] | B100: Treasury bill-heavy mix when yield exceeds threshold. Compresses basis trade collateral supply. | C100: 0.4 | D100: 0.4 | E100: 0.4 | F100: 0.4 | G100: 0.4 | H100: 0.4 | I100: 0.4 | J100: 0.4 | K100: 0.4 | L100: 0.4 | M100: 0.4
A101: Funding cost shock when FinServCo gate ON (% increment) | B101: Confidence spillover: gate fires → investors reprice similar funds → GlobalBankCo wholesale funding cost rises. | C101: 0 | D101: 0 | E101: 0 | F101: 0 | G101: 0 | H101: 0 | I101: 0 | J101: 0 | K101: 0 | L101: 0.005 | M101: 0.015
A103: HORMUZ / COMMODITY SHOCK — TWO-PHASE STRUCTURE
A104: Hormuz shock phase [0=normal, 1=Phase1 closed, 2=Phase2 reroute] | B104: Two-phase Korea analogy. Phase1=Hormuz closed (import collapses, false stabilization). Phase2=alternate routing at higher cost (real hit arrives). | C104: 0 | D104: 0 | E104: 0 | F104: 0 | G104: 0 | H104: 0 | I104: 0 | J104: 0 | K104: 1 | L104: 2 | M104: 2
A105: Phase 2 lag (quarters) — false stabilization window | B105: How long Phase 1 false stabilization lasts before Phase 2 hits. Korea=1Q, India=2Q, Japan=3-4Q (longer supply contracts). Setser empirical: oil shock → FX delay 3-4 quarters. | C105: 3 | D105: 3 | E105: 3 | F105: 3 | G105: 3 | H105: 3 | I105: 3 | J105: 3 | K105: 3 | L105: 3 | M105: 3
A106: Oil/LNG import volume index [1.0=normal, 0=Hormuz closed, 0.4=alternate routes] | B106: Endogenous: Phase1=0 (nothing transits Hormuz). Phase2=0.4 (partial reroute via Cape). Y10+=0.6 (further rerouting). Volume × price = import bill. | C106: 1 | D106: 1 | E106: 1 | F106: 1 | G106: 1 | H106: 1 | I106: 1 | J106: 1 | K106: 0 | L106: 0.4 | M106: 0.6
A107: Oil price index [1.0=normal, spikes Phase1, stays elevated Phase2] | B107: Phase1: price spikes as global supply drops 2.5% (Hormuz chart). Phase2: price moderates but stays elevated as rerouting adds cost. Calibrated to Hormuz = largest disruption in history. | C107: 1 | D107: 1 | E107: 1 | F107: 1 | G107: 1 | H107: 1 | I107: 1 | J107: 1 | K107: 2.8 | L107: 2.2 | M107: 1.8
A108: Japan export revenue ($B/yr) — manufacturing + services, not oil-dependent | B108: Japan exports: autos, electronics, machinery. Not directly affected by Hormuz. Mild demand shock in Phase2 as global growth slows. | C108: 800 | D108: 800 | E108: 810 | F108: 820 | G108: 830 | H108: 840 | I108: 850 | J108: 860 | K108: 860 | L108: 840 | M108: 830
A109: Japan oil import bill ($B/yr) = volume × price × base_bill | B109: Base bill = 150B/yr (Japan imports ~3mbd × $100/bbl). Phase1: volume=0 → bill=0 (false stabilization — CA surplus spikes). Phase2: volume=0.4, price=2.2 → bill=0.4×2.2×150=132B (higher than base!). | C109: 150 | D109: 150 | E109: 153 | F109: 156 | G109: 159 | H109: 162 | I109: 165 | J109: 168 | K109: 0 | L109: 132 | M109: 162
A110: CommodityCo export volume index [1.0=normal, 0=Hormuz closed, 0.4=reroute] | B110: Mirror of Japan oil import volume. CommodityCo cannot export through Hormuz in Phase1. Phase2: partial reroute but at higher transport cost. | C110: 1 | D110: 1 | E110: 1 | F110: 1 | G110: 1 | H110: 1 | I110: 1 | J110: 1 | K110: 0 | L110: 0.4 | M110: 0.6
A111: CommodityCo export price index [1.0=normal] — same as oil price | B111: CommodityCo receives higher price in Phase2 (scarcity premium). Phase1: cannot sell at any price (blocked). Phase2: sells at 2.2× normal. | C111: 1 | D111: 1 | E111: 1 | F111: 1 | G111: 1 | H111: 1 | I111: 1 | J111: 1 | K111: 0 | L111: 2.2 | M111: 1.8
A113: SRF / FIMA / DEBT CEILING PARAMETERS
A114: SRF administered rate (%) — Fed price ceiling on repo | B114: Standing Repo Facility rate. Current: 4.00%. When yield_stress > SRF_rate, Fed absorbs excess demand. yield_effective = MIN(yield_stress, SRF_rate). Real: $26B active April 2026 → toy scale 0.24B. | C114: 0.04 | D114: 0.04 | E114: 0.04 | F114: 0.04 | G114: 0.04 | H114: 0.04 | I114: 0.04 | J114: 0.04 | K114: 0.04 | L114: 0.04 | M114: 0.04
A115: SRF sensitivity (absorption per unit yield gap, $B) | B115: SRF_absorption = SRF_gap × SRF_sensitivity. Calibrated: $26B at ~15bps gap → sensitivity ≈ 1.7B per bp. Toy scale: 0.24B / 0.15bps = 1.6B per unit gap. | C115: 1.6 | D115: 1.6 | E115: 1.6 | F115: 1.6 | G115: 1.6 | H115: 1.6 | I115: 1.6 | J115: 1.6 | K115: 1.6 | L115: 1.6 | M115: 1.6
...

Sheet REALWORLD_DATA
A1: REAL-WORLD CALIBRATION DATA | Part IV: AmeriCo Internal Sectors | 2019-2024
A2: Sources: BEA NIPA, BLS, Fed Z.1, FRED. All values are annual. Used to validate toy model stylized trajectories.
A4: Measure | B4: Toy Model Analog | C4: Source / FRED Series | D4: 2019 | E4: 2020 | F4: 2021 | G4: 2022 | H4: 2023 | I4: 2024
A5: 1. WAGE SHARE / LABOR INCOME → HouseholdCo thesis: wage share falling as FinServCo grows
A6: Wage & salary share of GDI (%) | B6: HouseholdCo wage share | C6: BEA NIPA Table 1.10 / FRED W270RE1A156NBEA | D6: 45.4 | E6: 44.6 | F6: 45.2 | G6: 44.8 | H6: 45.1 | I6: 44.9
A7: ↳ Compensation of employees (wages+salaries) as % of Gross Domestic Income. Stable but structurally below 50%. Pre-2000 was ~51-52%.
A8: Nonfarm business labor share (BLS, index 2012=100) | B8: HouseholdCo wage share | C8: BLS PRS85006173 / FRED LABSHPUSA156NRUG | D8: 98 | E8: 101.5 | F8: 100.2 | G8: 97.8 | H8: 98.5 | I8: 97.9
A9: ↳ Structural decline from ~105 in 2000. Each FedCo absorption episode sees temporary recovery then drift lower.
A10: Manufacturing compensation ($B, annual) | B10: ManuCo wage bill | C10: BEA NIPA / BLS QCEW manufacturing | D10: 920 | E10: 870 | F10: 940 | G10: 1010 | H10: 1020 | I10: 1040
A11: ↳ Real-world ~$900-1,040B. Growing nominally but shrinking as share of GDP. 2020 COVID dip then recovery driven by CHIPS Act.
A12: Finance/insurance compensation ($B, annual) | B12: FinServCo wage bill | C12: BEA GDP by Industry / FRED | D12: 510 | E12: 520 | F12: 600 | G12: 650 | H12: 680 | I12: 710
A13: ↳ Financial sector wages growing ~5-7%/yr. Faster than mfg. FISIM income expansion drives compensation growth.
A14: Info tech sector compensation ($B, annual) | B14: ProdServiceCo wage bill | C14: BEA GDP by Industry | D14: 680 | E14: 710 | F14: 820 | G14: 890 | H14: 880 | I14: 920
A15: ↳ Tech sector wages up ~35% 2019-2024. AI/cloud buildout. Positive but not sufficient to offset mfg stagnation vs FISIM growth.
A17: 2. MANUFACTURING INVESTMENT → ManuCo thesis: investment crowded out as return differential widens
A18: Mfg structures investment ($B nominal) | B18: ManuCo capital investment | C18: BEA Table 5.4.5 / FRED C307RC1A027NBEA | D18: 73 | E18: 68 | F18: 75 | G18: 104 | H18: 157 | I18: 235
A19: ↳ CHIPS Act + IRA drove surge 2022-2024. BUT: concentrated in semiconductors/batteries. Broader mfg share still falling. 2024 = $234.8B.
A20: Mfg investment / total private fixed investment (%) | B20: ManuCo investment share | C20: BEA Table 5.4.5 derived | D20: 3.4 | E20: 3.3 | F20: 3.1 | G20: 4.1 | H20: 5.4 | I20: 6.8
A21: ↳ Share rising from CHIPS/IRA but from very low base. IP/software investment (ProdServiceCo) = 31% of total vs mfg structures = 7%.
A22: IP products investment / private fixed investment (%) | B22: ProdServiceCo investment share | C22: BEA / Richmond Fed | D22: 30 | E22: 30.5 | F22: 31 | G22: 31 | H22: 31.3 | I22: 32
A23: ↳ IP (software+R&D+entertainment) = 31.3% of private fixed investment Q1 2024. Grows 3-4x faster than mfg structures.
A25: 3. TECH/FINSERV VALUATION → ProdServiceCo thesis: equity rises with FedCo discount rate suppression
A26: IT sector share of S&P 500 market cap (%) | B26: ProdServiceCo equity / GDP analog | C26: S&P Dow Jones / Bloomberg | D26: 23.2 | E26: 27.6 | F26: 28.8 | G26: 24.1 | H26: 29.5 | I26: 34
A27: ↳ IT + comm services = ~44% of S&P 500 end-2024. Rose from 33% in 2019. ~2x market cap vs 5yr avg revenue growth. Valuation re-rate driven by rate suppression.
A28: S&P 500 IT sector P/E (trailing) | B28: ProdServiceCo P/E ratio | C28: FactSet / Bloomberg | D28: 26 | E28: 40 | F28: 34 | G28: 22 | H28: 31 | I28: 33
A29: ↳ P/E compressed 2022 when Fed raised rates (22x). Expanded 2020-21 with zero rates (40x). Confirms DCF identity: FedCo rate -> ProdServiceCo valuation.
A30: Total US stock market cap / GDP (Buffett indicator, %) | B30: Financial assets / productive base | C30: Fed Z.1 / FRED | D30: 152 | E30: 195 | F30: 222 | G30: 155 | H30: 180 | I30: 201
A31: ↳ 195% peak 2020 (COVID QE). 222% 2021. Reset 2022 with rate hikes. Re-expanded 2024. Each FedCo absorption cycle visible in ratio.
A33: 4. FINANCIAL SECTOR VALUE-ADD / FISIM → FinServCo thesis: FISIM income grows without productive base expansion
A34: Finance & insurance value added / GDP (%) | B34: FinServCo FISIM share of GDP | C34: BEA GDP by Industry Table | D34: 7.5 | E34: 8.1 | F34: 8.4 | G34: 8.1 | H34: 8.3 | I34: 8.5
A35: ↳ Financial sector value added = 8.5% of GDP 2024, up from 4% in 1980. Most of growth is FISIM (imputed intermediation margin). Not productive output.
A36: Domestic financial sector total assets / GDP | B36: FinServCo balance sheet / GDP | C36: Fed Z.1 / FRED DDDI06USA156NWDB | D36: 430 | E36: 490 | F36: 510 | G36: 450 | H36: 470 | I36: 490
A37: ↳ Financial sector assets ~4.9x GDP. Each basis point of spread income on $90T+ gross financial assets = ~$90B measured GDP. Pure intermediation counted as value-add.
A39: 5. HOUSEHOLD DEBT & WEALTH DIVERGENCE → HouseholdCo thesis: nominal wealth up, real backing flat
A40: Household net worth ($T) | B40: HouseholdCo total assets | C40: Fed Z.1 Table B.101 | D40: 118.7 | E40: 130.2 | F40: 150.3 | G40: 138.4 | H40: 151 | I40: 169.4
A41: ↳ Net worth $169.4T Q4 2024 (Fed Z.1). Up 43% from 2019. Almost entirely driven by equity + housing price appreciation, not wage accumulation.
A42: Household mortgage debt ($T) | B42: HouseholdCo mortgage liabilities | C42: Fed Z.1 Table D.3 | D42: 10.7 | E42: 10.9 | F42: 11.5 | G42: 12.3 | H42: 12.8 | I42: 13.1
A43: ↳ Mortgage debt $13.1T 2024. Household debt $20.2T total Q4 2024 (Fed Z.1). Growing alongside nominal wealth but as % of wages rising.
A44: Household debt / disposable personal income (%) | B44: HouseholdCo debt / wage income | C44: Fed Z.1 / BEA | D44: 95 | E44: 97 | F44: 90 | G44: 93 | H44: 97 | I44: 99
A45: ↳ Debt burden ~97-99% of DPI. Fell briefly 2021 on stimulus income. Back to trend. Confirms HouseholdCo debt/wage rising.
A47: 6. AMERIBANKCO REPO ROUTING → AmeriBankCo thesis: reserves route to FinServCo not productive lending
A48: Fed reserve balances at banks ($T) | B48: AmeriBankCo FedCo reserves | C48: FRED WRESBAL | D48: 1.7 | E48: 3.2 | F48: 4.1 | G48: 3.1 | H48: 3.3 | I48: 3.3
A49: ↳ Reserve glut 2020-21 from QE. Banks could not deploy productively. SLR constraint: routed to repo. 2022 QT drained but returned via bank stress/BTFP.
A50: FICC sponsored repo volume ($T, avg daily) | B50: AmeriBankCo repo routing intensity | C50: DTCC / OFR | D50: 0.9 | E50: 1.1 | F50: 1.4 | G50: 1.6 | H50: 2 | I50: 2.2
A51: ↳ DTCC sponsored repo: $2.2T daily average 2024. Up 2.4x from 2019. Grows with each reserve creation episode. Confirmed: SLR valve routing.
A52: Bank C&I loans / total bank assets (%) | B52: AmeriBankCo productive lending share | C52: Fed H.8 / FRED | D52: 11.2 | E52: 10.8 | F52: 9.9 | G52: 11.1 | H52: 10.8 | I52: 10.5
A53: ↳ Commercial & industrial loans falling as share of bank assets. Repo + securities growing faster. Confirms AmeriBankCo routing intensity rising.
A55: KEY THESIS VALIDATION SUMMARY
A56: ✓ CONFIRMED | B56: Wage share structurally below 50% and flat/falling. FinServCo compensation growing faster than ManuCo.
A57: ✓ CONFIRMED | B57: ProdServiceCo equity valuation rose and fell with FedCo rate cycle (2020-21 up, 2022 down, 2023-24 up again).
A58: ✓ CONFIRMED | B58: FICC sponsored repo volume 2.4x since 2019. AmeriBankCo routing reserves to FinServCo confirmed.
A59: ✓ CONFIRMED | B59: HH net worth +43% since 2019 on asset prices, not wages. Debt/income ratio rising back to 99%.
A60: ⚠ PARTIAL | B60: ManuCo investment share: CHIPS Act surge 2022-2024 complicates clean decline story. Concentration in semis not broad mfg. Sector-level PWT needed.
A61: ⚠ PARTIAL | B61: FISIM series: BEA GDP by industry shows finance = 8.5% but does not separate FISIM from genuine intermediation. BEA FISIM adjustment series (NIPA Table 7.4) needed for clean number.
A62: ✗ NOT YET | B62: FinServCo LP stake in HedgeCo: SEC Form PF data not public at required granularity. Barth-Beltran is best proxy. OFR cleared repo data requires agreement.

Sheet AmeriCo
A1: AmeriCo | Reserve Issuer | Treasury Issuer | Productive Base
A2: Account / Line Item | B2: Notes / Source | C2: Y0 | D2: Y1 | E2: Y2 | F2: Y3 | G2: Y4 | H2: Y5 | I2: Y6 | J2: Y7 | K2: Y8 | L2: Y9 | M2: Y10+ Stress
A3: ASSETS
A4: Productive capital K_real ($B) | B4: FISIM-adjusted. κ divergence theorem: κ_paper rises faster than κ_real as FISIM contamination grows. | C4: =ASSUMPTIONS!C4 -> 300 | D4: =ASSUMPTIONS!D4 -> 310 | E4: =ASSUMPTIONS!E4 -> 325 | F4: =ASSUMPTIONS!F4 -> 340 | G4: =ASSUMPTIONS!G4 -> 330 | H4: =ASSUMPTIONS!H4 -> 345 | I4: =ASSUMPTIONS!I4 -> 365 | J4: =ASSUMPTIONS!J4 -> 380 | ... M4: =ASSUMPTIONS!M4 -> 400
A5: Outward FDI ($B) | B5: Channel One legacy: AmeriCo lends long via FDI while borrowing short via reserve accumulation (Kindleberger 1966). | C5: 200 | D5: =C5*(1+0.02) -> 204 | E5: =D5*(1+0.02) -> 208.08 | F5: =E5*(1+0.02) -> 212.2416 | G5: =F5*(1+0.02) -> 216.48643 | H5: =G5*(1+0.02) -> 220.81616 | I5: =H5*(1+0.02) -> 225.23248 | J5: =I5*(1+0.02) -> 229.73713 | K5: =J5*(1+0.02) -> 234.33188 | ... M5: =L5*(1+0.02) -> 243.79888
A6: Other foreign claims ($B) | C6: 80 | D6: =C6*1.02 -> 81.6 | E6: =D6*1.02 -> 83.232 | F6: =E6*1.02 -> 84.89664 | G6: =F6*1.02 -> 86.594573 | H6: =G6*1.02 -> 88.326464 | I6: =H6*1.02 -> 90.092994 | J6: =I6*1.02 -> 91.894853 | K6: =J6*1.02 -> 93.73275 | ... M6: =L6*1.02 -> 97.519554
A7: TOTAL ASSETS | C7: =SUM(C4:C6) -> 580 | D7: =SUM(D4:D6) -> 595.6 | E7: =SUM(E4:E6) -> 616.312 | F7: =SUM(F4:F6) -> 637.13824 | G7: =SUM(G4:G6) -> 633.081 | H7: =SUM(H4:H6) -> 654.14262 | I7: =SUM(I4:I6) -> 680.32548 | J7: =SUM(J4:J6) -> 701.63199 | ... M7: =SUM(M4:M6) -> 741.31844
A9: LIABILITIES
A10: Official reserve liabilities ($B) [SELLER 3: sold after FinServCo + AmeriBankCo exhausted] | B10: Foreign CB holdings. Third seller in chain. Drains after HC_delta > 90B (FinServCo 60 + AmeriBankCo 30 exhausted). Represents reserve drawdown. | C10: =MAX(0,100-MIN(100,MAX(0,(HedgeCo!C4-ASSUMPTIONS!C70)*ASSUMPTIONS!C86*4))) -> 100 | D10: =MAX(0,100-MIN(100,MAX(0,(HedgeCo!D4-ASSUMPTIONS!C70)*ASSUMPTIONS!C86*4))) -> 75.445 | E10: =MAX(0,100-MIN(100,MAX(0,(HedgeCo!E4-ASSUMPTIONS!C70)*ASSUMPTIONS!C86*4))) -> 34.0497 | F10: =MAX(0,100-MIN(100,MAX(0,(HedgeCo!F4-ASSUMPTIONS!C70)*ASSUMPTIONS!C86*4))) -> 0 | G10: =MAX(0,100-MIN(100,MAX(0,(HedgeCo!G4-ASSUMPTIONS!C70)*ASSUMPTIONS!C86*4))) -> 0 | H10: =MAX(0,100-MIN(100,MAX(0,(HedgeCo!H4-ASSUMPTIONS!C70)*ASSUMPTIONS!C86*4))) -> 0 | I10: =MAX(0,100-MIN(100,MAX(0,(HedgeCo!I4-ASSUMPTIONS!C70)*ASSUMPTIONS!C86*4))) -> 0 | J10: =MAX(0,100-MIN(100,MAX(0,(HedgeCo!J4-ASSUMPTIONS!C70)*ASSUMPTIONS!C86*4))) -> 0 | K10: =MAX(0,100-MIN(100,MAX(0,(HedgeCo!K4-ASSUMPTIONS!C70)*ASSUMPTIONS!C86*4))) -> 0 | L10: =MAX(0,100-MIN(100,MAX(0,(HedgeCo!L4-ASSUMPTIONS!C70)*ASSUMPTIONS!C86*4))) -> 0 | M10: =MAX(0,100-MIN(100,MAX(0,(HedgeCo!M4-ASSUMPTIONS!C70)*ASSUMPTIONS!C86*4))) -> 0
A11: Private foreign Treasury (TIC-visible, $B) | B11: Barth-Beltran TIC-visible portion: $423B end-Y8. TVR = this / total basis trade. | C11: =RepoCo!C4 -> 0 | D11: =RepoCo!D4 -> 0 | E11: =RepoCo!E4 -> 0 | F11: =RepoCo!F4 -> 0 | G11: =RepoCo!G4 -> 0 | H11: =RepoCo!H4 -> 0 | I11: =RepoCo!I4 -> 0 | J11: =RepoCo!J4 -> 0 | ... M11: =RepoCo!M4 -> 0
A12: Private foreign Treasury (TIC-INVISIBLE, $B) | B12: Basis trade exposure invisible via FICC novation. Barth-Beltran: $1,427B invisible end-Y8. | C12: =RepoCo!C13 -> 61.68 | D12: =RepoCo!D13 -> 31.3665 | E12: =RepoCo!E13 -> 51.082605 | F12: =RepoCo!F13 -> 78.762991 | G12: =RepoCo!G13 -> 121.085 | H12: =RepoCo!H13 -> 167.78307 | I12: =RepoCo!I13 -> 306.50803 | J12: =RepoCo!J13 -> 413.02591 | ... M12: =RepoCo!M13 -> 777.16258
A13: Other foreign dollar claims ($B) | C13: 200 | D13: =C13*1.02 -> 204 | E13: =D13*1.02 -> 208.08 | F13: =E13*1.02 -> 212.2416 | G13: =F13*1.02 -> 216.48643 | H13: =G13*1.02 -> 220.81616 | I13: =H13*1.02 -> 225.23248 | J13: =I13*1.02 -> 229.73713 | K13: =J13*1.02 -> 234.33188 | ... M13: =L13*1.02 -> 243.79888
A14: TOTAL LIABILITIES | C14: =SUM(C10:C13) -> 361.68 | D14: =SUM(D10:D13) -> 310.8115 | E14: =SUM(E10:E13) -> 293.21231 | F14: =SUM(F10:F13) -> 291.00459 | G14: =SUM(G10:G13) -> 337.57143 | H14: =SUM(H10:H13) -> 388.59924 | I14: =SUM(I10:I13) -> 531.74051 | J14: =SUM(J10:J13) -> 642.76304 | ... M14: =SUM(M10:M13) -> 1020.9615
A16: NET INTERNATIONAL INVESTMENT POSITION (NIIP)
A17: NIIP = Total Assets - Total Liabilities ($B) | B17: Real-world: US NIIP = -$26.5T end-2024. Toy model scaled ratios. | C17: =C7-C14 -> 218.32 | D17: =D7-D14 -> 284.7885 | E17: =E7-E14 -> 323.09969 | F17: =F7-F14 -> 346.13365 | G17: =G7-G14 -> 295.50957 | H17: =H7-H14 -> 265.54339 | I17: =I7-I14 -> 148.58497 | J17: =J7-J14 -> 58.868945 | ... M17: =M7-M14 -> -279.64303
A19: FLOWS
A20: CA deficit per year ($B) | B20: Each year's deficit = net new claims issued on AmeriCo. Stock accumulates without ceiling. | C20: =ASSUMPTIONS!C7 -> -80 | D20: =ASSUMPTIONS!D7 -> 0 | E20: =ASSUMPTIONS!E7 -> 0 | F20: =ASSUMPTIONS!F7 -> 0 | G20: =ASSUMPTIONS!G7 -> 0 | H20: =ASSUMPTIONS!H7 -> 0 | I20: =ASSUMPTIONS!I7 -> 0 | J20: =ASSUMPTIONS!J7 -> 0 | ... M20: =ASSUMPTIONS!M7 -> 0
A22: FRACTIONAL MEASURES
A23: κ_paper = K_total / Y_productive | B23: Rising. FISIM contamination means κ_real diverges lower. Core κ divergence theorem claim. | C23: =(C7-C11-C12)/ASSUMPTIONS!C5 -> 1.8511429 | D23: =(D7-D11-D12)/ASSUMPTIONS!D5 -> 1.9659704 | E23: =(E7-E11-E12)/ASSUMPTIONS!E5 -> 1.922549 | F23: =(F7-F11-F12)/ASSUMPTIONS!F5 -> 1.8489247 | G23: =(G7-G11-G12)/ASSUMPTIONS!G5 -> 1.7777639 | H23: =(H7-H11-H12)/ASSUMPTIONS!H5 -> 1.6211985 | I23: =(I7-I11-I12)/ASSUMPTIONS!I5 -> 1.213693 | J23: =(J7-J11-J12)/ASSUMPTIONS!J5 -> 0.91620977 | ... M23: =(M7-M11-M12)/ASSUMPTIONS!M5 -> -0.11948048
A24: NIIP / GDP | B24: Interest burden at 4%: ~$300B/yr on official reserves alone by Y8. | C24: =C17/ASSUMPTIONS!C5 -> 0.77971429 | D24: =D17/ASSUMPTIONS!D5 -> 0.99229443 | E24: =E17/ASSUMPTIONS!E5 -> 1.0989786 | F24: =F17/ASSUMPTIONS!F5 -> 1.1461379 | G24: =G17/ASSUMPTIONS!G5 -> 1.0260749 | H24: =H17/ASSUMPTIONS!H5 -> 0.88514463 | I24: =I17/ASSUMPTIONS!I5 -> 0.48241872 | J24: =J17/ASSUMPTIONS!J5 -> 0.18688554 | ... M24: =M17/ASSUMPTIONS!M5 -> -0.93214343
A25: TVR = TIC-visible / (TIC-visible + TIC-invisible) | B25: Barth-Beltran: TVR = $423B / $1,850B = 22.9% end-Y8. Structural gauge failure. | C25: =IF((C11+C12)=0,"-",C11/(C11+C12)) -> 0 | D25: =IF((D11+D12)=0,"-",D11/(D11+D12)) -> 0 | E25: =IF((E11+E12)=0,"-",E11/(E11+E12)) -> 0 | F25: =IF((F11+F12)=0,"-",F11/(F11+F12)) -> 0 | G25: =IF((G11+G12)=0,"-",G11/(G11+G12)) -> 0 | H25: =IF((H11+H12)=0,"-",H11/(H11+H12)) -> 0 | I25: =IF((I11+I12)=0,"-",I11/(I11+I12)) -> 0 | J25: =IF((J11+J12)=0,"-",J11/(J11+J12)) -> 0 | ... M25: =IF((M11+M12)=0,"-",M11/(M11+M12)) -> 0

Sheet GovCo
A1: GovCo | AmeriCo Treasury & Finance Ministry | Sovereign Debt Issuer
A2: Account / Line Item | B2: Notes | C2: Y0 | D2: Y1 | E2: Y2 | F2: Y3 | G2: Y4 | H2: Y5 | I2: Y6 | J2: Y7 | K2: Y8 | L2: Y9 | M2: Y10+
A3: ASSETS
A4: GovCo financial assets / cash ($B) [stock: Y0=20, decremented by fiscal deficit] | B4: Stock of liquid government assets. Y0 stylized. Depleted by annual fiscal deficit. | C4: 20 | D4: =MAX(0,C4-C19) -> 0 | E4: =MAX(0,D4-D19) -> 0 | F4: =MAX(0,E4-E19) -> 0 | G4: =MAX(0,F4-F19) -> 0 | H4: =MAX(0,G4-G19) -> 0 | I4: =MAX(0,H4-H19) -> 0 | J4: =MAX(0,I4-I19) -> 0 | K4: =MAX(0,J4-J19) -> 0 | ... M4: =MAX(0,L4-L19) -> 0
A5: Other government assets ($B) | B5: Reserves, land, enterprise stakes | C5: 80 | D5: 80 | E5: 80 | F5: 80 | G5: 80 | H5: 80 | I5: 80 | J5: 80 | K5: 80 | L5: 80 | M5: 80
A6: TOTAL ASSETS | C6: =SUM(C4:C5) -> 100 | D6: =SUM(D4:D5) -> 80 | E6: =SUM(E4:E5) -> 80 | F6: =SUM(F4:F5) -> 80 | G6: =SUM(G4:G5) -> 80 | H6: =SUM(H4:H5) -> 80 | I6: =SUM(I4:I5) -> 80 | J6: =SUM(J4:J5) -> 80 | ... M6: =SUM(M4:M5) -> 80
A8: LIABILITIES
A9: GovCo bonds held by FedCo ($B) [SFC: = FedCo Treasury holdings] | B9: FedCo!Treasury r4 | C9: =FedCo!C4 -> 64 | D9: =FedCo!D4 -> 79 | E9: =FedCo!E4 -> 94 | F9: =FedCo!F4 -> 114 | G9: =FedCo!G4 -> 194 | H9: =FedCo!H4 -> 186 | I9: =FedCo!I4 -> 166 | J9: =FedCo!J4 -> 141 | ... M9: =FedCo!M4 -> 163
A10: Foreign private holdings via basis trade (HedgeCo cash TSY, $B) [SFC: = HedgeCo!cash_treasury] | B10: HedgeCo is the bond HOLDER. GlobalBankCo is only the financier (repo). Ownership and financing are distinct. SFC: = HedgeCo row 4. | C10: =HedgeCo!C4 -> 80 | D10: =HedgeCo!D4 -> 104.555 | E10: =HedgeCo!E4 -> 145.9503 | F10: =HedgeCo!F4 -> 196.90748 | G10: =HedgeCo!G4 -> 242.17 | H10: =HedgeCo!H4 -> 305.06014 | I10: =HedgeCo!I4 -> 437.86861 | J10: =HedgeCo!J4 -> 573.64709 | ... M10: =HedgeCo!M4 -> 1022.5823
A11: Official reserve liabilities ($B) [= AmeriCo r10 = foreign central bank Treasury holdings] | B11: AmeriCo official reserve liabilities (foreign CB holdings) | C11: =AmeriCo!C10 -> 100 | D11: =AmeriCo!D10 -> 75.445 | E11: =AmeriCo!E10 -> 34.0497 | F11: =AmeriCo!F10 -> 0 | G11: =AmeriCo!G10 -> 0 | H11: =AmeriCo!H10 -> 0 | I11: =AmeriCo!I10 -> 0 | J11: =AmeriCo!J10 -> 0 | ... M11: =AmeriCo!M10 -> 0
A12: Domestic: HouseholdCo direct TSY ($B) [= HouseholdCo!direct_treasury] | B12: Retail T-bills, MMF, savings bonds. 15% of GovCo total. SFC: = HouseholdCo!r8. | C12: =HouseholdCo!C8 -> #VALUE! | D12: =HouseholdCo!D8 -> #VALUE! | E12: =HouseholdCo!E8 -> #VALUE! | F12: =HouseholdCo!F8 -> #VALUE! | G12: =HouseholdCo!G8 -> #VALUE! | H12: =HouseholdCo!H8 -> #VALUE! | I12: =HouseholdCo!I8 -> #VALUE! | J12: =HouseholdCo!J8 -> #VALUE! | ... M12: =HouseholdCo!M8 -> #VALUE!
A13: Domestic: InsuranceCo TSY ($B) [= InsuranceCo!TSY_portfolio] | B13: Life insurance + DB pensions (ex-FinServCo LP chain). 12% of GovCo total. | C13: =InsuranceCo!C5 -> #VALUE! | D13: =InsuranceCo!D5 -> #VALUE! | E13: =InsuranceCo!E5 -> #VALUE! | F13: =InsuranceCo!F5 -> #VALUE! | G13: =InsuranceCo!G5 -> #VALUE! | H13: =InsuranceCo!H5 -> #VALUE! | I13: =InsuranceCo!I5 -> #VALUE! | J13: =InsuranceCo!J5 -> #VALUE! | ... M13: =InsuranceCo!M5 -> #VALUE!
A14: FinServCo long-duration TSY ($B) [= FinServCo!r5] | B14: FinServCo pension/insurance TSY portfolio. Shrinks as HedgeCo scales (seller chain). SFC mirror. | C14: =FinServCo!C5 -> 60 | D14: =FinServCo!D5 -> 35.445 | E14: =FinServCo!E5 -> 0 | F14: =FinServCo!F5 -> 0 | G14: =FinServCo!G5 -> 0 | H14: =FinServCo!H5 -> 0 | I14: =FinServCo!I5 -> 0 | J14: =FinServCo!J5 -> 0 | ... M14: =FinServCo!M5 -> 0
A15: AmeriBankCo HQLA Treasury ($B) [= AmeriBankCo!r6] | B15: AmeriBankCo LCR/HQLA Treasury holdings. Shrinks in reallocation chain (seller 2). SFC mirror. | C15: =AmeriBankCo!C6 -> 30 | D15: =AmeriBankCo!D6 -> 5.445 | E15: =AmeriBankCo!E6 -> 0 | F15: =AmeriBankCo!F6 -> 0 | G15: =AmeriBankCo!G6 -> 0 | H15: =AmeriBankCo!H6 -> 0 | I15: =AmeriBankCo!I6 -> 0 | J15: =AmeriBankCo!J6 -> 0 | ... M15: =AmeriBankCo!M6 -> 0
A16: OtherBankCo TSY ($B) [RESIDUAL ABSORBER: GovCo total − all 7 named holders] | B16: Y0=0B. Absorbs new GovCo issuance not taken by other named holders. True swing buyer. | C16: =GovCo!C18-GovCo!C9-GovCo!C10-GovCo!C11-GovCo!C12-GovCo!C13-GovCo!C14-GovCo!C15 -> #VALUE! | D16: =GovCo!D18-GovCo!D9-GovCo!D10-GovCo!D11-GovCo!D12-GovCo!D13-GovCo!D14-GovCo!D15 -> #VALUE! | E16: =GovCo!E18-GovCo!E9-GovCo!E10-GovCo!E11-GovCo!E12-GovCo!E13-GovCo!E14-GovCo!E15 -> #VALUE! | F16: =GovCo!F18-GovCo!F9-GovCo!F10-GovCo!F11-GovCo!F12-GovCo!F13-GovCo!F14-GovCo!F15 -> #VALUE! | G16: =GovCo!G18-GovCo!G9-GovCo!G10-GovCo!G11-GovCo!G12-GovCo!G13-GovCo!G14-GovCo!G15 -> #VALUE! | H16: =GovCo!H18-GovCo!H9-GovCo!H10-GovCo!H11-GovCo!H12-GovCo!H13-GovCo!H14-GovCo!H15 -> #VALUE! | I16: =GovCo!I18-GovCo!I9-GovCo!I10-GovCo!I11-GovCo!I12-GovCo!I13-GovCo!I14-GovCo!I15 -> #VALUE! | J16: =GovCo!J18-GovCo!J9-GovCo!J10-GovCo!J11-GovCo!J12-GovCo!J13-GovCo!J14-GovCo!J15 -> #VALUE! | ... M16: =GovCo!M18-GovCo!M9-GovCo!M10-GovCo!M11-GovCo!M12-GovCo!M13-GovCo!M14-GovCo!M15 -> #VALUE!
A17: True residual (= 0 by construction — OtherBankCo absorbs remainder) | B17: GovCo total - all 8 named holders. Must be zero. If non-zero: OtherBankCo formula error. | C17: =C18-C9-C10-C11-C12-C13-C14-C15-C16 -> #VALUE! | D17: =D18-D9-D10-D11-D12-D13-D14-D15-D16 -> #VALUE! | E17: =E18-E9-E10-E11-E12-E13-E14-E15-E16 -> #VALUE! | F17: =F18-F9-F10-F11-F12-F13-F14-F15-F16 -> #VALUE! | G17: =G18-G9-G10-G11-G12-G13-G14-G15-G16 -> #VALUE! | H17: =H18-H9-H10-H11-H12-H13-H14-H15-H16 -> #VALUE! | I17: =I18-I9-I10-I11-I12-I13-I14-I15-I16 -> #VALUE! | J17: =J18-J9-J10-J11-J12-J13-J14-J15-J16 -> #VALUE! | ... M17: =M18-M9-M10-M11-M12-M13-M14-M15-M16 -> #VALUE!
A18: TOTAL LIABILITIES (GovCo bonds outstanding, $B) | B18: Grows via fiscal deficit each year. The whole governs the parts. | C18: =ASSUMPTIONS!C52 -> 380 | D18: =MAX(0,C18+C21) -> #VALUE! | E18: =MAX(0,D18+D21) -> #VALUE! | F18: =MAX(0,E18+E21) -> #VALUE! | G18: =MAX(0,F18+F21) -> #VALUE! | H18: =MAX(0,G18+G21) -> #VALUE! | I18: =MAX(0,H18+H21) -> #VALUE! | J18: =MAX(0,I18+I21) -> #VALUE! | K18: =MAX(0,J18+J21) -> #VALUE! | ... M18: =MAX(0,L18+L21) -> #VALUE!
A19: Government spending ($B) | C19: =ASSUMPTIONS!C56 -> 300 | D19: =ASSUMPTIONS!D56 -> 300 | E19: =ASSUMPTIONS!E56 -> 300 | F19: =ASSUMPTIONS!F56 -> 300 | G19: =ASSUMPTIONS!G56 -> 300 | H19: =ASSUMPTIONS!H56 -> 300 | I19: =ASSUMPTIONS!I56 -> 300 | J19: =ASSUMPTIONS!J56 -> 300 | ... M19: =ASSUMPTIONS!M56 -> 300
A20: Interest on outstanding bonds ($B) | B20: Rate times total bonds outstanding prior year | C20: =ASSUMPTIONS!C54*ASSUMPTIONS!C52 -> 15.2 | D20: =ASSUMPTIONS!D54*C13 -> #VALUE! | E20: =ASSUMPTIONS!E54*D13 -> #VALUE! | F20: =ASSUMPTIONS!F54*E13 -> #VALUE! | G20: =ASSUMPTIONS!G54*F13 -> #VALUE! | H20: =ASSUMPTIONS!H54*G13 -> #VALUE! | I20: =ASSUMPTIONS!I54*H13 -> #VALUE! | J20: =ASSUMPTIONS!J54*I13 -> #VALUE! | K20: =ASSUMPTIONS!K54*J13 -> #VALUE! | ... M20: =ASSUMPTIONS!M54*L13 -> #VALUE!
A21: Fiscal deficit ($B) = spending + interest - revenue | C21: =C17+C18-C16 -> #VALUE! | D21: =D17+D18-D16 -> #VALUE! | E21: =E17+E18-E16 -> #VALUE! | F21: =F17+F18-F16 -> #VALUE! | G21: =G17+G18-G16 -> #VALUE! | H21: =H17+H18-H16 -> #VALUE! | I21: =I17+I18-I16 -> #VALUE! | J21: =J17+J18-J16 -> #VALUE! | ... M21: =M17+M18-M16 -> #VALUE!
A23: FRACTIONAL MEASURES
A24: Debt / GDP | C24: =IF(ASSUMPTIONS!C5=0,"-",C13/ASSUMPTIONS!C5) -> #VALUE! | D24: =IF(ASSUMPTIONS!C5=0,"-",D13/ASSUMPTIONS!C5) -> #VALUE! | E24: =IF(ASSUMPTIONS!C5=0,"-",E13/ASSUMPTIONS!C5) -> #VALUE! | F24: =IF(ASSUMPTIONS!C5=0,"-",F13/ASSUMPTIONS!C5) -> #VALUE! | G24: =IF(ASSUMPTIONS!C5=0,"-",G13/ASSUMPTIONS!C5) -> #VALUE! | H24: =IF(ASSUMPTIONS!C5=0,"-",H13/ASSUMPTIONS!C5) -> #VALUE! | I24: =IF(ASSUMPTIONS!C5=0,"-",I13/ASSUMPTIONS!C5) -> #VALUE! | J24: =IF(ASSUMPTIONS!C5=0,"-",J13/ASSUMPTIONS!C5) -> #VALUE! | K24: =IF(ASSUMPTIONS!C5=0,"-",K13/ASSUMPTIONS!C5) -> #VALUE! | L24: =IF(ASSUMPTIONS!C5=0,"-",L13/ASSUMPTIONS!C5) -> #VALUE! | M24: =IF(ASSUMPTIONS!C5=0,"-",M13/ASSUMPTIONS!C5) -> #VALUE!
A25: Foreign-held share of GovCo bonds (visible + invisible) | C25: =IF(C13=0,"-",(C10+C11)/C13) -> #VALUE! | D25: =IF(D13=0,"-",(D10+D11)/D13) -> #VALUE! | E25: =IF(E13=0,"-",(E10+E11)/E13) -> #VALUE! | F25: =IF(F13=0,"-",(F10+F11)/F13) -> #VALUE! | G25: =IF(G13=0,"-",(G10+G11)/G13) -> #VALUE! | H25: =IF(H13=0,"-",(H10+H11)/H13) -> #VALUE! | I25: =IF(I13=0,"-",(I10+I11)/I13) -> #VALUE! | J25: =IF(J13=0,"-",(J10+J11)/J13) -> #VALUE! | ... M25: =IF(M13=0,"-",(M10+M11)/M13) -> #VALUE!
A26: FedCo-held share of GovCo bonds | C26: =IF(C13=0,"-",C9/C13) -> #VALUE! | D26: =IF(D13=0,"-",D9/D13) -> #VALUE! | E26: =IF(E13=0,"-",E9/E13) -> #VALUE! | F26: =IF(F13=0,"-",F9/F13) -> #VALUE! | G26: =IF(G13=0,"-",G9/G13) -> #VALUE! | H26: =IF(H13=0,"-",H9/H13) -> #VALUE! | I26: =IF(I13=0,"-",I9/I13) -> #VALUE! | J26: =IF(J13=0,"-",J9/J13) -> #VALUE! | ... M26: =IF(M13=0,"-",M9/M13) -> #VALUE!
A27: Interest burden / tax revenue (debt service ratio) | C27: =IF(C16=0,"-",C18/C16) -> #VALUE! | D27: =IF(D16=0,"-",D18/D16) -> #VALUE! | E27: =IF(E16=0,"-",E18/E16) -> #VALUE! | F27: =IF(F16=0,"-",F18/F16) -> #VALUE! | G27: =IF(G16=0,"-",G18/G16) -> #VALUE! | H27: =IF(H16=0,"-",H18/H16) -> #VALUE! | I27: =IF(I16=0,"-",I18/I16) -> #VALUE! | J27: =IF(J16=0,"-",J18/J16) -> #VALUE! | ... M27: =IF(M16=0,"-",M18/M16) -> #VALUE!
A28: TIC-invisible / foreign private chain (reporting gap -- ClearCo novated / total repo) | B28: Rising = structural reporting gap widening | C28: =IF(GlobalBankCo!C4=0,"-",ClearCo!C4/GlobalBankCo!C4) -> 0.771 | D28: =IF(GlobalBankCo!D4=0,"-",ClearCo!D4/GlobalBankCo!D4) -> 0.3 | E28: =IF(GlobalBankCo!E4=0,"-",ClearCo!E4/GlobalBankCo!E4) -> 0.35 | F28: =IF(GlobalBankCo!F4=0,"-",ClearCo!F4/GlobalBankCo!F4) -> 0.4 | G28: =IF(GlobalBankCo!G4=0,"-",ClearCo!G4/GlobalBankCo!G4) -> 0.5 | H28: =IF(GlobalBankCo!H4=0,"-",ClearCo!H4/GlobalBankCo!H4) -> 0.55 | I28: =IF(GlobalBankCo!I4=0,"-",ClearCo!I4/GlobalBankCo!I4) -> 0.7 | J28: =IF(GlobalBankCo!J4=0,"-",ClearCo!J4/GlobalBankCo!J4) -> 0.72 | ... M28: =IF(GlobalBankCo!M4=0,"-",ClearCo!M4/GlobalBankCo!M4) -> 0.76
A30: Effective bond supply for basis trade (= new issuance × duration mix) | B30: When yield exceeds 5.5% threshold, GovCo shifts to bills. Effective bond collateral = fiscal_deficit × MEASURES!duration_mix. Bills do not serve as basis trade collateral. | C30: =GovCo!C21*MEASURES!C47 -> #VALUE! | D30: =GovCo!D21*MEASURES!D47 -> #VALUE! | E30: =GovCo!E21*MEASURES!E47 -> #VALUE! | F30: =GovCo!F21*MEASURES!F47 -> #VALUE! | G30: =GovCo!G21*MEASURES!G47 -> #VALUE! | H30: =GovCo!H21*MEASURES!H47 -> #VALUE! | I30: =GovCo!I21*MEASURES!I47 -> #VALUE! | J30: =GovCo!J21*MEASURES!J47 -> #VALUE! | ... M30: =GovCo!M21*MEASURES!M47 -> #VALUE!

Sheet HouseholdCo
A1: HouseholdCo | Wage Earners + Asset Holders | Dual Exposure
A2: Wage income from ManuCo+ProdServiceCo+FinServCo. Pension assets in FinServCo (LP channel). Nominal wealth rising via asset prices; real productive backing flat. Wage share falling.
A3: Account / Line Item | B3: Notes / Source | C3: Y0 | D3: Y1 | E3: Y2 | F3: Y3 | G3: Y4 | H3: Y5 | I3: Y6 | J3: Y7 | K3: Y8 | L3: Y9 | M3: Y10+ Stress
A4: ASSETS
A5: Pension assets — claim on FinServCo net worth ($B) [SFC: FinServCo assets − obligations] | B5: HH holds FinServCo NET worth, not gross. = FinServCo total assets - pension obligations - repo payable. | C5: =FinServCo!C9-FinServCo!C11-FinServCo!C12 -> -35 | D5: =FinServCo!D9-FinServCo!D11-FinServCo!D12 -> -36 | E5: =FinServCo!E9-FinServCo!E11-FinServCo!E12 -> -36.92 | F5: =FinServCo!F9-FinServCo!F11-FinServCo!F12 -> -38.9104 | G5: =FinServCo!G9-FinServCo!G11-FinServCo!G12 -> -39.135168 | H5: =FinServCo!H9-FinServCo!H11-FinServCo!H12 -> -40.534092 | I5: =FinServCo!I9-FinServCo!I11-FinServCo!I12 -> -42.288864 | J5: =FinServCo!J9-FinServCo!J11-FinServCo!J12 -> -42.590639 | ... M5: =FinServCo!M9-FinServCo!M11-FinServCo!M12 -> -47.797553
A6: Housing equity ($B) | B6: Real asset. Sensitive to interest rates (mortgage cost = FedCo rate). Rises with suppressed rates. | C6: 80 | D6: 84 | E6: 88 | F6: 94 | G6: 90 | H6: 100 | I6: 110 | J6: 115 | K6: 120 | L6: 122 | M6: 108
A7: Deposits at AmeriBankCo ($B) [SFC: Identity 13 partial] | B7: Checking + savings. SFC: HouseholdCo deposit = AmeriBankCo deposit liability (domestic HH portion). | C7: =ASSUMPTIONS!C5*0.25 -> 70 | D7: =ASSUMPTIONS!D5*0.25 -> 71.75 | E7: =ASSUMPTIONS!E5*0.25 -> 73.5 | F7: =ASSUMPTIONS!F5*0.25 -> 75.5 | G7: =ASSUMPTIONS!G5*0.25 -> 72 | H7: =ASSUMPTIONS!H5*0.25 -> 75 | I7: =ASSUMPTIONS!I5*0.25 -> 77 | J7: =ASSUMPTIONS!J5*0.25 -> 78.75 | ... M7: =ASSUMPTIONS!M5*0.25 -> 75
A8: Direct Treasury holdings ($B) [SFC: GovCo holder HH_direct] | B8: Y0=45.0B (11.8% of GovCo). Grows proportionally with new GovCo issuance. | C8: =28*(GovCo!C16/ASSUMPTIONS!C52) -> #VALUE! | D8: =28*(GovCo!D16/ASSUMPTIONS!C52) -> #VALUE! | E8: =28*(GovCo!E16/ASSUMPTIONS!C52) -> #VALUE! | F8: =28*(GovCo!F16/ASSUMPTIONS!C52) -> #VALUE! | G8: =28*(GovCo!G16/ASSUMPTIONS!C52) -> #VALUE! | H8: =28*(GovCo!H16/ASSUMPTIONS!C52) -> #VALUE! | I8: =28*(GovCo!I16/ASSUMPTIONS!C52) -> #VALUE! | J8: =28*(GovCo!J16/ASSUMPTIONS!C52) -> #VALUE! | K8: =28*(GovCo!K16/ASSUMPTIONS!C52) -> #VALUE! | L8: =28*(GovCo!L16/ASSUMPTIONS!C52) -> #VALUE! | M8: =28*(GovCo!M16/ASSUMPTIONS!C52) -> #VALUE!
A9: TOTAL ASSETS | C9: =SUM(C5:C8) -> #VALUE! | D9: =SUM(D5:D8) -> #VALUE! | E9: =SUM(E5:E8) -> #VALUE! | F9: =SUM(F5:F8) -> #VALUE! | G9: =SUM(G5:G8) -> #VALUE! | H9: =SUM(H5:H8) -> #VALUE! | I9: =SUM(I5:I8) -> #VALUE! | J9: =SUM(J5:J8) -> #VALUE! | ... M9: =SUM(M5:M8) -> #VALUE!
A10: LIABILITIES
A11: Mortgage debt ($B) | B11: Sensitive to rates. Cheaper when FedCo suppresses. Housing equity inflated by same suppression. | C11: 60 | D11: 62 | E11: 64 | F11: 67 | G11: 65 | H11: 68 | I11: 72 | J11: 74 | K11: 76 | L11: 78 | M11: 80
A12: Consumer + student debt ($B) | B12: Rising. Real wages flat -> more debt to maintain consumption. | C12: 25 | D12: 26 | E12: 27 | F12: 28 | G12: 28 | H12: 29 | I12: 30 | J12: 31 | K12: 32 | L12: 33 | M12: 34
A13: TOTAL LIABILITIES | C13: =SUM(C11:C12) -> 85 | D13: =SUM(D11:D12) -> 88 | E13: =SUM(E11:E12) -> 91 | F13: =SUM(F11:F12) -> 95 | G13: =SUM(G11:G12) -> 93 | H13: =SUM(H11:H12) -> 97 | I13: =SUM(I11:I12) -> 102 | J13: =SUM(J11:J12) -> 105 | ... M13: =SUM(M11:M12) -> 114
A14: NET WORTH = Total Assets − Total Liabilities | B14: HH net worth. Rises nominally via asset price inflation. Flat in real terms if wage share falls. | C14: =C9-C13 -> #VALUE! | D14: =D9-D13 -> #VALUE! | E14: =E9-E13 -> #VALUE! | F14: =F9-F13 -> #VALUE! | G14: =G9-G13 -> #VALUE! | H14: =H9-H13 -> #VALUE! | I14: =I9-I13 -> #VALUE! | J14: =J9-J13 -> #VALUE! | ... M14: =M9-M13 -> #VALUE!
A15: Wage income from ManuCo ($B) [SFC: = ManuCo!wage_bill] | B15: ManuCo wage bill. Declining. ASSUMPTIONS row 59. | C15: =ManuCo!C12 -> 80 | D15: =ManuCo!D12 -> 79 | E15: =ManuCo!E12 -> 78 | F15: =ManuCo!F12 -> 77 | G15: =ManuCo!G12 -> 70 | H15: =ManuCo!H12 -> 72 | I15: =ManuCo!I12 -> 73 | J15: =ManuCo!J12 -> 72 | ... M15: =ManuCo!M12 -> 65
A16: Wage income from ProdServiceCo ($B) [SFC: = ProdServiceCo!wage_bill] | B16: ProdServiceCo wage bill. Growing. ASSUMPTIONS row 61. | C16: =ProdServiceCo!C12 -> 60 | D16: =ProdServiceCo!D12 -> 63 | E16: =ProdServiceCo!E12 -> 67 | F16: =ProdServiceCo!F12 -> 72 | G16: =ProdServiceCo!G12 -> 68 | H16: =ProdServiceCo!H12 -> 78 | I16: =ProdServiceCo!I12 -> 88 | J16: =ProdServiceCo!J12 -> 96 | ... M16: =ProdServiceCo!M12 -> 108
A17: Wage income from FinServCo ($B) [SFC: = FinServCo!wage_bill] | B17: FinServCo wage bill. Growing with FISIM. ASSUMPTIONS row 63. | C17: =FinServCo!C15 -> 105 | D17: =FinServCo!D15 -> 111 | E17: =FinServCo!E15 -> 118.71 | F17: =FinServCo!F15 -> 128.2468 | G17: =FinServCo!G15 -> 148.5585 | H17: =FinServCo!H15 -> 169.8702 | I17: =FinServCo!I15 -> 190.65073 | J17: =FinServCo!J15 -> 206.2158 | ... M17: =FinServCo!M15 -> 251.55703
A18: TOTAL WAGE INCOME ($B) [SFC Identity 12 total] | B18: Sum of all three. SFC: must = ManuCo + ProdServiceCo + FinServCo wage bills. | C18: =SUM(C15:C17) -> 245 | D18: =SUM(D15:D17) -> 253 | E18: =SUM(E15:E17) -> 263.71 | F18: =SUM(F15:F17) -> 277.2468 | G18: =SUM(G15:G17) -> 286.5585 | H18: =SUM(H15:H17) -> 319.8702 | I18: =SUM(I15:I17) -> 351.65073 | J18: =SUM(J15:J17) -> 374.2158 | ... M18: =SUM(M15:M17) -> 424.55703
A19: FRACTIONAL MEASURES
A20: Wage share of GDP (total HouseholdCo wages / GDP) | B20: CORE THESIS MEASURE. Falling as FinServCo grows relative to ManuCo. FedCo absorptions do not expand wage base. | C20: =IF(ASSUMPTIONS!C5=0,"-",C18/ASSUMPTIONS!C5) -> 0.875 | D20: =IF(ASSUMPTIONS!D5=0,"-",D18/ASSUMPTIONS!D5) -> 0.8815331 | E20: =IF(ASSUMPTIONS!E5=0,"-",E18/ASSUMPTIONS!E5) -> 0.89697279 | F20: =IF(ASSUMPTIONS!F5=0,"-",F18/ASSUMPTIONS!F5) -> 0.91803576 | G20: =IF(ASSUMPTIONS!G5=0,"-",G18/ASSUMPTIONS!G5) -> 0.99499479 | H20: =IF(ASSUMPTIONS!H5=0,"-",H18/ASSUMPTIONS!H5) -> 1.066234 | I20: =IF(ASSUMPTIONS!I5=0,"-",I18/ASSUMPTIONS!I5) -> 1.1417231 | J20: =IF(ASSUMPTIONS!J5=0,"-",J18/ASSUMPTIONS!J5) -> 1.1879867 | ... M20: =IF(ASSUMPTIONS!M5=0,"-",M18/ASSUMPTIONS!M5) -> 1.4151901
A21: ManuCo wage share of total wages | B21: Declining. The picker's share of household income falling. | C21: =IF(C18=0,"-",C15/C18) -> 0.32653061 | D21: =IF(D18=0,"-",D15/D18) -> 0.31225296 | E21: =IF(E18=0,"-",E15/E18) -> 0.29577945 | F21: =IF(F18=0,"-",F15/F18) -> 0.27773089 | G21: =IF(G18=0,"-",G15/G18) -> 0.24427822 | H21: =IF(H18=0,"-",H15/H18) -> 0.2250913 | I21: =IF(I18=0,"-",I15/I18) -> 0.20759235 | J21: =IF(J18=0,"-",J15/J18) -> 0.19240235 | ... M21: =IF(M18=0,"-",M15/M18) -> 0.15310075
A22: Nominal wealth / wage income ratio | B22: Rising. Asset price inflation outpaces wage growth. Wealth looks fine. Income pressure growing. | C22: =IF(C18=0,"-",C9/C18) -> #VALUE! | D22: =IF(D18=0,"-",D9/D18) -> #VALUE! | E22: =IF(E18=0,"-",E9/E18) -> #VALUE! | F22: =IF(F18=0,"-",F9/F18) -> #VALUE! | G22: =IF(G18=0,"-",G9/G18) -> #VALUE! | H22: =IF(H18=0,"-",H9/H18) -> #VALUE! | I22: =IF(I18=0,"-",I9/I18) -> #VALUE! | J22: =IF(J18=0,"-",J9/J18) -> #VALUE! | ... M22: =IF(M18=0,"-",M9/M18) -> #VALUE!
A23: Debt / wage income | B23: Rising. Debt serviced from wages. As wage share falls, debt burden rises. | C23: =IF(C18=0,"-",C13/C18) -> 0.34693878 | D23: =IF(D18=0,"-",D13/D18) -> 0.34782609 | E23: =IF(E18=0,"-",E13/E18) -> 0.34507603 | F23: =IF(F18=0,"-",F13/F18) -> 0.34265499 | G23: =IF(G18=0,"-",G13/G18) -> 0.32454106 | H23: =IF(H18=0,"-",H13/H18) -> 0.303248 | I23: =IF(I18=0,"-",I13/I18) -> 0.29006054 | J23: =IF(J18=0,"-",J13/J18) -> 0.28058676 | ... M23: =IF(M18=0,"-",M13/M18) -> 0.26851516

Sheet ManuCo
A1: ManuCo | Physical Productive Base | The Orange Picker
A2: Plant, equipment, tradeable output. Wage bill = primary HouseholdCo income source. Investment crowded out as return differential widens vs FinServCo.
A3: Account / Line Item | B3: Notes / Source | C3: Y0 | D3: Y1 | E3: Y2 | F3: Y3 | G3: Y4 | H3: Y5 | I3: Y6 | J3: Y7 | K3: Y8 | L3: Y9 | M3: Y10+ Stress
A4: ASSETS
A5: Physical capital stock ($B) | B5: ManuCo share of AmeriCo K_real. Declining as investment routes to ProdServiceCo/FinServCo. | C5: 195 | D5: 198.4 | E5: 204.8 | F5: 210.8 | G5: 198 | H5: 203.5 | I5: 208 | J5: 209 | K5: 212 | L5: 211.7 | M5: 200
A6: Trade receivables ($B) | B6: Export earnings. Tradeable goods output. | C6: 15 | D6: 16 | E6: 16 | F6: 17 | G6: 14 | H6: 16 | I6: 17 | J6: 17 | K6: 18 | L6: 18 | M6: 16
A7: TOTAL ASSETS | C7: =SUM(C5:C6) -> 210 | D7: =SUM(D5:D6) -> 214.4 | E7: =SUM(E5:E6) -> 220.8 | F7: =SUM(F5:F6) -> 227.8 | G7: =SUM(G5:G6) -> 212 | H7: =SUM(H5:H6) -> 219.5 | I7: =SUM(I5:I6) -> 225 | J7: =SUM(J5:J6) -> 226 | ... M7: =SUM(M5:M6) -> 216
A8: LIABILITIES
A9: Corporate debt ($B) | B9: Equipment financing, working capital. Real-world: US mfg debt load rising. | C9: 40 | D9: 42 | E9: 44 | F9: 46 | G9: 44 | H9: 46 | I9: 48 | J9: 49 | K9: 50 | L9: 51 | M9: 52
A10: TOTAL LIABILITIES | C10: =C9 -> 40 | D10: =D9 -> 42 | E10: =E9 -> 44 | F10: =F9 -> 46 | G10: =G9 -> 44 | H10: =H9 -> 46 | I10: =I9 -> 48 | J10: =J9 -> 49 | ... M10: =M9 -> 52
A11: INCOME FLOWS
A12: Wage bill ($B) [SFC: = HouseholdCo!manu_wages] | B12: From ASSUMPTIONS row 59. Declining. SFC: must equal HouseholdCo manu wage income. | C12: =ASSUMPTIONS!C59 -> 80 | D12: =ASSUMPTIONS!D59 -> 79 | E12: =ASSUMPTIONS!E59 -> 78 | F12: =ASSUMPTIONS!F59 -> 77 | G12: =ASSUMPTIONS!G59 -> 70 | H12: =ASSUMPTIONS!H59 -> 72 | I12: =ASSUMPTIONS!I59 -> 73 | J12: =ASSUMPTIONS!J59 -> 72 | ... M12: =ASSUMPTIONS!M59 -> 65
A13: Capital investment ($B) | B13: ManuCo capex. = GDP * investment share. Declining as return differential routes capital to FinServCo. | C13: =ASSUMPTIONS!C5*ASSUMPTIONS!C65 -> 28 | D13: =ASSUMPTIONS!D5*ASSUMPTIONS!D65 -> 28.126 | E13: =ASSUMPTIONS!E5*ASSUMPTIONS!E65 -> 28.224 | F13: =ASSUMPTIONS!F5*ASSUMPTIONS!F65 -> 28.388 | G13: =ASSUMPTIONS!G5*ASSUMPTIONS!G65 -> 24.48 | H13: =ASSUMPTIONS!H5*ASSUMPTIONS!H65 -> 26.4 | I13: =ASSUMPTIONS!I5*ASSUMPTIONS!I65 -> 26.488 | J13: =ASSUMPTIONS!J5*ASSUMPTIONS!J65 -> 26.46 | ... M13: =ASSUMPTIONS!M5*ASSUMPTIONS!M65 -> 22.5
A14: Output / revenue ($B) | B14: Productive output. FISIM-clean -- no financial spread income. | C14: 110 | D14: 113 | E14: 116 | F14: 120 | G14: 102 | H14: 112 | I14: 118 | J14: 122 | K14: 126 | L14: 128 | M14: 118
A15: FRACTIONAL MEASURES
A16: Wage bill / GDP (wage share, ManuCo) | B16: Declining. Core thesis: FedCo absorption episodes do not expand ManuCo wage base. | C16: =IF(ASSUMPTIONS!C5=0,"-",C12/ASSUMPTIONS!C5) -> 0.28571429 | D16: =IF(ASSUMPTIONS!D5=0,"-",D12/ASSUMPTIONS!D5) -> 0.27526132 | E16: =IF(ASSUMPTIONS!E5=0,"-",E12/ASSUMPTIONS!E5) -> 0.26530612 | F16: =IF(ASSUMPTIONS!F5=0,"-",F12/ASSUMPTIONS!F5) -> 0.25496689 | G16: =IF(ASSUMPTIONS!G5=0,"-",G12/ASSUMPTIONS!G5) -> 0.24305556 | H16: =IF(ASSUMPTIONS!H5=0,"-",H12/ASSUMPTIONS!H5) -> 0.24 | I16: =IF(ASSUMPTIONS!I5=0,"-",I12/ASSUMPTIONS!I5) -> 0.23701299 | J16: =IF(ASSUMPTIONS!J5=0,"-",J12/ASSUMPTIONS!J5) -> 0.22857143 | ... M16: =IF(ASSUMPTIONS!M5=0,"-",M12/ASSUMPTIONS!M5) -> 0.21666667
A17: Capital investment / GDP | B17: ManuCo investment share. Structural decline = picker aging. | C17: =ASSUMPTIONS!C65 -> 0.1 | D17: =ASSUMPTIONS!D65 -> 0.098 | E17: =ASSUMPTIONS!E65 -> 0.096 | F17: =ASSUMPTIONS!F65 -> 0.094 | G17: =ASSUMPTIONS!G65 -> 0.085 | H17: =ASSUMPTIONS!H65 -> 0.088 | I17: =ASSUMPTIONS!I65 -> 0.086 | J17: =ASSUMPTIONS!J65 -> 0.084 | ... M17: =ASSUMPTIONS!M65 -> 0.075
A18: Return on capital (output / capital stock) | B18: Falling IRR. At high kappa, return to productive investment < return to financial intermediation. | C18: =IF(C5=0,"-",C14/C5) -> 0.56410256 | D18: =IF(D5=0,"-",D14/D5) -> 0.56955645 | E18: =IF(E5=0,"-",E14/E5) -> 0.56640625 | F18: =IF(F5=0,"-",F14/F5) -> 0.56925996 | G18: =IF(G5=0,"-",G14/G5) -> 0.51515152 | H18: =IF(H5=0,"-",H14/H5) -> 0.55036855 | I18: =IF(I5=0,"-",I14/I5) -> 0.56730769 | J18: =IF(J5=0,"-",J14/J5) -> 0.58373206 | ... M18: =IF(M5=0,"-",M14/M5) -> 0.59
A20: EQUITY & RETAINED EARNINGS
A21: Retained earnings ($B) = output − wages − debt interest | B21: Capital income after wages and debt service. Reinvested or distributed. | C21: =C14-C12-(C9*0.04) -> 28.4 | D21: =D14-D12-(D9*0.04) -> 32.32 | E21: =E14-E12-(E9*0.04) -> 36.24 | F21: =F14-F12-(F9*0.04) -> 41.16 | G21: =G14-G12-(G9*0.04) -> 30.24 | H21: =H14-H12-(H9*0.04) -> 38.16 | I21: =I14-I12-(I9*0.04) -> 43.08 | J21: =J14-J12-(J9*0.04) -> 48.04 | ... M21: =M14-M12-(M9*0.04) -> 50.92
A22: Net worth = Capital stock − Corporate debt + Retained earnings | B22: ManuCo equity. Declining as IRR falls and retained earnings compress. | C22: =C5-C9+C21 -> 183.4 | D22: =D5-D9+D21 -> 188.72 | E22: =E5-E9+E21 -> 197.04 | F22: =F5-F9+F21 -> 205.96 | G22: =G5-G9+G21 -> 184.24 | H22: =H5-H9+H21 -> 195.66 | I22: =I5-I9+I21 -> 203.08 | J22: =J5-J9+J21 -> 208.04 | ... M22: =M5-M9+M21 -> 198.92

Sheet ProdServiceCo
A1: ProdServiceCo | Technology & Software | Real TFP Gains
A2: IP, software, AI infrastructure. Equity-funded. Valuation rises mechanically as FedCo suppresses discount rate. TFP gains real but racing against κ accumulation.
A3: Account / Line Item | B3: Notes / Source | C3: Y0 | D3: Y1 | E3: Y2 | F3: Y3 | G3: Y4 | H3: Y5 | I3: Y6 | J3: Y7 | K3: Y8 | L3: Y9 | M3: Y10+ Stress
A4: ASSETS
A5: IP & software capital stock ($B) | B5: ProdServiceCo share of AmeriCo K_real. Growing. | C5: 60 | D5: 65.1 | E5: 71.5 | F5: 78.2 | G5: 75.9 | H5: 82.8 | I5: 94.9 | J5: 106.4 | K5: 120 | L5: 132.8 | M5: 128
A6: Equity market valuation ($B) | B6: annual output × P/E ratio (ASSUMPTIONS row 66). Rises as FedCo absorbs and discount rate falls. | C6: =C14*ASSUMPTIONS!C66 -> 1210 | D6: =D14*ASSUMPTIONS!D66 -> 1416 | E6: =E14*ASSUMPTIONS!E66 -> 1664 | F6: =F14*ASSUMPTIONS!F66 -> 1960 | G6: =G14*ASSUMPTIONS!G66 -> 1560 | H6: =H14*ASSUMPTIONS!H66 -> 2730 | I6: =I14*ASSUMPTIONS!I66 -> 3420 | J6: =J14*ASSUMPTIONS!J66 -> 3168 | ... M6: =M14*ASSUMPTIONS!M66 -> 1980
A7: TOTAL ASSETS (book) | C7: =SUM(C5:C5) -> 60 | D7: =SUM(D5:D5) -> 65.1 | E7: =SUM(E5:E5) -> 71.5 | F7: =SUM(F5:F5) -> 78.2 | G7: =SUM(G5:G5) -> 75.9 | H7: =SUM(H5:H5) -> 82.8 | I7: =SUM(I5:I5) -> 94.9 | J7: =SUM(J5:J5) -> 106.4 | ... M7: =SUM(M5:M5) -> 128
A8: LIABILITIES
A9: Equity held by investors ($B) [SFC: FinServCo equity portfolio + HH direct equity] | B9: Wired to actual holders. FinServCo pension equity portfolio + HH direct equity (fraction of HH net worth). | C9: =FinServCo!C6+HouseholdCo!C14*ASSUMPTIONS!C71 -> #VALUE! | D9: =FinServCo!D6+HouseholdCo!D14*ASSUMPTIONS!C71 -> #VALUE! | E9: =FinServCo!E6+HouseholdCo!E14*ASSUMPTIONS!C71 -> #VALUE! | F9: =FinServCo!F6+HouseholdCo!F14*ASSUMPTIONS!C71 -> #VALUE! | G9: =FinServCo!G6+HouseholdCo!G14*ASSUMPTIONS!C71 -> #VALUE! | H9: =FinServCo!H6+HouseholdCo!H14*ASSUMPTIONS!C71 -> #VALUE! | I9: =FinServCo!I6+HouseholdCo!I14*ASSUMPTIONS!C71 -> #VALUE! | J9: =FinServCo!J6+HouseholdCo!J14*ASSUMPTIONS!C71 -> #VALUE! | K9: =FinServCo!K6+HouseholdCo!K14*ASSUMPTIONS!C71 -> #VALUE! | L9: =FinServCo!L6+HouseholdCo!L14*ASSUMPTIONS!C71 -> #VALUE! | M9: =FinServCo!M6+HouseholdCo!M14*ASSUMPTIONS!C71 -> #VALUE!
A10: Private credit debt to FinServCo ($B) [SFC ID27: = FinServCo!PC_loans] | B10: Mirror of FinServCo PC loan. Exact equality enforced by SFC Identity 27. | C10: =FinServCo!C9 -> 20 | D10: =FinServCo!D9 -> 22 | E10: =FinServCo!E9 -> 25.08 | F10: =FinServCo!F9 -> 28.0896 | G10: =FinServCo!G9 -> 32.864832 | H10: =FinServCo!H9 -> 37.465908 | I10: =FinServCo!I9 -> 42.711136 | J10: =FinServCo!J9 -> 47.409361 | ... M10: =FinServCo!M9 -> 52.202447
A11: TOTAL LIABILITIES | B11: External equity + PC debt. | C11: =SUM(C9:C10) -> #VALUE! | D11: =SUM(D9:D10) -> #VALUE! | E11: =SUM(E9:E10) -> #VALUE! | F11: =SUM(F9:F10) -> #VALUE! | G11: =SUM(G9:G10) -> #VALUE! | H11: =SUM(H9:H10) -> #VALUE! | I11: =SUM(I9:I10) -> #VALUE! | J11: =SUM(J9:J10) -> #VALUE! | ... M11: =SUM(M9:M10) -> #VALUE!
A12: Wage bill ($B) [SFC: = HouseholdCo!prod_wages] | B12: From ASSUMPTIONS row 61. Growing. | C12: =ASSUMPTIONS!C61 -> 60 | D12: =ASSUMPTIONS!D61 -> 63 | E12: =ASSUMPTIONS!E61 -> 67 | F12: =ASSUMPTIONS!F61 -> 72 | G12: =ASSUMPTIONS!G61 -> 68 | H12: =ASSUMPTIONS!H61 -> 78 | I12: =ASSUMPTIONS!I61 -> 88 | J12: =ASSUMPTIONS!J61 -> 96 | ... M12: =ASSUMPTIONS!M61 -> 108
A13: Capital investment ($B) | B13: R&D + software + AI capex. Equity-funded. Grows independently of FedCo cycle. | C13: =C5*0.12 -> 7.2 | D13: =D5*0.12 -> 7.812 | E13: =E5*0.12 -> 8.58 | F13: =F5*0.12 -> 9.384 | G13: =G5*0.12 -> 9.108 | H13: =H5*0.12 -> 9.936 | I13: =I5*0.12 -> 11.388 | J13: =J5*0.12 -> 12.768 | ... M13: =M5*0.12 -> 15.36
A14: Output / revenue ($B) | B14: Technology services, software. FISIM-clean. | C14: 55 | D14: 59 | E14: 64 | F14: 70 | G14: 65 | H14: 78 | I14: 90 | J14: 99 | K14: 110 | L14: 118 | M14: 110
A15: FRACTIONAL MEASURES
A16: Wage bill / GDP | B16: Growing. ProdServiceCo expanding wage share. But: does it offset ManuCo decline? Key empirical question. | C16: =IF(ASSUMPTIONS!C5=0,"-",C12/ASSUMPTIONS!C5) -> 0.21428571 | D16: =IF(ASSUMPTIONS!D5=0,"-",D12/ASSUMPTIONS!D5) -> 0.2195122 | E16: =IF(ASSUMPTIONS!E5=0,"-",E12/ASSUMPTIONS!E5) -> 0.22789116 | F16: =IF(ASSUMPTIONS!F5=0,"-",F12/ASSUMPTIONS!F5) -> 0.2384106 | G16: =IF(ASSUMPTIONS!G5=0,"-",G12/ASSUMPTIONS!G5) -> 0.23611111 | H16: =IF(ASSUMPTIONS!H5=0,"-",H12/ASSUMPTIONS!H5) -> 0.26 | I16: =IF(ASSUMPTIONS!I5=0,"-",I12/ASSUMPTIONS!I5) -> 0.28571429 | J16: =IF(ASSUMPTIONS!J5=0,"-",J12/ASSUMPTIONS!J5) -> 0.3047619 | ... M16: =IF(ASSUMPTIONS!M5=0,"-",M12/ASSUMPTIONS!M5) -> 0.36
A17: Equity valuation / GDP (P/E-adjusted) | B17: Rising with FedCo suppression. The asset price inflation channel. Falls sharply in stress (Y10+). | C17: =IF(ASSUMPTIONS!C5=0,"-",C6/ASSUMPTIONS!C5) -> 4.3214286 | D17: =IF(ASSUMPTIONS!D5=0,"-",D6/ASSUMPTIONS!D5) -> 4.9337979 | E17: =IF(ASSUMPTIONS!E5=0,"-",E6/ASSUMPTIONS!E5) -> 5.6598639 | F17: =IF(ASSUMPTIONS!F5=0,"-",F6/ASSUMPTIONS!F5) -> 6.4900662 | G17: =IF(ASSUMPTIONS!G5=0,"-",G6/ASSUMPTIONS!G5) -> 5.4166667 | H17: =IF(ASSUMPTIONS!H5=0,"-",H6/ASSUMPTIONS!H5) -> 9.1 | I17: =IF(ASSUMPTIONS!I5=0,"-",I6/ASSUMPTIONS!I5) -> 11.103896 | J17: =IF(ASSUMPTIONS!J5=0,"-",J6/ASSUMPTIONS!J5) -> 10.057143 | ... M17: =IF(ASSUMPTIONS!M5=0,"-",M6/ASSUMPTIONS!M5) -> 6.6
A18: Output growth rate (TFP proxy) | B18: Real TFP gains. Positive. Key question: large enough to offset ManuCo contraction + FISIM inflation? | C18: - | D18: =IF(D14=0,"-",(D14-C14)/C14) -> 0.072727273 | E18: =IF(E14=0,"-",(E14-D14)/D14) -> 0.084745763 | F18: =IF(F14=0,"-",(F14-E14)/E14) -> 0.09375 | G18: =IF(G14=0,"-",(G14-F14)/F14) -> -0.071428571 | H18: =IF(H14=0,"-",(H14-G14)/G14) -> 0.2 | I18: =IF(I14=0,"-",(I14-H14)/H14) -> 0.15384615 | J18: =IF(J14=0,"-",(J14-I14)/I14) -> 0.1 | K18: =IF(K14=0,"-",(K14-J14)/J14) -> 0.11111111 | ... M18: =IF(M14=0,"-",(M14-L14)/L14) -> -0.06779661

Sheet FinServCo
A1: FinServCo | Pension Funds + Insurance | HedgeCo LP | FISIM Income
A2: Structural long-duration Treasury holder. LP in HedgeCo (basis trade). Long equities. In stress: yield spike hits all three simultaneously. FISIM spread income counted as GDP but not productive output.
A3: Account / Line Item | B3: Notes / Source | C3: Y0 | D3: Y1 | E3: Y2 | F3: Y3 | G3: Y4 | H3: Y5 | I3: Y6 | J3: Y7 | K3: Y8 | L3: Y9 | M3: Y10+ Stress
A4: ASSETS
A5: Long-duration Treasury portfolio ($B) [DYNAMIC: shrinks as HedgeCo scales] | B5: FinServCo is the explicit SELLER. TSY = TSY_Y0(60) - (HedgeCo_current - HedgeCo_Y0). Shrinks dollar-for-dollar as HedgeCo basis trade scales. Floor = 0 (cannot sell more than owned). Proceeds flow to equity portfolio (row 6). | C5: =MAX(0,60-MIN(60,MAX(0,(HedgeCo!C4-ASSUMPTIONS!C70)*ASSUMPTIONS!C84*2))) -> 60 | D5: =MAX(0,60-MIN(60,MAX(0,(HedgeCo!D4-ASSUMPTIONS!C70)*ASSUMPTIONS!C84*2))) -> 35.445 | E5: =MAX(0,60-MIN(60,MAX(0,(HedgeCo!E4-ASSUMPTIONS!C70)*ASSUMPTIONS!C84*2))) -> 0 | F5: =MAX(0,60-MIN(60,MAX(0,(HedgeCo!F4-ASSUMPTIONS!C70)*ASSUMPTIONS!C84*2))) -> 0 | G5: =MAX(0,60-MIN(60,MAX(0,(HedgeCo!G4-ASSUMPTIONS!C70)*ASSUMPTIONS!C84*2))) -> 0 | H5: =MAX(0,60-MIN(60,MAX(0,(HedgeCo!H4-ASSUMPTIONS!C70)*ASSUMPTIONS!C84*2))) -> 0 | I5: =MAX(0,60-MIN(60,MAX(0,(HedgeCo!I4-ASSUMPTIONS!C70)*ASSUMPTIONS!C84*2))) -> 0 | J5: =MAX(0,60-MIN(60,MAX(0,(HedgeCo!J4-ASSUMPTIONS!C70)*ASSUMPTIONS!C84*2))) -> 0 | K5: =MAX(0,60-MIN(60,MAX(0,(HedgeCo!K4-ASSUMPTIONS!C70)*ASSUMPTIONS!C84*2))) -> 0 | L5: =MAX(0,60-MIN(60,MAX(0,(HedgeCo!L4-ASSUMPTIONS!C70)*ASSUMPTIONS!C84*2))) -> 0 | M5: =MAX(0,60-MIN(60,MAX(0,(HedgeCo!M4-ASSUMPTIONS!C70)*ASSUMPTIONS!C84*2))) -> 0
A6: Equity portfolio ($B) [BASE + TSY sale proceeds reinvested as HedgeCo scales] | B6: Long equities. Base = 15% of ProdServiceCo equity (FedCo rate suppression). PLUS proceeds from Treasury sales as basis trade scales. This is the Part IV thesis link: FinServCo sells bonds → buys equity → ProdServiceCo valuation rises. | C6: =ProdServiceCo!C6*0.15+MAX(0,HedgeCo!C4-ASSUMPTIONS!C70) -> 181.5 | D6: =ProdServiceCo!D6*0.15+MAX(0,HedgeCo!D4-ASSUMPTIONS!C70) -> 236.955 | E6: =ProdServiceCo!E6*0.15+MAX(0,HedgeCo!E4-ASSUMPTIONS!C70) -> 315.5503 | F6: =ProdServiceCo!F6*0.15+MAX(0,HedgeCo!F4-ASSUMPTIONS!C70) -> 410.90748 | G6: =ProdServiceCo!G6*0.15+MAX(0,HedgeCo!G4-ASSUMPTIONS!C70) -> 396.17 | H6: =ProdServiceCo!H6*0.15+MAX(0,HedgeCo!H4-ASSUMPTIONS!C70) -> 634.56014 | I6: =ProdServiceCo!I6*0.15+MAX(0,HedgeCo!I4-ASSUMPTIONS!C70) -> 870.86861 | J6: =ProdServiceCo!J6*0.15+MAX(0,HedgeCo!J4-ASSUMPTIONS!C70) -> 968.84709 | K6: =ProdServiceCo!K6*0.15+MAX(0,HedgeCo!K4-ASSUMPTIONS!C70) -> 1168.9858 | L6: =ProdServiceCo!L6*0.15+MAX(0,HedgeCo!L4-ASSUMPTIONS!C70) -> 1344.4137 | M6: =ProdServiceCo!M6*0.15+MAX(0,HedgeCo!M4-ASSUMPTIONS!C70) -> 1239.5823
A7: LP stake in HedgeCo ($B) [SFC: Identity 17] | B7: Pension fund LP in basis trade vehicle. = HedgeCo equity * LP fraction (ASSUMPTIONS row 67). In stress: LP losses direct hit. | C7: =ASSUMPTIONS!C67*ASSUMPTIONS!C43 -> 3 | D7: =ASSUMPTIONS!D67*ASSUMPTIONS!D43 -> 3 | E7: =ASSUMPTIONS!E67*ASSUMPTIONS!E43 -> 3.2 | F7: =ASSUMPTIONS!F67*ASSUMPTIONS!F43 -> 3.2 | G7: =ASSUMPTIONS!G67*ASSUMPTIONS!G43 -> 3 | H7: =ASSUMPTIONS!H67*ASSUMPTIONS!H43 -> 3.5 | I7: =ASSUMPTIONS!I67*ASSUMPTIONS!I43 -> 3.8 | J7: =ASSUMPTIONS!J67*ASSUMPTIONS!J43 -> 4 | ... M7: =ASSUMPTIONS!M67*ASSUMPTIONS!M43 -> 4
A8: Repo receivable from AmeriBankCo ($B) [SFC: Identity 14] | B8: FedCo reserves -> AmeriBankCo -> repo -> FinServCo. Each FedCo absorption episode loads this. | C8: =AmeriBankCo!C5 -> 50 | D8: =AmeriBankCo!D5 -> 53 | E8: =AmeriBankCo!E5 -> 56.71 | F8: =AmeriBankCo!F5 -> 61.2468 | G8: =AmeriBankCo!G5 -> 76.5585 | H8: =AmeriBankCo!H5 -> 91.8702 | I8: =AmeriBankCo!I5 -> 105.65073 | J8: =AmeriBankCo!J5 -> 116.2158 | ... M8: =AmeriBankCo!M5 -> 151.55703
A9: Private credit loans to ProdServiceCo ($B) [ILLIQUID | SFC: = ProdServiceCo!priv_credit_debt] | B9: 5-7yr lockup. Not in TIC, not in H.8. Funded via AmeriBankCo repo. SFC: mirror identity with ProdServiceCo PC debt. | C9: =ASSUMPTIONS!C75 -> 20 | D9: =C9*(1+ASSUMPTIONS!D76) -> 22 | E9: =D9*(1+ASSUMPTIONS!E76) -> 25.08 | F9: =E9*(1+ASSUMPTIONS!F76) -> 28.0896 | G9: =F9*(1+ASSUMPTIONS!G76) -> 32.864832 | H9: =G9*(1+ASSUMPTIONS!H76) -> 37.465908 | I9: =H9*(1+ASSUMPTIONS!I76) -> 42.711136 | J9: =I9*(1+ASSUMPTIONS!J76) -> 47.409361 | K9: =J9*(1+ASSUMPTIONS!K76) -> 52.150297 | ... M9: =L9*(1+ASSUMPTIONS!M76) -> 52.202447
A10: TOTAL ASSETS | B10: All on-balance-sheet assets incl. PC loans. | C10: =SUM(C5:C9) -> 314.5 | D10: =SUM(D5:D9) -> 350.4 | E10: =SUM(E5:E9) -> 400.5403 | F10: =SUM(F5:F9) -> 503.44388 | G10: =SUM(G5:G9) -> 508.59333 | H10: =SUM(H5:H9) -> 767.39624 | I10: =SUM(I5:I9) -> 1023.0305 | J10: =SUM(J5:J9) -> 1136.4723 | ... M10: =SUM(M5:M9) -> 1447.3418
A11: LIABILITIES
A12: Pension obligations TOTAL ($B) | B12: Total pension liability = stable + callable. | C12: 55 | D12: 58 | E12: 62 | F12: 67 | G12: 72 | H12: 78 | I12: 85 | J12: 90 | K12: 96 | L12: 100 | M12: 100
A13: → Callable portion ($B) = callable_frac × total [HH max redemption request] | B13: What HH can demand back. Gate fires when callable > liquid TSY assets. | C13: =ASSUMPTIONS!C77*C12 -> 2.75 | D13: =ASSUMPTIONS!D77*D12 -> 2.9 | E13: =ASSUMPTIONS!E77*E12 -> 3.72 | F13: =ASSUMPTIONS!F77*F12 -> 4.02 | G13: =ASSUMPTIONS!G77*G12 -> 7.2 | H13: =ASSUMPTIONS!H77*H12 -> 6.24 | I13: =ASSUMPTIONS!I77*I12 -> 6.8 | J13: =ASSUMPTIONS!J77*J12 -> 9 | ... M13: =ASSUMPTIONS!M77*M12 -> 22
A14: Repo payable to AmeriBankCo ($B) [SFC: Identity 14] | B14: Mirror of AmeriBankCo repo to FinServCo. | C14: =AmeriBankCo!C5 -> 50 | D14: =AmeriBankCo!D5 -> 53 | E14: =AmeriBankCo!E5 -> 56.71 | F14: =AmeriBankCo!F5 -> 61.2468 | G14: =AmeriBankCo!G5 -> 76.5585 | H14: =AmeriBankCo!H5 -> 91.8702 | I14: =AmeriBankCo!I5 -> 105.65073 | J14: =AmeriBankCo!J5 -> 116.2158 | ... M14: =AmeriBankCo!M5 -> 151.55703
A15: TOTAL LIABILITIES | B15: Pension total + repo payable. | C15: =C12+C14 -> 105 | D15: =D12+D14 -> 111 | E15: =E12+E14 -> 118.71 | F15: =F12+F14 -> 128.2468 | G15: =G12+G14 -> 148.5585 | H15: =H12+H14 -> 169.8702 | I15: =I12+I14 -> 190.65073 | J15: =J12+J14 -> 206.2158 | ... M15: =M12+M14 -> 251.55703
A16: LIQUID ASSETS = TSY portfolio only [equity excluded — not cash] | B16: Only TSY is liquid. Equity ≠ cash. Blue Owl gating is precisely because illiquid PC book > liquid TSY. | C16: =C5 -> 60 | D16: =D5 -> 35.445 | E16: =E5 -> 0 | F16: =F5 -> 0 | G16: =G5 -> 0 | H16: =H5 -> 0 | I16: =I5 -> 0 | J16: =J5 -> 0 | ... M16: =M5 -> 0
A17: HH redemption REQUEST ($B) = callable portion | B17: What HH demands back. Gate fires when this exceeds liquid assets. | C17: =C13 -> 2.75 | D17: =D13 -> 2.9 | E17: =E13 -> 3.72 | F17: =F13 -> 4.02 | G17: =G13 -> 7.2 | H17: =H13 -> 6.24 | I17: =I13 -> 6.8 | J17: =J13 -> 9 | ... M17: =M13 -> 22
A18: ACTUAL PAYOUT ($B) = MIN(liquid assets, request) [gate applied] | B18: Capped at liquid TSY. Shortfall = gated. SFC: TSY sold for payout — buyer = AmeriBankCo or FedCo. | C18: =MIN(C16,C17) -> 2.75 | D18: =MIN(D16,D17) -> 2.9 | E18: =MIN(E16,E17) -> 0 | F18: =MIN(F16,F17) -> 0 | G18: =MIN(G16,G17) -> 0 | H18: =MIN(H16,H17) -> 0 | I18: =MIN(I16,I17) -> 0 | J18: =MIN(J16,J17) -> 0 | ... M18: =MIN(M16,M17) -> 0
A19: GATE STATUS [GATE=stabilizing brake | GATE FAILED=cascade trigger] | B19: Gate is NOT automatic cascade trigger. Gate stops the fire sale. Cascade fires only if: (1) gate persists AND (2) PC defaults occur simultaneously. Single-period gate = brake, not failure. | C19: =IF(C17>C16,IF(C22>5,"GATE FAILED — cascade","GATE ON — brake"),"OK") -> OK | D19: =IF(D17>D16,IF(D22>5,"GATE FAILED — cascade","GATE ON — brake"),"OK") -> OK | E19: =IF(E17>E16,IF(E22>5,"GATE FAILED — cascade","GATE ON — brake"),"OK") -> GATE FAILED — cascade | F19: =IF(F17>F16,IF(F22>5,"GATE FAILED — cascade","GATE ON — brake"),"OK") -> GATE FAILED — cascade | G19: =IF(G17>G16,IF(G22>5,"GATE FAILED — cascade","GATE ON — brake"),"OK") -> GATE FAILED — cascade | H19: =IF(H17>H16,IF(H22>5,"GATE FAILED — cascade","GATE ON — brake"),"OK") -> GATE FAILED — cascade | I19: =IF(I17>I16,IF(I22>5,"GATE FAILED — cascade","GATE ON — brake"),"OK") -> GATE FAILED — cascade | J19: =IF(J17>J16,IF(J22>5,"GATE FAILED — cascade","GATE ON — brake"),"OK") -> GATE FAILED — cascade | ... M19: =IF(M17>M16,IF(M22>5,"GATE FAILED — cascade","GATE ON — brake"),"OK") -> GATE FAILED — cascade
A20: Gate persistence note: cascade requires illiquidity ratio > 5 AND PC default shock | B20: Single period gate = stabilization. Multi-period + PC defaults = Blue Owl cascade. This is the reviewer's brake vs trigger distinction. | C20: =MAX(0,C17-C18) -> 0 | D20: =MAX(0,D17-D18) -> 0 | E20: =MAX(0,E17-E18) -> 3.72 | F20: =MAX(0,F17-F18) -> 4.02 | G20: =MAX(0,G17-G18) -> 7.2 | H20: =MAX(0,H17-H18) -> 6.24 | I20: =MAX(0,I17-I18) -> 6.8 | J20: =MAX(0,J17-J18) -> 9 | ... M20: =MAX(0,M17-M18) -> 22
A21: FRACTIONAL MEASURES
A22: Illiquidity ratio = PC loans / liquid TSY [> 1 → gate likely] | B22: Core Blue Owl measure. Rising as PC book grows and TSY sold off. | C22: =IF(C16=0,"-",C9/C16) -> 0.33333333 | D22: =IF(D16=0,"-",D9/D16) -> 0.62067993 | E22: =IF(E16=0,"-",E9/E16) -> - | F22: =IF(F16=0,"-",F9/F16) -> - | G22: =IF(G16=0,"-",G9/G16) -> - | H22: =IF(H16=0,"-",H9/H16) -> - | I22: =IF(I16=0,"-",I9/I16) -> - | J22: =IF(J16=0,"-",J9/J16) -> - | ... M22: =IF(M16=0,"-",M9/M16) -> -
A23: FISIM / GDP | B23: Rising. κ_paper inflation without κ_real expansion. | C23: =IF(ASSUMPTIONS!C5=0,"-",C25/ASSUMPTIONS!C5) -> 0.014285714 | D23: =IF(ASSUMPTIONS!D5=0,"-",D25/ASSUMPTIONS!D5) -> 0.017421603 | E23: =IF(ASSUMPTIONS!E5=0,"-",E25/ASSUMPTIONS!E5) -> 0.020408163 | F23: =IF(ASSUMPTIONS!F5=0,"-",F25/ASSUMPTIONS!F5) -> 0.023178808 | G23: =IF(ASSUMPTIONS!G5=0,"-",G25/ASSUMPTIONS!G5) -> 0.020833333 | H23: =IF(ASSUMPTIONS!H5=0,"-",H25/ASSUMPTIONS!H5) -> 0.03 | I23: =IF(ASSUMPTIONS!I5=0,"-",I25/ASSUMPTIONS!I5) -> 0.035714286 | J23: =IF(ASSUMPTIONS!J5=0,"-",J25/ASSUMPTIONS!J5) -> 0.038095238 | ... M23: =IF(ASSUMPTIONS!M5=0,"-",M25/ASSUMPTIONS!M5) -> 0.026666667
A24: Duration mismatch (TSY / pension obligations) | B24: Falling as TSY sold to meet redemptions. | C24: =IF(C12=0,"-",C5/C12) -> 1.0909091 | D24: =IF(D12=0,"-",D5/D12) -> 0.61112069 | E24: =IF(E12=0,"-",E5/E12) -> 0 | F24: =IF(F12=0,"-",F5/F12) -> 0 | G24: =IF(G12=0,"-",G5/G12) -> 0 | H24: =IF(H12=0,"-",H5/H12) -> 0 | I24: =IF(I12=0,"-",I5/I12) -> 0 | J24: =IF(J12=0,"-",J5/J12) -> 0 | ... M24: =IF(M12=0,"-",M5/M12) -> 0
A25: FISIM spread income ($B) | B25: TSY spread + PC carry + insurance float. Counted as GDP. | C25: 4 | D25: 5 | E25: 6 | F25: 7 | G25: 6 | H25: 9 | I25: 11 | J25: 12 | K25: 13 | L25: 14 | M25: 8
A26: LP exposure / total assets | B26: Rising = more basis trade exposure inside pension system. | C26: =IF(C10=0,"-",C7/C10) -> 0.0095389507 | D26: =IF(D10=0,"-",D7/D10) -> 0.0085616438 | E26: =IF(E10=0,"-",E7/E10) -> 0.0079892086 | F26: =IF(F10=0,"-",F7/F10) -> 0.0063562199 | G26: =IF(G10=0,"-",G7/G10) -> 0.0058986224 | H26: =IF(H10=0,"-",H7/H10) -> 0.0045608772 | I26: =IF(I10=0,"-",I7/I10) -> 0.0037144544 | J26: =IF(J10=0,"-",J7/J10) -> 0.0035196636 | ... M26: =IF(M10=0,"-",M7/M10) -> 0.0027636872
A27: STRESS TRANSMISSION (Y10+)
A28: TSY portfolio MTM loss ($B) | B28: Yield spike hits TSY portfolio. | C28: 0 | D28: 0 | E28: 0 | F28: 0 | G28: 0 | H28: 0 | I28: 0 | J28: 0 | K28: 0 | L28: 0 | M28: =-L5*0.08 -> 0
A29: LP loss from HedgeCo unwind ($B) | B29: LP stake marks down. | C29: 0 | D29: 0 | E29: 0 | F29: 0 | G29: 0 | H29: 0 | I29: 0 | J29: 0 | K29: 0 | L29: 0 | M29: =-ASSUMPTIONS!M77*ASSUMPTIONS!M43*0.5 -> -1.1
A30: PrivCred default loss ($B) = PC book × shock | B30: AI/software stress. Exogenous. | C30: 0 | D30: 0 | E30: 0 | F30: 0 | G30: 0 | H30: 0 | I30: 0 | J30: 0 | K30: 0 | L30: 0 | M30: =-M9*ASSUMPTIONS!M78 -> -7.830367
A31: TOTAL STRESS LOSS ($B) | B31: Three-sided hit in stress. | C31: 0 | D31: 0 | E31: 0 | F31: 0 | G31: 0 | H31: 0 | I31: 0 | J31: 0 | K31: 0 | L31: 0 | M31: =M28+M29+M30 -> -8.930367

Sheet AmeriBankCo
A1: AmeriBankCo | Regulated Intermediary | SLR Valve | Passive Conduit
A2: Receives FedCo reserves. SLR-constrained. Routes reserves to FinServCo via repo -- not to ManuCo capex. The valve, not the decision-maker.
A3: Account / Line Item | B3: Notes / Source | C3: Y0 | D3: Y1 | E3: Y2 | F3: Y3 | G3: Y4 | H3: Y5 | I3: Y6 | J3: Y7 | K3: Y8 | L3: Y9 | M3: Y10+ Stress
A4: ASSETS
A5: Repo to FinServCo ($B) [SFC: Identity 14 = FinServCo repo payable] | B5: FedCo reserves -> AmeriBankCo -> repo -> FinServCo. SLR makes this most capital-efficient. Y0 from ASSUMPTIONS row 68. | C5: =ASSUMPTIONS!C68 -> 50 | D5: =C5*(1+ASSUMPTIONS!D69) -> 53 | E5: =D5*(1+ASSUMPTIONS!E69) -> 56.71 | F5: =E5*(1+ASSUMPTIONS!F69) -> 61.2468 | G5: =F5*(1+ASSUMPTIONS!G69) -> 76.5585 | H5: =G5*(1+ASSUMPTIONS!H69) -> 91.8702 | I5: =H5*(1+ASSUMPTIONS!I69) -> 105.65073 | J5: =I5*(1+ASSUMPTIONS!J69) -> 116.2158 | K5: =J5*(1+ASSUMPTIONS!K69) -> 125.51307 | ... M5: =L5*(1+ASSUMPTIONS!M69) -> 151.55703
A6: Treasury holdings (HQLA, $B) [SELLER 2: sold after FinServCo TSY exhausted] | B6: Starts at 30B. Sold once FinServCo TSY exhausted (HC_delta > 60B). Sequential seller chain: FinServCo first, then AmeriBankCo. | C6: =MAX(0,30-MIN(30,MAX(0,(HedgeCo!C4-ASSUMPTIONS!C70)*ASSUMPTIONS!C85*4))) -> 30 | D6: =MAX(0,30-MIN(30,MAX(0,(HedgeCo!D4-ASSUMPTIONS!C70)*ASSUMPTIONS!C85*4))) -> 5.445 | E6: =MAX(0,30-MIN(30,MAX(0,(HedgeCo!E4-ASSUMPTIONS!C70)*ASSUMPTIONS!C85*4))) -> 0 | F6: =MAX(0,30-MIN(30,MAX(0,(HedgeCo!F4-ASSUMPTIONS!C70)*ASSUMPTIONS!C85*4))) -> 0 | G6: =MAX(0,30-MIN(30,MAX(0,(HedgeCo!G4-ASSUMPTIONS!C70)*ASSUMPTIONS!C85*4))) -> 0 | H6: =MAX(0,30-MIN(30,MAX(0,(HedgeCo!H4-ASSUMPTIONS!C70)*ASSUMPTIONS!C85*4))) -> 0 | I6: =MAX(0,30-MIN(30,MAX(0,(HedgeCo!I4-ASSUMPTIONS!C70)*ASSUMPTIONS!C85*4))) -> 0 | J6: =MAX(0,30-MIN(30,MAX(0,(HedgeCo!J4-ASSUMPTIONS!C70)*ASSUMPTIONS!C85*4))) -> 0 | K6: =MAX(0,30-MIN(30,MAX(0,(HedgeCo!K4-ASSUMPTIONS!C70)*ASSUMPTIONS!C85*4))) -> 0 | L6: =MAX(0,30-MIN(30,MAX(0,(HedgeCo!L4-ASSUMPTIONS!C70)*ASSUMPTIONS!C85*4))) -> 0 | M6: =MAX(0,30-MIN(30,MAX(0,(HedgeCo!M4-ASSUMPTIONS!C70)*ASSUMPTIONS!C85*4))) -> 0
A7: Reserves at FedCo ($B) [= FedCo!reserves. AmeriBankCo = consolidated banking sector.] | B7: Full FedCo reserve liability. AmeriBankCo = consolidated US banking sector. | C7: =FedCo!C9 -> 200 | D7: =FedCo!D9 -> 200 | E7: =FedCo!E9 -> 200 | F7: =FedCo!F9 -> 200 | G7: =FedCo!G9 -> 200 | H7: =FedCo!H9 -> 200 | I7: =FedCo!I9 -> 200 | J7: =FedCo!J9 -> 200 | ... M7: =FedCo!M9 -> 200
A8: Loan book ($B) [SFC: HH mortgage + HH consumer + ManuCo debt] | B8: Wired from borrower balance sheets. AmeriBankCo asset = sum of borrower liabilities. | C8: =HouseholdCo!C11+HouseholdCo!C12+ManuCo!C9 -> 125 | D8: =HouseholdCo!D11+HouseholdCo!D12+ManuCo!D9 -> 130 | E8: =HouseholdCo!E11+HouseholdCo!E12+ManuCo!E9 -> 135 | F8: =HouseholdCo!F11+HouseholdCo!F12+ManuCo!F9 -> 141 | G8: =HouseholdCo!G11+HouseholdCo!G12+ManuCo!G9 -> 137 | H8: =HouseholdCo!H11+HouseholdCo!H12+ManuCo!H9 -> 143 | I8: =HouseholdCo!I11+HouseholdCo!I12+ManuCo!I9 -> 150 | J8: =HouseholdCo!J11+HouseholdCo!J12+ManuCo!J9 -> 154 | ... M8: =HouseholdCo!M11+HouseholdCo!M12+ManuCo!M9 -> 166
A9: TOTAL ASSETS | C9: =SUM(C5:C8) -> 405 | D9: =SUM(D5:D8) -> 388.445 | E9: =SUM(E5:E8) -> 391.71 | F9: =SUM(F5:F8) -> 402.2468 | G9: =SUM(G5:G8) -> 413.5585 | H9: =SUM(H5:H8) -> 434.8702 | I9: =SUM(I5:I8) -> 455.65073 | J9: =SUM(J5:J8) -> 470.2158 | ... M9: =SUM(M5:M8) -> 517.55703
A10: LIABILITIES
A11: Deposits from HouseholdCo ($B) [SFC: Identity 13. v2 FIX: wired to HouseholdCo r7] | B11: Household checking + savings deposits. Primary funding source. | C11: =HouseholdCo!C7 -> 70 | D11: =HouseholdCo!D7 -> 71.75 | E11: =HouseholdCo!E7 -> 73.5 | F11: =HouseholdCo!F7 -> 75.5 | G11: =HouseholdCo!G7 -> 72 | H11: =HouseholdCo!H7 -> 75 | I11: =HouseholdCo!I7 -> 77 | J11: =HouseholdCo!J7 -> 78.75 | ... M11: =HouseholdCo!M7 -> 75
A12: Deposits from ManuCo + ProdServiceCo ($B) [SFC: Identity 13 partial] | B12: Corporate deposits. SFC: HouseholdCo + ManuCo + ProdServiceCo = total domestic deposits. | C12: =ManuCo!C14*0.08+ProdServiceCo!C14*0.06 -> 12.1 | D12: =ManuCo!D14*0.08+ProdServiceCo!D14*0.06 -> 12.58 | E12: =ManuCo!E14*0.08+ProdServiceCo!E14*0.06 -> 13.12 | F12: =ManuCo!F14*0.08+ProdServiceCo!F14*0.06 -> 13.8 | G12: =ManuCo!G14*0.08+ProdServiceCo!G14*0.06 -> 12.06 | H12: =ManuCo!H14*0.08+ProdServiceCo!H14*0.06 -> 13.64 | I12: =ManuCo!I14*0.08+ProdServiceCo!I14*0.06 -> 14.84 | J12: =ManuCo!J14*0.08+ProdServiceCo!J14*0.06 -> 15.7 | ... M12: =ManuCo!M14*0.08+ProdServiceCo!M14*0.06 -> 16.04
A13: Wholesale funding ($B) | B13: FHLB advances, commercial paper. Supplemental funding. | C13: 20 | D13: 21 | E13: 21 | F13: 22 | G13: 22 | H13: 23 | I13: 23 | J13: 24 | K13: 24 | L13: 25 | M13: 24
A14: TOTAL LIABILITIES | C14: =SUM(C11:C13) -> 102.1 | D14: =SUM(D11:D13) -> 105.33 | E14: =SUM(E11:E13) -> 107.62 | F14: =SUM(F11:F13) -> 111.3 | G14: =SUM(G11:G13) -> 106.06 | H14: =SUM(H11:H13) -> 111.64 | I14: =SUM(I11:I13) -> 114.84 | J14: =SUM(J11:J13) -> 118.45 | ... M14: =SUM(M11:M13) -> 115.04
A15: EQUITY = Total Assets − Total Liabilities | B15: Residual. Grows as reserves/assets expand. Wholesale funding hardcoded; equity absorbs remainder. | C15: =C9-C14 -> 302.9 | D15: =D9-D14 -> 283.115 | E15: =E9-E14 -> 284.09 | F15: =F9-F14 -> 290.9468 | G15: =G9-G14 -> 307.4985 | H15: =H9-H14 -> 323.2302 | I15: =I9-I14 -> 340.81073 | J15: =J9-J14 -> 351.7658 | ... M15: =M9-M14 -> 402.51703
A16: SLR (simplified) = Tier1 / Total Exposure | B16: Constraint that makes repo to FinServCo capital-efficient. When binding: valve partially closes. | C16: =C9*0.08/(C9*1.05) -> 0.076190476 | D16: =D9*0.08/(D9*1.05) -> 0.076190476 | E16: =E9*0.08/(E9*1.05) -> 0.076190476 | F16: =F9*0.08/(F9*1.05) -> 0.076190476 | G16: =G9*0.08/(G9*1.05) -> 0.076190476 | H16: =H9*0.08/(H9*1.05) -> 0.076190476 | I16: =I9*0.08/(I9*1.05) -> 0.076190476 | J16: =J9*0.08/(J9*1.05) -> 0.076190476 | ... M16: =M9*0.08/(M9*1.05) -> 0.076190476
A17: Repo to FinServCo / Total Assets (routing intensity) | B17: Rising = more reserves routed to financial sector vs productive lending. The crowding-out measure. | C17: =IF(C9=0,"-",C5/C9) -> 0.12345679 | D17: =IF(D9=0,"-",D5/D9) -> 0.13644145 | E17: =IF(E9=0,"-",E5/E9) -> 0.14477547 | F17: =IF(F9=0,"-",F5/F9) -> 0.15226175 | G17: =IF(G9=0,"-",G5/G9) -> 0.18512133 | H17: =IF(H9=0,"-",H5/H9) -> 0.2112589 | I17: =IF(I9=0,"-",I5/I9) -> 0.23186779 | J17: =IF(J9=0,"-",J5/J9) -> 0.24715418 | ... M17: =IF(M9=0,"-",M5/M9) -> 0.29283155
A18: Loan book / Total Assets (productive lending share) | B18: Falling as repo grows faster than loans. AmeriBankCo increasingly a conduit, not a lender. | C18: =IF(C9=0,"-",C8/C9) -> 0.30864198 | D18: =IF(D9=0,"-",D8/D9) -> 0.33466771 | E18: =IF(E9=0,"-",E8/E9) -> 0.34464272 | F18: =IF(F9=0,"-",F8/F9) -> 0.35053107 | G18: =IF(G9=0,"-",G8/G9) -> 0.33127115 | H18: =IF(H9=0,"-",H8/H9) -> 0.32883375 | I18: =IF(I9=0,"-",I8/I9) -> 0.32919952 | J18: =IF(J9=0,"-",J8/J9) -> 0.3275092 | ... M18: =IF(M9=0,"-",M8/M9) -> 0.3207376
A20: SRF repo liability ($B) = repo borrowed from FedCo at administered rate | B20: When private repo too thin/expensive: AmeriBankCo taps SRF. FedCo mirror: SRF repo asset. SFC: = FedCo!SRF_repo_asset. | C20: =FedCo!C20 -> 0.0032 | D20: =FedCo!D20 -> 0.04484528 | E20: =FedCo!E20 -> 0.091363903 | F20: =FedCo!F20 -> 0.11061333 | G20: =FedCo!G20 -> 0.11061333 | H20: =FedCo!H20 -> 0.11061333 | I20: =FedCo!I20 -> 0.11061333 | J20: =FedCo!J20 -> 0.11061333 | ... M20: =FedCo!M20 -> 0.16341333

Sheet InsuranceCo
A1: InsuranceCo | Life Insurance + Defined Benefit Pensions | Passive Long-Duration Holder
A2: Long-duration Treasury buyer. NOT in basis trade LP chain (that's FinServCo). Liabilities = policy reserves + annuity obligations. Passive — no repo, no derivatives.
A3: Account / Line Item | B3: Notes / Source | C3: Y0 | D3: Y1 | E3: Y2 | F3: Y3 | G3: Y4 | H3: Y5 | I3: Y6 | J3: Y7 | K3: Y8 | L3: Y9 | M3: Y10+ Stress
A4: ASSETS
A5: Long-duration Treasury portfolio ($B) [SFC: GovCo holder INS_direct] | B5: Y0=27.0B (7.1% of GovCo). Grows with new issuance. Passive long-duration holder. | C5: =18*(GovCo!C16/ASSUMPTIONS!C52) -> #VALUE! | D5: =18*(GovCo!D16/ASSUMPTIONS!C52) -> #VALUE! | E5: =18*(GovCo!E16/ASSUMPTIONS!C52) -> #VALUE! | F5: =18*(GovCo!F16/ASSUMPTIONS!C52) -> #VALUE! | G5: =18*(GovCo!G16/ASSUMPTIONS!C52) -> #VALUE! | H5: =18*(GovCo!H16/ASSUMPTIONS!C52) -> #VALUE! | I5: =18*(GovCo!I16/ASSUMPTIONS!C52) -> #VALUE! | J5: =18*(GovCo!J16/ASSUMPTIONS!C52) -> #VALUE! | K5: =18*(GovCo!K16/ASSUMPTIONS!C52) -> #VALUE! | L5: =18*(GovCo!L16/ASSUMPTIONS!C52) -> #VALUE! | M5: =18*(GovCo!M16/ASSUMPTIONS!C52) -> #VALUE!
A6: Corporate bond portfolio ($B) | B6: Investment-grade corporates. Complement to Treasuries for yield pickup. | C6: =GovCo!C13*0.06 -> #VALUE! | D6: =GovCo!D13*0.06 -> #VALUE! | E6: =GovCo!E13*0.06 -> #VALUE! | F6: =GovCo!F13*0.06 -> #VALUE! | G6: =GovCo!G13*0.06 -> #VALUE! | H6: =GovCo!H13*0.06 -> #VALUE! | I6: =GovCo!I13*0.06 -> #VALUE! | J6: =GovCo!J13*0.06 -> #VALUE! | ... M6: =GovCo!M13*0.06 -> #VALUE!
A7: Equity portfolio ($B) [separate from FinServCo] | B7: Modest equity allocation. Life insurance general accounts ~10-15% equity. | C7: =ProdServiceCo!C6*0.05 -> 60.5 | D7: =ProdServiceCo!D6*0.05 -> 70.8 | E7: =ProdServiceCo!E6*0.05 -> 83.2 | F7: =ProdServiceCo!F6*0.05 -> 98 | G7: =ProdServiceCo!G6*0.05 -> 78 | H7: =ProdServiceCo!H6*0.05 -> 136.5 | I7: =ProdServiceCo!I6*0.05 -> 171 | J7: =ProdServiceCo!J6*0.05 -> 158.4 | ... M7: =ProdServiceCo!M6*0.05 -> 99
A8: TOTAL ASSETS | C8: =SUM(C5:C7) -> #VALUE! | D8: =SUM(D5:D7) -> #VALUE! | E8: =SUM(E5:E7) -> #VALUE! | F8: =SUM(F5:F7) -> #VALUE! | G8: =SUM(G5:G7) -> #VALUE! | H8: =SUM(H5:H7) -> #VALUE! | I8: =SUM(I5:I7) -> #VALUE! | J8: =SUM(J5:J7) -> #VALUE! | ... M8: =SUM(M5:M7) -> #VALUE!
A9: LIABILITIES
A10: Policy reserves + annuity obligations ($B) | B10: Long-duration liabilities. Matched against TSY portfolio. Duration: 15-20yr. | C10: =GovCo!C13*0.1 -> #VALUE! | D10: =GovCo!D13*0.1 -> #VALUE! | E10: =GovCo!E13*0.1 -> #VALUE! | F10: =GovCo!F13*0.1 -> #VALUE! | G10: =GovCo!G13*0.1 -> #VALUE! | H10: =GovCo!H13*0.1 -> #VALUE! | I10: =GovCo!I13*0.1 -> #VALUE! | J10: =GovCo!J13*0.1 -> #VALUE! | ... M10: =GovCo!M13*0.1 -> #VALUE!
A11: Short-term claims payable ($B) | B11: Current-period policy payouts. Low relative to reserve stock. | C11: 8 | D11: 8 | E11: 9 | F11: 9 | G11: 9 | H11: 10 | I11: 10 | J11: 11 | K11: 11 | L11: 12 | M11: 12
A12: TOTAL LIABILITIES | C12: =SUM(C10:C11) -> #VALUE! | D12: =SUM(D10:D11) -> #VALUE! | E12: =SUM(E10:E11) -> #VALUE! | F12: =SUM(F10:F11) -> #VALUE! | G12: =SUM(G10:G11) -> #VALUE! | H12: =SUM(H10:H11) -> #VALUE! | I12: =SUM(I10:I11) -> #VALUE! | J12: =SUM(J10:J11) -> #VALUE! | ... M12: =SUM(M10:M11) -> #VALUE!
A13: EQUITY / NET WORTH
A14: Net worth = Total Assets − Total Liabilities | C14: =C8-C12 -> #VALUE! | D14: =D8-D12 -> #VALUE! | E14: =E8-E12 -> #VALUE! | F14: =F8-F12 -> #VALUE! | G14: =G8-G12 -> #VALUE! | H14: =H8-H12 -> #VALUE! | I14: =I8-I12 -> #VALUE! | J14: =J8-J12 -> #VALUE! | ... M14: =M8-M12 -> #VALUE!
A15: FRACTIONAL MEASURES
A16: Treasury / total assets (TSY concentration) | B16: High = structural vulnerability to yield spike. Same direction as FinServCo but no basis trade feedback. | C16: =IF(C8=0,"-",C5/C8) -> #VALUE! | D16: =IF(D8=0,"-",D5/D8) -> #VALUE! | E16: =IF(E8=0,"-",E5/E8) -> #VALUE! | F16: =IF(F8=0,"-",F5/F8) -> #VALUE! | G16: =IF(G8=0,"-",G5/G8) -> #VALUE! | H16: =IF(H8=0,"-",H5/H8) -> #VALUE! | I16: =IF(I8=0,"-",I5/I8) -> #VALUE! | J16: =IF(J8=0,"-",J5/J8) -> #VALUE! | ... M16: =IF(M8=0,"-",M5/M8) -> #VALUE!
A17: Duration match (TSY / policy reserves) | B17: Should be ~1.2. Falling = duration mismatch widening. | C17: =IF(C10=0,"-",C5/C10) -> #VALUE! | D17: =IF(D10=0,"-",D5/D10) -> #VALUE! | E17: =IF(E10=0,"-",E5/E10) -> #VALUE! | F17: =IF(F10=0,"-",F5/F10) -> #VALUE! | G17: =IF(G10=0,"-",G5/G10) -> #VALUE! | H17: =IF(H10=0,"-",H5/H10) -> #VALUE! | I17: =IF(I10=0,"-",I5/I10) -> #VALUE! | J17: =IF(J10=0,"-",J5/J10) -> #VALUE! | ... M17: =IF(M10=0,"-",M5/M10) -> #VALUE!

Sheet OtherBankCo
A1: OtherBankCo | Regional + Community Banks | Passive Treasury Holders
A2: All US banks except AmeriBankCo (GSIB). Hold Treasuries for LCR/liquidity. No sponsored repo. No derivatives. Funded by retail deposits. Passive in reallocation chain.
A3: Account / Line Item | B3: Notes / Source | C3: Y0 | D3: Y1 | E3: Y2 | F3: Y3 | G3: Y4 | H3: Y5 | I3: Y6 | J3: Y7 | K3: Y8 | L3: Y9 | M3: Y10+ Stress
A4: ASSETS
A5: Treasury holdings (HQLA, $B) [RESIDUAL ABSORBER: GovCo - all named holders] | B5: Y0=0B. True residual = GovCo total minus all seven named holders. Swing buyer of new issuance and secondary market. Zero at Y0 by construction. | C5: =GovCo!C18-FedCo!C4-HedgeCo!C4-AmeriCo!C10-FinServCo!C5-AmeriBankCo!C6-HouseholdCo!C8-InsuranceCo!C5 -> #VALUE! | D5: =GovCo!D18-FedCo!D4-HedgeCo!D4-AmeriCo!D10-FinServCo!D5-AmeriBankCo!D6-HouseholdCo!D8-InsuranceCo!D5 -> #VALUE! | E5: =GovCo!E18-FedCo!E4-HedgeCo!E4-AmeriCo!E10-FinServCo!E5-AmeriBankCo!E6-HouseholdCo!E8-InsuranceCo!E5 -> #VALUE! | F5: =GovCo!F18-FedCo!F4-HedgeCo!F4-AmeriCo!F10-FinServCo!F5-AmeriBankCo!F6-HouseholdCo!F8-InsuranceCo!F5 -> #VALUE! | G5: =GovCo!G18-FedCo!G4-HedgeCo!G4-AmeriCo!G10-FinServCo!G5-AmeriBankCo!G6-HouseholdCo!G8-InsuranceCo!G5 -> #VALUE! | H5: =GovCo!H18-FedCo!H4-HedgeCo!H4-AmeriCo!H10-FinServCo!H5-AmeriBankCo!H6-HouseholdCo!H8-InsuranceCo!H5 -> #VALUE! | I5: =GovCo!I18-FedCo!I4-HedgeCo!I4-AmeriCo!I10-FinServCo!I5-AmeriBankCo!I6-HouseholdCo!I8-InsuranceCo!I5 -> #VALUE! | J5: =GovCo!J18-FedCo!J4-HedgeCo!J4-AmeriCo!J10-FinServCo!J5-AmeriBankCo!J6-HouseholdCo!J8-InsuranceCo!J5 -> #VALUE! | ... M5: =GovCo!M18-FedCo!M4-HedgeCo!M4-AmeriCo!M10-FinServCo!M5-AmeriBankCo!M6-HouseholdCo!M8-InsuranceCo!M5 -> #VALUE!
A6: Loan book ($B) | B6: Retail mortgage + SME loans. Core business. Not wired to HH/ManuCo (those go to AmeriBankCo). | C6: 80 | D6: 82 | E6: 84 | F6: 86 | G6: 82 | H6: 85 | I6: 88 | J6: 90 | K6: 92 | L6: 94 | M6: 90
A7: Reserves at FedCo ($B) | B7: Smaller share than AmeriBankCo. ~15% of FedCo total reserves. | C7: =FedCo!C9*0.15 -> 30 | D7: =FedCo!D9*0.15 -> 30 | E7: =FedCo!E9*0.15 -> 30 | F7: =FedCo!F9*0.15 -> 30 | G7: =FedCo!G9*0.15 -> 30 | H7: =FedCo!H9*0.15 -> 30 | I7: =FedCo!I9*0.15 -> 30 | J7: =FedCo!J9*0.15 -> 30 | ... M7: =FedCo!M9*0.15 -> 30
A8: TOTAL ASSETS | C8: =SUM(C5:C7) -> #VALUE! | D8: =SUM(D5:D7) -> #VALUE! | E8: =SUM(E5:E7) -> #VALUE! | F8: =SUM(F5:F7) -> #VALUE! | G8: =SUM(G5:G7) -> #VALUE! | H8: =SUM(H5:H7) -> #VALUE! | I8: =SUM(I5:I7) -> #VALUE! | J8: =SUM(J5:J7) -> #VALUE! | ... M8: =SUM(M5:M7) -> #VALUE!
A9: LIABILITIES
A10: Retail deposits ($B) | B10: Primary funding. Sticky. No wholesale funding dependency (key difference from AmeriBankCo). | C10: 60 | D10: 62 | E10: 64 | F10: 66 | G10: 64 | H10: 67 | I10: 70 | J10: 72 | K10: 74 | L10: 76 | M10: 74
A11: FHLB advances ($B) | B11: Federal Home Loan Bank borrowing. Supplemental funding. | C11: 20 | D11: 20 | E11: 21 | F11: 21 | G11: 21 | H11: 22 | I11: 22 | J11: 23 | K11: 23 | L11: 24 | M11: 24
A12: TOTAL LIABILITIES | C12: =SUM(C10:C11) -> 80 | D12: =SUM(D10:D11) -> 82 | E12: =SUM(E10:E11) -> 85 | F12: =SUM(F10:F11) -> 87 | G12: =SUM(G10:G11) -> 85 | H12: =SUM(H10:H11) -> 89 | I12: =SUM(I10:I11) -> 92 | J12: =SUM(J10:J11) -> 95 | ... M12: =SUM(M10:M11) -> 98
A13: EQUITY / NET WORTH
A14: Net worth = Total Assets − Total Liabilities | C14: =C8-C12 -> #VALUE! | D14: =D8-D12 -> #VALUE! | E14: =E8-E12 -> #VALUE! | F14: =F8-F12 -> #VALUE! | G14: =G8-G12 -> #VALUE! | H14: =H8-H12 -> #VALUE! | I14: =I8-I12 -> #VALUE! | J14: =J8-J12 -> #VALUE! | ... M14: =M8-M12 -> #VALUE!
A15: FRACTIONAL MEASURES
A16: Treasury / total assets | B16: LCR-driven. Relatively stable. No basis trade feedback. | C16: =IF(C8=0,"-",C5/C8) -> #VALUE! | D16: =IF(D8=0,"-",D5/D8) -> #VALUE! | E16: =IF(E8=0,"-",E5/E8) -> #VALUE! | F16: =IF(F8=0,"-",F5/F8) -> #VALUE! | G16: =IF(G8=0,"-",G5/G8) -> #VALUE! | H16: =IF(H8=0,"-",H5/H8) -> #VALUE! | I16: =IF(I8=0,"-",I5/I8) -> #VALUE! | J16: =IF(J8=0,"-",J5/J8) -> #VALUE! | ... M16: =IF(M8=0,"-",M5/M8) -> #VALUE!
A17: Loan book / total assets (productive lending share) | B17: Stays high — OtherBankCo is a real lender unlike AmeriBankCo post-QE. | C17: =IF(C8=0,"-",C6/C8) -> #VALUE! | D17: =IF(D8=0,"-",D6/D8) -> #VALUE! | E17: =IF(E8=0,"-",E6/E8) -> #VALUE! | F17: =IF(F8=0,"-",F6/F8) -> #VALUE! | G17: =IF(G8=0,"-",G6/G8) -> #VALUE! | H17: =IF(H8=0,"-",H6/H8) -> #VALUE! | I17: =IF(I8=0,"-",I6/I8) -> #VALUE! | J17: =IF(J8=0,"-",J6/J8) -> #VALUE! | ... M17: =IF(M8=0,"-",M6/M8) -> #VALUE!

Sheet JapanCo
A1: JapanCo | Surplus Accumulator | JapCBCo = Central Bank | JapY = Domestic Currency
A2: Account / Line Item | B2: Notes / Source | C2: Y0 | D2: Y1 | E2: Y2 | F2: Y3 | G2: Y4 | H2: Y5 | I2: Y6 | J2: Y7 | K2: Y8 | L2: Y9 | M2: Y10+ Stress
A3: ASSETS
A4: JapCBCo official FX reserves ($B) | B4: JapCBCo = JapanCo central bank. Flat since Y0 peak. Routing gap = CA surplus not here. | C4: 650 | D4: =C4+ASSUMPTIONS!D15*ASSUMPTIONS!D14 -> 650.9 | E4: =D4+ASSUMPTIONS!E15*ASSUMPTIONS!E14 -> 652.4 | F4: =E4+ASSUMPTIONS!F15*ASSUMPTIONS!F14 -> 654.2 | G4: =F4+ASSUMPTIONS!G15*ASSUMPTIONS!G14 -> 656 | H4: =G4+ASSUMPTIONS!H15*ASSUMPTIONS!H14 -> 657.95 | I4: =H4+ASSUMPTIONS!I15*ASSUMPTIONS!I14 -> 660.47 | J4: =I4+ASSUMPTIONS!J15*ASSUMPTIONS!J14 -> 662.57 | K4: =J4+ASSUMPTIONS!K15*ASSUMPTIONS!K14 -> 664.67 | ... M4: =L4+ASSUMPTIONS!M15*ASSUMPTIONS!M14 -> 667.79
A5: Deposit at GlobalBankCo ($B) | B5: State rerouting channel. SLR entry point. SFC: = GlobalBankCo!liability_to_JapanCo. | C5: 40 | D5: =C5+ASSUMPTIONS!D12*(1-ASSUMPTIONS!D13)*ASSUMPTIONS!D14 -> 57.955 | E5: =D5+ASSUMPTIONS!E12*(1-ASSUMPTIONS!E13)*ASSUMPTIONS!E14 -> 91.205 | F5: =E5+ASSUMPTIONS!F12*(1-ASSUMPTIONS!F13)*ASSUMPTIONS!F14 -> 131.945 | G5: =F5+ASSUMPTIONS!G12*(1-ASSUMPTIONS!G13)*ASSUMPTIONS!G14 -> 168.401 | H5: =G5+ASSUMPTIONS!H12*(1-ASSUMPTIONS!H13)*ASSUMPTIONS!H14 -> 212.991 | I5: =H5+ASSUMPTIONS!I12*(1-ASSUMPTIONS!I13)*ASSUMPTIONS!I14 -> 287.835 | J5: =I5+ASSUMPTIONS!J12*(1-ASSUMPTIONS!J13)*ASSUMPTIONS!J14 -> 324.585 | K5: =J5+ASSUMPTIONS!K12*(1-ASSUMPTIONS!K13)*ASSUMPTIONS!K14 -> 398.835 | ... M5: =L5+ASSUMPTIONS!M12*(1-ASSUMPTIONS!M13)*ASSUMPTIONS!M14 -> 547.335
A6: Productive capital (domestic, JapY-denominated, $B equiv) | B6: High κ_paper domestic economy. Export-led accumulation model. JapY = JapanCo domestic currency. | C6: 800 | D6: =C6*1.04 -> 832 | E6: =D6*1.04 -> 865.28 | F6: =E6*1.04 -> 899.8912 | G6: =F6*1.04 -> 935.88685 | H6: =G6*1.04 -> 973.32232 | I6: =H6*1.04 -> 1012.2552 | J6: =I6*1.04 -> 1052.7454 | K6: =J6*1.04 -> 1094.8552 | ... M6: =L6*1.04 -> 1184.1954
A7: JapInv project claims ($B) | B7: Outward project lending (BRI analog). Claims on CommodityCo sovereigns. | C7: 50 | D7: =C7+ASSUMPTIONS!D19 -> 50 | E7: =D7+ASSUMPTIONS!E19 -> 50 | F7: =E7+ASSUMPTIONS!F19 -> 50 | G7: =F7+ASSUMPTIONS!G19 -> 50 | H7: =G7+ASSUMPTIONS!H19 -> 50 | I7: =H7+ASSUMPTIONS!I19 -> 50 | J7: =I7+ASSUMPTIONS!J19 -> 50 | K7: =J7+ASSUMPTIONS!K19 -> 50 | ... M7: =L7+ASSUMPTIONS!M19 -> 50
A8: TOTAL ASSETS | C8: =SUM(C4:C7) -> 1540 | D8: =SUM(D4:D7) -> 1590.855 | E8: =SUM(E4:E7) -> 1658.885 | F8: =SUM(F4:F7) -> 1736.0362 | G8: =SUM(G4:G7) -> 1810.2878 | H8: =SUM(H4:H7) -> 1894.2633 | I8: =SUM(I4:I7) -> 2010.5602 | J8: =SUM(J4:J7) -> 2089.9004 | ... M8: =SUM(M4:M7) -> 2449.3204
A10: LIABILITIES
A11: Domestic monetary base (JapY) | C11: 400 | D11: =C11*1.03 -> 412 | E11: =D11*1.03 -> 424.36 | F11: =E11*1.03 -> 437.0908 | G11: =F11*1.03 -> 450.20352 | H11: =G11*1.03 -> 463.70963 | I11: =H11*1.03 -> 477.62092 | J11: =I11*1.03 -> 491.94955 | K11: =J11*1.03 -> 506.70803 | ... M11: =L11*1.03 -> 537.56655
A12: Sterilization bonds ($B equiv) | B12: Cost of sterilization rises with reserve stock. Political economy constraint on JapY revaluation. | C12: 200 | D12: =C12*0.98 -> 196 | E12: =D12*0.98 -> 192.08 | F12: =E12*0.98 -> 188.2384 | G12: =F12*0.98 -> 184.47363 | H12: =G12*0.98 -> 180.78416 | I12: =H12*0.98 -> 177.16848 | J12: =I12*0.98 -> 173.62511 | K12: =J12*0.98 -> 170.1526 | ... M12: =L12*0.98 -> 163.41456
A13: TOTAL LIABILITIES | C13: =SUM(C11:C12) -> 600 | D13: =SUM(D11:D12) -> 608 | E13: =SUM(E11:E12) -> 616.44 | F13: =SUM(F11:F12) -> 625.3292 | G13: =SUM(G11:G12) -> 634.67716 | H13: =SUM(H11:H12) -> 644.49379 | I13: =SUM(I11:I12) -> 654.78939 | J13: =SUM(J11:J12) -> 665.57465 | ... M13: =SUM(M11:M12) -> 700.98111
A15: FRACTIONAL MEASURES
A16: Routing gap (cumul. CA surplus - JapCBCo reserve chg, $B) | B16: Real-world: $2.7T by Y9/2025 (Setser/IMF). Dollars not in official reserves. | C16: =0 -> 0 | D16: =C16+ASSUMPTIONS!D12*(1-ASSUMPTIONS!D13) -> 199.5 | E16: =D16+ASSUMPTIONS!E12*(1-ASSUMPTIONS!E13) -> 532 | F16: =E16+ASSUMPTIONS!F12*(1-ASSUMPTIONS!F13) -> 939.4 | G16: =F16+ASSUMPTIONS!G12*(1-ASSUMPTIONS!G13) -> 1243.2 | H16: =G16+ASSUMPTIONS!H12*(1-ASSUMPTIONS!H13) -> 1586.2 | I16: =H16+ASSUMPTIONS!I12*(1-ASSUMPTIONS!I13) -> 2002 | J16: =I16+ASSUMPTIONS!J12*(1-ASSUMPTIONS!J13) -> 2247 | K16: =J16+ASSUMPTIONS!K12*(1-ASSUMPTIONS!K13) -> 2742 | ... M16: =L16+ASSUMPTIONS!M12*(1-ASSUMPTIONS!M13) -> 3880.5
A17: Private channel open? | C17: =IF(ASSUMPTIONS!C20=1,"YES","NO") -> NO | D17: =IF(ASSUMPTIONS!D20=1,"YES","NO") -> NO | E17: =IF(ASSUMPTIONS!E20=1,"YES","NO") -> NO | F17: =IF(ASSUMPTIONS!F20=1,"YES","NO") -> NO | G17: =IF(ASSUMPTIONS!G20=1,"YES","NO") -> NO | H17: =IF(ASSUMPTIONS!H20=1,"YES","NO") -> NO | I17: =IF(ASSUMPTIONS!I20=1,"YES","NO") -> NO | J17: =IF(ASSUMPTIONS!J20=1,"YES","NO") -> NO | ... M17: =IF(ASSUMPTIONS!M20=1,"YES","NO") -> NO
A18: GlobalBankCo deposit share of routing gap | C18: =IF(C16=0,"-",C5/C16) -> - | D18: =IF(D16=0,"-",D5/D16) -> 0.29050125 | E18: =IF(E16=0,"-",E5/E16) -> 0.17143797 | F18: =IF(F16=0,"-",F5/F16) -> 0.14045667 | G18: =IF(G16=0,"-",G5/G16) -> 0.13545769 | H18: =IF(H16=0,"-",H5/H16) -> 0.13427752 | I18: =IF(I16=0,"-",I5/I16) -> 0.14377373 | J18: =IF(J16=0,"-",J5/J16) -> 0.1444526 | ... M18: =IF(M16=0,"-",M5/M16) -> 0.14104755
A20: TRADE FLOWS (endogenous — two-phase Hormuz structure)
A21: Export revenue ($B/yr) [manufacturing+services — not oil-dependent] | B21: Japan exports: autos, electronics, machinery. Not directly Hormuz-affected. Mild demand reduction in Phase 2 as global growth slows. | C21: =ASSUMPTIONS!C108 -> 800 | D21: =ASSUMPTIONS!D108 -> 800 | E21: =ASSUMPTIONS!E108 -> 810 | F21: =ASSUMPTIONS!F108 -> 820 | G21: =ASSUMPTIONS!G108 -> 830 | H21: =ASSUMPTIONS!H108 -> 840 | I21: =ASSUMPTIONS!I108 -> 850 | J21: =ASSUMPTIONS!J108 -> 860 | ... M21: =ASSUMPTIONS!M108 -> 830
A22: Oil/LNG import volume index [1.0=normal, 0=Hormuz closed, 0.4=reroute] | B22: Phase 1: volume=0 (Hormuz blocked). Phase 2: 0.4 (alternate routes, Cape of Good Hope). Endogenous from ASSUMPTIONS oil_volume parameter. | C22: =ASSUMPTIONS!C106 -> 1 | D22: =ASSUMPTIONS!D106 -> 1 | E22: =ASSUMPTIONS!E106 -> 1 | F22: =ASSUMPTIONS!F106 -> 1 | G22: =ASSUMPTIONS!G106 -> 1 | H22: =ASSUMPTIONS!H106 -> 1 | I22: =ASSUMPTIONS!I106 -> 1 | J22: =ASSUMPTIONS!J106 -> 1 | ... M22: =ASSUMPTIONS!M106 -> 0.6
A23: Oil price index [1.0=normal, 2.8=Phase1 spike, 2.2=Phase2 elevated] | B23: Phase 1: global supply drops 2.5% (Hormuz = largest disruption in history). Price spikes immediately. Phase 2: moderates but stays elevated (rerouting cost premium). | C23: =ASSUMPTIONS!C107 -> 1 | D23: =ASSUMPTIONS!D107 -> 1 | E23: =ASSUMPTIONS!E107 -> 1 | F23: =ASSUMPTIONS!F107 -> 1 | G23: =ASSUMPTIONS!G107 -> 1 | H23: =ASSUMPTIONS!H107 -> 1 | I23: =ASSUMPTIONS!I107 -> 1 | J23: =ASSUMPTIONS!J107 -> 1 | ... M23: =ASSUMPTIONS!M107 -> 1.8
A24: Oil import bill ($B/yr) = volume × price × base_bill [TWO-PHASE KEY] | B24: PHASE 1: volume=0 → bill=0 → FALSE STABILIZATION. PHASE 2: volume=0.4, price=2.2 → bill=132B > normal 150B. This endogenous collapse and recovery IS the two-phase structure. | C24: =ASSUMPTIONS!C109 -> 150 | D24: =ASSUMPTIONS!D109 -> 150 | E24: =ASSUMPTIONS!E109 -> 153 | F24: =ASSUMPTIONS!F109 -> 156 | G24: =ASSUMPTIONS!G109 -> 159 | H24: =ASSUMPTIONS!H109 -> 162 | I24: =ASSUMPTIONS!I109 -> 165 | J24: =ASSUMPTIONS!J109 -> 168 | ... M24: =ASSUMPTIONS!M109 -> 162
A25: CA SURPLUS = export revenue − oil import bill [endogenous, two-phase] | B25: Phase 1: CA surplus spikes (export_rev - 0). False stabilization — accumulation accelerates. Phase 2: CA surplus compresses (export_rev - 132B). Dollar inflows slow. This drives the routing gap and GlobalBankCo deposit dynamics. | C25: =ASSUMPTIONS!C108-ASSUMPTIONS!C109 -> 650 | D25: =ASSUMPTIONS!D108-ASSUMPTIONS!D109 -> 650 | E25: =ASSUMPTIONS!E108-ASSUMPTIONS!E109 -> 657 | F25: =ASSUMPTIONS!F108-ASSUMPTIONS!F109 -> 664 | G25: =ASSUMPTIONS!G108-ASSUMPTIONS!G109 -> 671 | H25: =ASSUMPTIONS!H108-ASSUMPTIONS!H109 -> 678 | I25: =ASSUMPTIONS!I108-ASSUMPTIONS!I109 -> 685 | J25: =ASSUMPTIONS!J108-ASSUMPTIONS!J109 -> 692 | ... M25: =ASSUMPTIONS!M108-ASSUMPTIONS!M109 -> 668
A26: Routing gap contribution ($B/yr) = CA surplus − JapCBCo official accumulation | B26: Surplus not captured by official reserves routes through GlobalBankCo deposits. Phase 1: routing gap spikes (CA surplus up, official reserves constrained). Phase 2: routing gap compresses (CA surplus falls, basis trade loses funding). | C26: =(C25-12)*0.4 -> 255.2 | D26: =(D25-12)*0.4 -> 255.2 | E26: =(E25-12)*0.4 -> 258 | F26: =(F25-12)*0.4 -> 260.8 | G26: =(G25-12)*0.4 -> 263.6 | H26: =(H25-12)*0.4 -> 266.4 | I26: =(I25-12)*0.4 -> 269.2 | J26: =(J25-12)*0.4 -> 272 | ... M26: =(M25-12)*0.4 -> 262.4
A27: JapCBCo appreciation loop — break-even appreciation rate (% per year) | B27: Break-even = interest_income / JapCBCo_reserve_stock. Phase 1: false stabilization masks deterioration. Phase 2: appreciation pressure resumes as CA surplus compresses. JapCBCo at accounting limit when break-even = 0%. | C27: =IF(JapanCo!C4=0,0,(0.042*JapanCo!C4)/JapanCo!C4) -> 0.042 | D27: =IF(JapanCo!D4=0,0,(0.042*JapanCo!D4)/JapanCo!D4) -> 0.042 | E27: =IF(JapanCo!E4=0,0,(0.042*JapanCo!E4)/JapanCo!E4) -> 0.042 | F27: =IF(JapanCo!F4=0,0,(0.042*JapanCo!F4)/JapanCo!F4) -> 0.042 | G27: =IF(JapanCo!G4=0,0,(0.042*JapanCo!G4)/JapanCo!G4) -> 0.042 | H27: =IF(JapanCo!H4=0,0,(0.042*JapanCo!H4)/JapanCo!H4) -> 0.042 | I27: =IF(JapanCo!I4=0,0,(0.042*JapanCo!I4)/JapanCo!I4) -> 0.042 | J27: =IF(JapanCo!J4=0,0,(0.042*JapanCo!J4)/JapanCo!J4) -> 0.042 | ... M27: =IF(JapanCo!M4=0,0,(0.042*JapanCo!M4)/JapanCo!M4) -> 0.042
A29: FIMA repo to FedCo ($B) = TSY pledged to Fed instead of sold outright | B29: Path B bypass. JapanCo repos TSY to FedCo for dollars. Yield spike suppressed. FedCo balance sheet expands. When FIMA_active=1 in ASSUMPTIONS: fraction of official TSY goes here instead of hitting the secondary market. | C29: =IF(ASSUMPTIONS!C117=0,0,JapanCo!C4*ASSUMPTIONS!C117) -> 0 | D29: =IF(ASSUMPTIONS!D117=0,0,JapanCo!D4*ASSUMPTIONS!D117) -> 0 | E29: =IF(ASSUMPTIONS!E117=0,0,JapanCo!E4*ASSUMPTIONS!E117) -> 0 | F29: =IF(ASSUMPTIONS!F117=0,0,JapanCo!F4*ASSUMPTIONS!F117) -> 0 | G29: =IF(ASSUMPTIONS!G117=0,0,JapanCo!G4*ASSUMPTIONS!G117) -> 0 | H29: =IF(ASSUMPTIONS!H117=0,0,JapanCo!H4*ASSUMPTIONS!H117) -> 0 | I29: =IF(ASSUMPTIONS!I117=0,0,JapanCo!I4*ASSUMPTIONS!I117) -> 0 | J29: =IF(ASSUMPTIONS!J117=0,0,JapanCo!J4*ASSUMPTIONS!J117) -> 0 | ... M29: =IF(ASSUMPTIONS!M117=0,0,JapanCo!M4*ASSUMPTIONS!M117) -> 133.558
A32: JAPANCO DOMESTIC BALANCE SHEETS
A33: Account / Line Item | C33: Y0 | D33: Y1 | E33: Y2 | F33: Y3 | G33: Y4 | H33: Y5 | I33: Y6 | J33: Y7 | K33: Y8 | L33: Y9 | M33: Y10+
A35: JapHouseholdCo -- Household Sector
A36: ASSETS
A37: Financial assets (JGB + bank deposits, $B equiv) | C37: 1200 | D37: 1237 | E37: 1274 | F37: 1312 | G37: 1351 | H37: 1390 | I37: 1430 | J37: 1471 | K37: 1513 | L37: 1554 | M37: 1594
A38: of which: bank deposits | C38: 720 | D38: 742 | E38: 764 | F38: 787 | G38: 811 | H38: 834 | I38: 858 | J38: 883 | K38: 908 | L38: 932 | M38: 956
A39: of which: JGB direct holdings | C39: 360 | D39: 371 | E39: 382 | F39: 394 | G39: 405 | H39: 417 | I39: 429 | J39: 441 | K39: 454 | L39: 466 | M39: 478
A40: of which: equity/other | C40: 120 | D40: 124 | E40: 127 | F40: 131 | G40: 135 | H40: 139 | I40: 143 | J40: 147 | K40: 151 | L40: 155 | M40: 159
A41: INCOME FLOWS
A42: Wage income ($B/yr) | C42: 720 | D42: 732 | E42: 744 | F42: 758 | G42: 772 | H42: 788 | I42: 804 | J42: 822 | K42: 838 | L42: 816 | M42: 800
A43: Consumption ($B/yr) | C43: 684 | D43: 695 | E43: 707 | F43: 720 | G43: 733 | H43: 749 | I43: 764 | J43: 781 | K43: 796 | L43: 775 | M43: 760
A44: Household savings flow ($B/yr) | C44: 36 | D44: 37 | E44: 37 | F44: 38 | G44: 39 | H44: 39 | I44: 40 | J44: 41 | K44: 42 | L44: 41 | M44: 40
A45: FRACTIONAL MEASURES
A46: Consumption / GDP (%) | C46: 38 | D46: 38 | E46: 38 | F46: 38 | G46: 38 | H46: 38 | I46: 38 | J46: 38 | K46: 38 | L46: 38 | M46: 38
A47: Household savings rate (% of wage income) | C47: 5 | D47: 5.1 | E47: 5 | F47: 5 | G47: 5.1 | H47: 4.9 | I47: 5 | J47: 5 | K47: 5 | L47: 5 | M47: 5
A49: JapBankCo -- Domestic Banking Sector
A50: ASSETS
A51: JGB holdings ($B equiv) | C51: 600 | D51: 625 | E51: 650 | F51: 676 | G51: 703 | H51: 730 | I51: 758 | J51: 787 | K51: 817 | L51: 847 | M51: 878
A52: Deposit at GlobalBankCo ($B) | C52: 40 | D52: 40 | E52: 40 | F52: 40 | G52: 40 | H52: 40 | I52: 40 | J52: 40 | K52: 40 | L52: 40 | M52: 40
A53: Domestic loans ($B equiv) | C53: 260 | D53: 272 | E53: 284 | F53: 296 | G53: 308 | H53: 320 | I53: 332 | J53: 344 | K53: 356 | L53: 367 | M53: 376
A54: LIABILITIES
A55: HH deposits ($B equiv) | C55: 900 | D55: 937 | E55: 974 | F55: 1012 | G55: 1051 | H55: 1090 | I55: 1130 | J55: 1171 | K55: 1213 | L55: 1254 | M55: 1294
A56: Net worth | C56: 0 | D56: 0 | E56: 0 | F56: 0 | G56: 0 | H56: 0 | I56: 0 | J56: 0 | K56: 0 | L56: 0 | M56: 0
A58: JapGovCo -- Public Sector
A59: JGB outstanding ($B equiv) | C59: 3600 | D59: 3672 | E59: 3745 | F59: 3820 | G59: 3896 | H59: 3974 | I59: 4054 | J59: 4135 | K59: 4218 | L59: 4302 | M59: 4388
A60: Government spending ($B/yr) | C60: 540 | D60: 549 | E60: 558 | F60: 568 | G60: 579 | H60: 591 | I60: 604 | J60: 617 | K60: 629 | L60: 612 | M60: 599
A61: Government revenue ($B/yr) | C61: 468 | D61: 476 | E61: 484 | F61: 493 | G61: 502 | H61: 512 | I61: 522 | J61: 533 | K61: 545 | L61: 530 | M61: 520
A62: Fiscal deficit ($B/yr) | C62: 72 | D62: 73 | E62: 74 | F62: 75 | G62: 77 | H62: 79 | I62: 82 | J62: 84 | K62: 84 | L62: 82 | M62: 79
A63: Debt / GDP (%) | C63: 200 | D63: 201 | E63: 201 | F63: 202 | G63: 202 | H63: 202 | I63: 202 | J63: 201 | K63: 201 | L63: 211 | M63: 219
A64: Deficit rationale: compensating for suppressed domestic demand
A66: JapCBCo -- Sterilization Mechanics
A67: Sterilization bonds outstanding ($B equiv) | C67: 200 | D67: 208 | E67: 216 | F67: 224 | G67: 232 | H67: 240 | I67: 248 | J67: 256 | K67: 264 | L67: 272 | M67: 280
A68: Reserve asset return (% on FX reserves) | C68: 1.5 | D68: 1.5 | E68: 1.5 | F68: 1.5 | G68: 1.5 | H68: 1.5 | I68: 1.5 | J68: 1.5 | K68: 1.5 | L68: 1.5 | M68: 1.5
A69: Sterilization bond yield (domestic %) | C69: 2.5 | D69: 2.5 | E69: 2.5 | F69: 2.5 | G69: 2.5 | H69: 2.5 | I69: 2.5 | J69: 2.5 | K69: 2.5 | L69: 2.5 | M69: 2.5
A70: Net sterilization carry cost ($B/yr) | C70: -6.5 | D70: -6.6 | E70: -6.6 | F70: -6.7 | G70: -6.8 | H70: -6.8 | I70: -6.9 | J70: -7 | K70: -7 | L70: -7.1 | M70: -7.2
A71: [negative = JapCBCo pays more on sterilization bonds than it earns on reserves]
A73: SUPPRESSION SUMMARY -- The Mirror of AmeriCo
A74: Consumption / GDP (%) -- suppressed vs 55-60% in AmeriCo | C74: 38 | D74: 38 | E74: 38 | F74: 38 | G74: 38 | H74: 38 | I74: 38 | J74: 38 | K74: 38 | L74: 38 | M74: 38
A75: Private savings / GDP (%) -- excess savings = surplus | C75: 32 | D75: 32 | E75: 32 | F75: 32 | G75: 32 | H75: 32 | I75: 31.9 | J75: 32 | K75: 32 | L75: 32 | M75: 32
A76: JapGovCo debt / GDP (%) -- fiscal cost of demand suppression | C76: 200 | D76: 201 | E76: 201 | F76: 202 | G76: 202 | H76: 202 | I76: 202 | J76: 201 | K76: 201 | L76: 211 | M76: 219
A77: Annual sterilization cost ($B) -- cost of holding the surplus | C77: -6.5 | D77: -6.6 | E77: -6.6 | F77: -6.7 | G77: -6.8 | H77: -6.8 | I77: -6.9 | J77: -7 | K77: -7 | L77: -7.1 | M77: -7.2
A78: Cumulative sterilization cost ($B) | C78: 6 | D78: 13 | E78: 20 | F78: 26 | G78: 33 | H78: 40 | I78: 47 | J78: 54 | K78: 61 | L78: 68 | M78: 75

Sheet CommodityCo
A1: CommodityCo | Commodity Sovereign | Exogenous Shock Origin | Generic in Publication
A2: Account / Line Item | B2: Notes / Source | C2: Y0 | D2: Y1 | E2: Y2 | F2: Y3 | G2: Y4 | H2: Y5 | I2: Y6 | J2: Y7 | K2: Y8 | L2: Y9 | M2: Y10+ Stress
A3: ASSETS
A4: Deposit at GlobalBankCo ($B) | B4: Liquid dollar buffer. Withdrawal triggers DCR shock at GlobalBankCo (Path A). | C4: =ASSUMPTIONS!C22 -> 45 | D4: =C4*(1+ASSUMPTIONS!D23) -> 46.8 | E4: =D4*(1+ASSUMPTIONS!E23) -> 48.672 | F4: =E4*(1+ASSUMPTIONS!F23) -> 50.13216 | G4: =F4*(1+ASSUMPTIONS!G23) -> 47.12423 | H4: =G4*(1+ASSUMPTIONS!H23) -> 50.894169 | I4: =H4*(1+ASSUMPTIONS!I23) -> 53.947819 | J4: =I4*(1+ASSUMPTIONS!J23) -> 56.64521 | K4: =J4*(1+ASSUMPTIONS!K23) -> 59.47747 | ... M4: =L4*(1+ASSUMPTIONS!M23) -> 33.366861
A5: Direct Treasury holdings ($B) | B5: TIC-visible. Second liquidation target. Sale triggers yield spike (Path B). | C5: =ASSUMPTIONS!C24 -> 20 | D5: =C5*(1+ASSUMPTIONS!D25) -> 20.6 | E5: =D5*(1+ASSUMPTIONS!E25) -> 21.218 | F5: =E5*(1+ASSUMPTIONS!F25) -> 21.64236 | G5: =F5*(1+ASSUMPTIONS!G25) -> 20.776666 | H5: =G5*(1+ASSUMPTIONS!H25) -> 22.023266 | I5: =H5*(1+ASSUMPTIONS!I25) -> 23.124429 | J5: =I5*(1+ASSUMPTIONS!J25) -> 24.049406 | K5: =J5*(1+ASSUMPTIONS!K25) -> 25.011382 | ... M5: =L5*(1+ASSUMPTIONS!M25) -> 13.521153
A6: Commodity receivables ($B) | B6: Oil/gas/minerals. Price shock = exogenous trigger. Forces liquidation of dollar assets. | C6: =ASSUMPTIONS!C20 -> 60 | D6: =C6*(1+ASSUMPTIONS!D21) -> 54 | E6: =D6*(1+ASSUMPTIONS!E21) -> 56.7 | F6: =E6*(1+ASSUMPTIONS!F21) -> 62.37 | G6: =F6*(1+ASSUMPTIONS!G21) -> 34.3035 | H6: =G6*(1+ASSUMPTIONS!H21) -> 44.59455 | I6: =H6*(1+ASSUMPTIONS!I21) -> 53.51346 | J6: =I6*(1+ASSUMPTIONS!J21) -> 56.189133 | K6: =J6*(1+ASSUMPTIONS!K21) -> 61.808046 | ... M6: =L6*(1+ASSUMPTIONS!M21) -> 17.615293
A7: Sovereign wealth fund (equity/alts, $B) | C7: 100 | D7: =C7*1.04 -> 104 | E7: =D7*1.04 -> 108.16 | F7: =E7*1.04 -> 112.4864 | G7: =F7*1.04 -> 116.98586 | H7: =G7*1.04 -> 121.66529 | I7: =H7*1.04 -> 126.5319 | J7: =I7*1.04 -> 131.59318 | K7: =J7*1.04 -> 136.85691 | ... M7: =L7*1.04 -> 148.02443
A8: Gold reserves ($B) [Path C: outside banking chain] | C8: =ASSUMPTIONS!C26 -> 25 | D8: =C8*(1+ASSUMPTIONS!D27) -> 25 | E8: =D8*(1+ASSUMPTIONS!E27) -> 25 | F8: =E8*(1+ASSUMPTIONS!F27) -> 25 | G8: =F8*(1+ASSUMPTIONS!G27) -> 25 | H8: =G8*(1+ASSUMPTIONS!H27) -> 25 | I8: =H8*(1+ASSUMPTIONS!I27) -> 25 | J8: =I8*(1+ASSUMPTIONS!J27) -> 25 | K8: =J8*(1+ASSUMPTIONS!K27) -> 25 | L8: =K8*(1+ASSUMPTIONS!L27) -> 25 | M8: =L8*(1-ASSUMPTIONS!M28) -> 10
A9: Gold proceeds -> GBC deposit (stress yr, temp) [SFC: = GBC gold_temp_dep] | C9: 0 | D9: 0 | E9: 0 | F9: 0 | G9: 0 | H9: 0 | I9: 0 | J9: 0 | K9: 0 | L9: 0 | M9: =L8*ASSUMPTIONS!M28*ASSUMPTIONS!M29 -> 12
A10: TOTAL ASSETS
A12: LIABILITIES
A13: Sovereign debt (USD-denominated, $B) | C13: 15 | D13: =C13*1.04 -> 15.6 | E13: =D13*1.04 -> 16.224 | F13: =E13*1.04 -> 16.87296 | G13: =F13*1.04 -> 17.547878 | H13: =G13*1.04 -> 18.249794 | I13: =H13*1.04 -> 18.979785 | J13: =I13*1.04 -> 19.738977 | K13: =J13*1.04 -> 20.528536 | ... M13: =L13*1.04 -> 22.203664
A14: JapInv project obligations ($B) | B14: SFC: = JapanCo!JapInv_project_claims. Cross-actor identity. | C14: =JapanCo!C7 -> 50 | D14: =JapanCo!D7 -> 50 | E14: =JapanCo!E7 -> 50 | F14: =JapanCo!F7 -> 50 | G14: =JapanCo!G7 -> 50 | H14: =JapanCo!H7 -> 50 | I14: =JapanCo!I7 -> 50 | J14: =JapanCo!J7 -> 50 | ... M14: =JapanCo!M7 -> 50
A15: Short-term import financing ($B) | C15: 8 | D15: =C15*1.03 -> 8.24 | E15: =D15*1.03 -> 8.4872 | F15: =E15*1.03 -> 8.741816 | G15: =F15*1.03 -> 9.0040705 | H15: =G15*1.03 -> 9.2741926 | I15: =H15*1.03 -> 9.5524184 | J15: =I15*1.03 -> 9.8389909 | K15: =J15*1.03 -> 10.134161 | ... M15: =L15*1.03 -> 10.751331
A16: TOTAL LIABILITIES
A18: FRACTIONAL MEASURES
A19: CLC = L_liquid / (S_short + B_JapInv) | B19: Liquidity cliff. Below 1.2: forced liquidation. L_liquid = deposit + direct Treasury. S_short = USD sovereign debt. B_JapInv = JapInv project obligations due. | C19: =(C4+C5+C7*0.2+C8)/(C13+C14) -> 1.6923077 | D19: =(D4+D5+D7*0.2+D8)/(D13+D14) -> 1.7256098 | E19: =(E4+E5+E7*0.2+E8)/(E13+E14) -> 1.7595132 | F19: =(F4+F5+F7*0.2+F8)/(F13+F14) -> 1.783558 | G19: =(G4+G5+G7*0.2+G8)/(G13+G14) -> 1.7217131 | H19: =(H4+H5+H7*0.2+H8)/(H13+H14) -> 1.7912214 | I19: =(I4+I5+I7*0.2+I8)/(I13+I14) -> 1.8466081 | J19: =(J4+J5+J7*0.2+J8)/(J13+J14) -> 1.8929623 | ... M19: =(M4+M5+M7*0.2+M8)/(M13+M14) -> 1.1979018
A20: CLC hard constraint breach (< 1.0) -- forced liquidation is accounting consequence | C20: =IF(C19<1,"BREACH -- forced liquidation","OK") -> OK | D20: =IF(D19<1,"BREACH -- forced liquidation","OK") -> OK | E20: =IF(E19<1,"BREACH -- forced liquidation","OK") -> OK | F20: =IF(F19<1,"BREACH -- forced liquidation","OK") -> OK | G20: =IF(G19<1,"BREACH -- forced liquidation","OK") -> OK | H20: =IF(H19<1,"BREACH -- forced liquidation","OK") -> OK | I20: =IF(I19<1,"BREACH -- forced liquidation","OK") -> OK | J20: =IF(J19<1,"BREACH -- forced liquidation","OK") -> OK | ... M20: =IF(M19<1,"BREACH -- forced liquidation","OK") -> OK
A21: CLC (ex-gold): liquid w/o gold / obligations | C21: =(C4+C5+C7*0.2)/(C13+C14) -> 1.3076923 | D21: =(D4+D5+D7*0.2)/(D13+D14) -> 1.3445122 | E21: =(E4+E5+E7*0.2)/(E13+E14) -> 1.3820065 | F21: =(F4+F5+F7*0.2)/(F13+F14) -> 1.4097148 | G21: =(G4+G5+G7*0.2)/(G13+G14) -> 1.3516053 | H21: =(H4+H5+H7*0.2)/(H13+H14) -> 1.42492 | I21: =(I4+I5+I7*0.2)/(I13+I14) -> 1.4841831 | J21: =(J4+J5+J7*0.2)/(J13+J14) -> 1.5344827 | ... M21: =(M4+M5+M7*0.2)/(M13+M14) -> 1.0594047
A22: CLC early warning (< 1.2) -- buffer thinning, precautionary liquidation possible | C22: =IF(C19<1.2,IF(C19<1,"BREACH","WARNING"),"OK") -> OK | D22: =IF(D19<1.2,IF(D19<1,"BREACH","WARNING"),"OK") -> OK | E22: =IF(E19<1.2,IF(E19<1,"BREACH","WARNING"),"OK") -> OK | F22: =IF(F19<1.2,IF(F19<1,"BREACH","WARNING"),"OK") -> OK | G22: =IF(G19<1.2,IF(G19<1,"BREACH","WARNING"),"OK") -> OK | H22: =IF(H19<1.2,IF(H19<1,"BREACH","WARNING"),"OK") -> OK | I22: =IF(I19<1.2,IF(I19<1,"BREACH","WARNING"),"OK") -> OK | J22: =IF(J19<1.2,IF(J19<1,"BREACH","WARNING"),"OK") -> OK | ... M22: =IF(M19<1.2,IF(M19<1,"BREACH","WARNING"),"OK") -> WARNING
A24: TRADE FLOWS — ENDOGENOUS TWO-PHASE (mirrors JapanCo import structure)
A25: Export volume index [1.0=normal, 0=Phase1 blocked, 0.4=Phase2 reroute] | B25: Phase 1: Hormuz closed → CommodityCo cannot ship. Revenue = 0. Phase 2: alternate routes (Cape of Good Hope + overland) recover 40% volume. | C25: =ASSUMPTIONS!C110 -> 1 | D25: =ASSUMPTIONS!D110 -> 1 | E25: =ASSUMPTIONS!E110 -> 1 | F25: =ASSUMPTIONS!F110 -> 1 | G25: =ASSUMPTIONS!G110 -> 1 | H25: =ASSUMPTIONS!H110 -> 1 | I25: =ASSUMPTIONS!I110 -> 1 | J25: =ASSUMPTIONS!J110 -> 1 | ... M25: =ASSUMPTIONS!M110 -> 0.6
A26: Export price index [1.0=normal, 0=Phase1 (can't sell), 2.2=Phase2 scarcity] | B26: Phase 1: price moot — cannot export. Phase 2: scarcity premium. CommodityCo receives 2.2× normal price on whatever volume gets through. | C26: =ASSUMPTIONS!C111 -> 1 | D26: =ASSUMPTIONS!D111 -> 1 | E26: =ASSUMPTIONS!E111 -> 1 | F26: =ASSUMPTIONS!F111 -> 1 | G26: =ASSUMPTIONS!G111 -> 1 | H26: =ASSUMPTIONS!H111 -> 1 | I26: =ASSUMPTIONS!I111 -> 1 | J26: =ASSUMPTIONS!J111 -> 1 | ... M26: =ASSUMPTIONS!M111 -> 1.8
A27: Export revenue ($B/yr) = volume × price × base_revenue [TWO-PHASE CORE] | B27: Base export revenue = 60B/yr (commodity receivables Y0). Phase 1: 0×2.8×60 = 0B → CLC BREACHES immediately. Phase 2: 0.4×2.2×60 = 52.8B → partial recovery but below base. SFC: this replaces static commodity receivables (ASSUMPTIONS r20). | C27: =ASSUMPTIONS!C110*ASSUMPTIONS!C111*60 -> 60 | D27: =ASSUMPTIONS!D110*ASSUMPTIONS!D111*60 -> 60 | E27: =ASSUMPTIONS!E110*ASSUMPTIONS!E111*60 -> 60 | F27: =ASSUMPTIONS!F110*ASSUMPTIONS!F111*60 -> 60 | G27: =ASSUMPTIONS!G110*ASSUMPTIONS!G111*60 -> 60 | H27: =ASSUMPTIONS!H110*ASSUMPTIONS!H111*60 -> 60 | I27: =ASSUMPTIONS!I110*ASSUMPTIONS!I111*60 -> 60 | J27: =ASSUMPTIONS!J110*ASSUMPTIONS!J111*60 -> 60 | ... M27: =ASSUMPTIONS!M110*ASSUMPTIONS!M111*60 -> 64.8
A28: Path A trigger — deposit withdrawal from GlobalBankCo when revenue collapses | B28: Phase 1: export revenue = 0 → CommodityCo draws down GlobalBankCo deposit to cover obligations. Path A fires immediately. Withdrawal = MAX(0, obligations - export_revenue). | C28: =MAX(0,(CommodityCo!C13+CommodityCo!C14+CommodityCo!C15)-C27) -> 13 | D28: =MAX(0,(CommodityCo!D13+CommodityCo!D14+CommodityCo!D15)-D27) -> 13.84 | E28: =MAX(0,(CommodityCo!E13+CommodityCo!E14+CommodityCo!E15)-E27) -> 14.7112 | F28: =MAX(0,(CommodityCo!F13+CommodityCo!F14+CommodityCo!F15)-F27) -> 15.614776 | G28: =MAX(0,(CommodityCo!G13+CommodityCo!G14+CommodityCo!G15)-G27) -> 16.551949 | H28: =MAX(0,(CommodityCo!H13+CommodityCo!H14+CommodityCo!H15)-H27) -> 17.523986 | I28: =MAX(0,(CommodityCo!I13+CommodityCo!I14+CommodityCo!I15)-I27) -> 18.532204 | J28: =MAX(0,(CommodityCo!J13+CommodityCo!J14+CommodityCo!J15)-J27) -> 19.577968 | ... M28: =MAX(0,(CommodityCo!M13+CommodityCo!M14+CommodityCo!M15)-M27) -> 18.154995
A29: Path C trigger — gold liquidation when deposit insufficient (Phase 1 Month 2) | B29: When deposit < obligations AND Path A insufficient: gold sold. False stabilization signal: gold proceeds temporarily reload GlobalBankCo deposit. CLC appears to improve Month 2 before Path A+B fire Month 3. | C29: =MAX(0,C28-CommodityCo!C4) -> 0 | D29: =MAX(0,D28-CommodityCo!D4) -> 0 | E29: =MAX(0,E28-CommodityCo!E4) -> 0 | F29: =MAX(0,F28-CommodityCo!F4) -> 0 | G29: =MAX(0,G28-CommodityCo!G4) -> 0 | H29: =MAX(0,H28-CommodityCo!H4) -> 0 | I29: =MAX(0,I28-CommodityCo!I4) -> 0 | J29: =MAX(0,J28-CommodityCo!J4) -> 0 | ... M29: =MAX(0,M28-CommodityCo!M4) -> 0
A30: ENDOGENOUS CLC (replaces static) = liquid_assets / obligations | B30: liquid_assets = deposit + direct_TSY + SWF×0.2 + gold (if not yet sold). Endogenous: collapses in Phase1, partially recovers Phase2. Phase1 Month 1: CLC breaches. Month 2: gold props it up (false signal). Month 3: Path A+B fire as gold exhausted. | C30: =IF((C27+CommodityCo!C8)>0,(C27+CommodityCo!C4+CommodityCo!C5+CommodityCo!C7*0.2+CommodityCo!C8)/(CommodityCo!C13+CommodityCo!C14),0) -> 2.6153846 | D30: =IF((D27+CommodityCo!D8)>0,(D27+CommodityCo!D4+CommodityCo!D5+CommodityCo!D7*0.2+CommodityCo!D8)/(CommodityCo!D13+CommodityCo!D14),0) -> 2.6402439 | E30: =IF((E27+CommodityCo!E8)>0,(E27+CommodityCo!E4+CommodityCo!E5+CommodityCo!E7*0.2+CommodityCo!E8)/(CommodityCo!E13+CommodityCo!E14),0) -> 2.6655291 | F30: =IF((F27+CommodityCo!F8)>0,(F27+CommodityCo!F4+CommodityCo!F5+CommodityCo!F7*0.2+CommodityCo!F8)/(CommodityCo!F13+CommodityCo!F14),0) -> 2.6807816 | G30: =IF((G27+CommodityCo!G8)>0,(G27+CommodityCo!G4+CommodityCo!G5+CommodityCo!G7*0.2+CommodityCo!G8)/(CommodityCo!G13+CommodityCo!G14),0) -> 2.6099719 | H30: =IF((H27+CommodityCo!H8)>0,(H27+CommodityCo!H4+CommodityCo!H5+CommodityCo!H7*0.2+CommodityCo!H8)/(CommodityCo!H13+CommodityCo!H14),0) -> 2.670345 | I30: =IF((I27+CommodityCo!I8)>0,(I27+CommodityCo!I4+CommodityCo!I5+CommodityCo!I7*0.2+CommodityCo!I8)/(CommodityCo!I13+CommodityCo!I14),0) -> 2.7164281 | J30: =IF((J27+CommodityCo!J8)>0,(J27+CommodityCo!J4+CommodityCo!J5+CommodityCo!J7*0.2+CommodityCo!J8)/(CommodityCo!J13+CommodityCo!J14),0) -> 2.7533133 | ... M30: =IF((M27+CommodityCo!M8)>0,(M27+CommodityCo!M4+CommodityCo!M5+CommodityCo!M7*0.2+CommodityCo!M8)/(CommodityCo!M13+CommodityCo!M14),0) -> 2.0953632
A31: Phase 2 net effect — CommodityCo revenue vs normal base | B31: Phase2 revenue (52.8B) vs normal base (60B) = -7.2B shortfall. CommodityCo remains impaired in Phase2 even at higher prices because volume only 40%. | C31: =C27-60 -> 0 | D31: =D27-60 -> 0 | E31: =E27-60 -> 0 | F31: =F27-60 -> 0 | G31: =G27-60 -> 0 | H31: =H27-60 -> 0 | I31: =I27-60 -> 0 | J31: =J27-60 -> 0 | ... M31: =M27-60 -> 4.8

Sheet ClearCo
A1: ClearCo | Novation & Clearing Entity | Mirrors FICC CCP function
A2: Account / Line Item | B2: Notes | C2: Y0 | D2: Y1 | E2: Y2 | F2: Y3 | G2: Y4 | H2: Y5 | I2: Y6 | J2: Y7 | K2: Y8 | L2: Y9 | M2: Y10+
A3: ASSETS
A4: Novated GovCo bond collateral ($B) [SFC: = RepoCo off-balance novated Treasury r13] | B4: CCP holds novated bonds | C4: =RepoCo!C13 -> 61.68 | D4: =RepoCo!D13 -> 31.3665 | E4: =RepoCo!E13 -> 51.082605 | F4: =RepoCo!F13 -> 78.762991 | G4: =RepoCo!G13 -> 121.085 | H4: =RepoCo!H13 -> 167.78307 | I4: =RepoCo!I13 -> 306.50803 | J4: =RepoCo!J13 -> 413.02591 | ... M4: =RepoCo!M13 -> 777.16258
A5: TOTAL ASSETS | C5: =SUM(C4:C4) -> 61.68 | D5: =SUM(D4:D4) -> 31.3665 | E5: =SUM(E4:E4) -> 51.082605 | F5: =SUM(F4:F4) -> 78.762991 | G5: =SUM(G4:G4) -> 121.085 | H5: =SUM(H4:H4) -> 167.78307 | I5: =SUM(I4:I4) -> 306.50803 | J5: =SUM(J4:J4) -> 413.02591 | ... M5: =SUM(M4:M4) -> 777.16258
A7: LIABILITIES
A8: Novated repo obligation to RepoCo ($B) [SFC: = ClearCo assets -- CCP substituted as CCP] | B8: CCP owes back to RepoCo | C8: =C4 -> 61.68 | D8: =D4 -> 31.3665 | E8: =E4 -> 51.082605 | F8: =F4 -> 78.762991 | G8: =G4 -> 121.085 | H8: =H4 -> 167.78307 | I8: =I4 -> 306.50803 | J8: =J4 -> 413.02591 | ... M8: =M4 -> 777.16258
A9: TOTAL LIABILITIES | C9: =SUM(C8:C8) -> 61.68 | D9: =SUM(D8:D8) -> 31.3665 | E9: =SUM(E8:E8) -> 51.082605 | F9: =SUM(F8:F8) -> 78.762991 | G9: =SUM(G8:G8) -> 121.085 | H9: =SUM(H8:H8) -> 167.78307 | I9: =SUM(I8:I8) -> 306.50803 | J9: =SUM(J8:J8) -> 413.02591 | ... M9: =SUM(M8:M8) -> 777.16258
A11: NET POSITION (Assets - Liabilities) [Must = 0: ClearCo is pure pass-through] | C11: =C5-C9 -> 0 | D11: =D5-D9 -> 0 | E11: =E5-E9 -> 0 | F11: =F5-F9 -> 0 | G11: =G5-G9 -> 0 | H11: =H5-H9 -> 0 | I11: =I5-I9 -> 0 | J11: =J5-J9 -> 0 | ... M11: =M5-M9 -> 0
A13: ANALYTICAL NOTE
A14: Novation fraction (ASSUMPTIONS r39) -- % of repo book routed through ClearCo | C14: =ASSUMPTIONS!C39 -> 0.771 | D14: =ASSUMPTIONS!D39 -> 0.3 | E14: =ASSUMPTIONS!E39 -> 0.35 | F14: =ASSUMPTIONS!F39 -> 0.4 | G14: =ASSUMPTIONS!G39 -> 0.5 | H14: =ASSUMPTIONS!H39 -> 0.55 | I14: =ASSUMPTIONS!I39 -> 0.7 | J14: =ASSUMPTIONS!J39 -> 0.72 | ... M14: =ASSUMPTIONS!M39 -> 0.76
A15: ClearCo bonds / GlobalBankCo total repo book -- chain invisibility ratio | C15: =IF(GlobalBankCo!C4=0,"-",C4/GlobalBankCo!C4) -> 0.771 | D15: =IF(GlobalBankCo!D4=0,"-",D4/GlobalBankCo!D4) -> 0.3 | E15: =IF(GlobalBankCo!E4=0,"-",E4/GlobalBankCo!E4) -> 0.35 | F15: =IF(GlobalBankCo!F4=0,"-",F4/GlobalBankCo!F4) -> 0.4 | G15: =IF(GlobalBankCo!G4=0,"-",G4/GlobalBankCo!G4) -> 0.5 | H15: =IF(GlobalBankCo!H4=0,"-",H4/GlobalBankCo!H4) -> 0.55 | I15: =IF(GlobalBankCo!I4=0,"-",I4/GlobalBankCo!I4) -> 0.7 | J15: =IF(GlobalBankCo!J4=0,"-",J4/GlobalBankCo!J4) -> 0.72 | ... M15: =IF(GlobalBankCo!M4=0,"-",M4/GlobalBankCo!M4) -> 0.76
A16: NOTE: ClearCo holds the novated GovCo bonds as central counterparty. TIC reporting sees ClearCo (domestic CCP) not the original foreign funding chain. This is the structural reporting break -- not fraud, not concealment. The bond exists. The chain is severed at this step.

Sheet GlobalBankCo
A1: GlobalBankCo | International Bank | SLR Valve | Deposit-to-Repo Router
A2: Account / Line Item | B2: Notes / Source | C2: Y0 | D2: Y1 | E2: Y2 | F2: Y3 | G2: Y4 | H2: Y5 | I2: Y6 | J2: Y7 | K2: Y8 | L2: Y9 | M2: Y10+ Stress
A3: ASSETS
A4: Repo loans to RepoCo ($B) [SFC: = RepoCo!repo_payable_to_GlobalBankCo] | B4: Path B: SLR-constrained deposits routed to repo. SFC identity: this = RepoCo repo payable to GlobalBankCo. | C4: 80 | D4: =C4+(JapanCo!D5-JapanCo!C5)+(CommodityCo!D4-CommodityCo!C4)+C4*0.06 -> 104.555 | E4: =D4+(JapanCo!E5-JapanCo!D5)+(CommodityCo!E4-CommodityCo!D4)+D4*0.06 -> 145.9503 | F4: =E4+(JapanCo!F5-JapanCo!E5)+(CommodityCo!F4-CommodityCo!E4)+E4*0.06 -> 196.90748 | G4: =F4+(JapanCo!G5-JapanCo!F5)+(CommodityCo!G4-CommodityCo!F4)+F4*0.06 -> 242.17 | H4: =G4+(JapanCo!H5-JapanCo!G5)+(CommodityCo!H4-CommodityCo!G4)+G4*0.06 -> 305.06014 | I4: =H4+(JapanCo!I5-JapanCo!H5)+(CommodityCo!I4-CommodityCo!H4)+H4*0.18 -> 437.86861 | J4: =I4+(JapanCo!J5-JapanCo!I5)+(CommodityCo!J4-CommodityCo!I4)+I4*0.22 -> 573.64709 | K4: =J4+(JapanCo!K5-JapanCo!J5)+(CommodityCo!K4-CommodityCo!J4)+J4*0.18 -> 753.98583 | L4: =K4+(JapanCo!L5-JapanCo!K5)+(CommodityCo!L4-CommodityCo!K4)+K4*0.12 -> 928.81368 | M4: =L4+(JapanCo!M5-JapanCo!L5)+(CommodityCo!M4-CommodityCo!L4)+L4*0.06 -> 1022.5823
A5: Gold-funded additional repo to RepoCo (stress yr) [SFC: = RepoCo!gold_repo] | C5: 0 | D5: 0 | E5: 0 | F5: 0 | G5: 0 | H5: 0 | I5: 0 | J5: 0 | K5: 0 | L5: 0 | M5: =CommodityCo!M9 -> 12
A6: Direct Treasury (Path A, HQLA, $B) | B6: Path A: when SLR not binding, deposits -> direct Treasury. TIC-visible. Stable demand. | C6: 60 | D6: =C6*1.03 -> 61.8 | E6: =D6*1.03 -> 63.654 | F6: =E6*1.03 -> 65.56362 | G6: =F6*1.03 -> 67.530529 | H6: =G6*1.03 -> 69.556444 | I6: =H6*1.03 -> 71.643138 | J6: =I6*1.03 -> 73.792432 | K6: =J6*1.03 -> 76.006205 | ... M6: =L6*1.03 -> 80.634983
A7: Other loans ($B) | C7: =ASSUMPTIONS!C31 -> 25 | D7: =C7*1.02 -> 25.5 | E7: =D7*1.02 -> 26.01 | F7: =E7*1.02 -> 26.5302 | G7: =F7*1.02 -> 27.060804 | H7: =G7*1.02 -> 27.60202 | I7: =H7*1.02 -> 28.15406 | J7: =I7*1.02 -> 28.717142 | K7: =J7*1.02 -> 29.291485 | ... M7: =L7*1.02 -> 30.47486
A8: Reserves at FedCo ($B) | B8: Count toward SLR denominator. Post-COVID reserve glut constrained SLR for major banks. | C8: 40 | D8: =C8*1.01 -> 40.4 | E8: =D8*1.01 -> 40.804 | F8: =E8*1.01 -> 41.21204 | G8: =F8*1.01 -> 41.62416 | H8: =G8*1.01 -> 42.040402 | I8: =H8*1.01 -> 42.460806 | J8: =I8*1.01 -> 42.885414 | K8: =J8*1.01 -> 43.314268 | ... M8: =L8*1.01 -> 44.184885
A9: TOTAL ASSETS | C9: =SUM(C4:C8) -> 205 | D9: =SUM(D4:D8) -> 232.255 | E9: =SUM(E4:E8) -> 276.4183 | F9: =SUM(F4:F8) -> 330.21334 | G9: =SUM(G4:G8) -> 378.38549 | H9: =SUM(H4:H8) -> 444.259 | I9: =SUM(I4:I8) -> 580.12661 | J9: =SUM(J4:J8) -> 719.04208 | ... M9: =SUM(M4:M8) -> 1189.8771
A11: LIABILITIES
A12: Deposits from JapanCo ($B) [SFC: = JapanCo!deposit_at_GlobalBankCo] | B12: SFC identity enforced by formula. BIS LBS code G proxy (loans+deposits, inseparable -- structural BIS limitation). | C12: =JapanCo!C5 -> 40 | D12: =JapanCo!D5 -> 57.955 | E12: =JapanCo!E5 -> 91.205 | F12: =JapanCo!F5 -> 131.945 | G12: =JapanCo!G5 -> 168.401 | H12: =JapanCo!H5 -> 212.991 | I12: =JapanCo!I5 -> 287.835 | J12: =JapanCo!J5 -> 324.585 | ... M12: =JapanCo!M5 -> 547.335
A13: Deposits from CommodityCo ($B) [SFC: = CommodityCo!deposit_at_GlobalBankCo] | B13: Second sovereign deposit source. Withdrawal at stress = CLC breach trigger. | C13: =CommodityCo!C4 -> 45 | D13: =CommodityCo!D4 -> 46.8 | E13: =CommodityCo!E4 -> 48.672 | F13: =CommodityCo!F4 -> 50.13216 | G13: =CommodityCo!G4 -> 47.12423 | H13: =CommodityCo!H4 -> 50.894169 | I13: =CommodityCo!I4 -> 53.947819 | J13: =CommodityCo!J4 -> 56.64521 | ... M13: =CommodityCo!M4 -> 33.366861
A14: Gold proceeds temp deposit (stress yr) [SFC: = CommodityCo!gold_proceeds] | C14: 0 | D14: 0 | E14: 0 | F14: 0 | G14: 0 | H14: 0 | I14: 0 | J14: 0 | K14: 0 | L14: 0 | M14: =CommodityCo!M9 -> 12
A15: Wholesale funding ($B) | C15: 100 | D15: =C13*1.02 -> 45.9 | E15: =D13*1.02 -> 47.736 | F15: =E13*1.02 -> 49.64544 | G15: =F13*1.02 -> 51.134803 | H15: =G13*1.02 -> 48.066715 | I15: =H13*1.02 -> 51.912052 | J15: =I13*1.02 -> 55.026775 | K15: =J13*1.02 -> 57.778114 | ... M15: =L13*1.02 -> 61.88036
A16: Other liabilities ($B) | C16: 40 | D16: =C14*1.01 -> 0 | E16: =D14*1.01 -> 0 | F16: =E14*1.01 -> 0 | G16: =F14*1.01 -> 0 | H16: =G14*1.01 -> 0 | I16: =H14*1.01 -> 0 | J16: =I14*1.01 -> 0 | K16: =J14*1.01 -> 0 | ... M16: =L14*1.01 -> 0
A17: TOTAL LIABILITIES
A19: FRACTIONAL MEASURES
A20: DCR = (Dep_JapanCo + Dep_CommodityCo) / Repo_book | B20: Deposit Coverage Ratio. DCR < 1 = repo book exceeds sovereign deposit base. DCR decline signals withdrawal risk. Pressure gauge for Path A trigger. | C20: =IF(C4=0,"-",(C11+C12)/C4) -> 0.5 | D20: =IF(D4=0,"-",(D11+D12)/D4) -> 0.55430156 | E20: =IF(E4=0,"-",(E11+E12)/E4) -> 0.62490451 | F20: =IF(F4=0,"-",(F11+F12)/F4) -> 0.67008628 | G20: =IF(G4=0,"-",(G11+G12)/G4) -> 0.69538342 | H20: =IF(H4=0,"-",(H11+H12)/H4) -> 0.69819349 | I20: =IF(I4=0,"-",(I11+I12)/I4) -> 0.65735473 | J20: =IF(J4=0,"-",(J11+J12)/J4) -> 0.56582697 | ... M20: =IF(M4=0,"-",(M11+M12)/M4) -> 0.53524785
A21: SLR (simplified) = Tier1 / Total Exposure | B21: Simplified SLR. Tier1 ~8% of assets. Total exposure = total assets + off-BS items. Minimum 5% (US GSIBs). SLR reform Nov 2025 changes denominator. | C21: =C9*0.08/(C9*1.05) -> 0.076190476 | D21: =D9*0.08/(D9*1.05) -> 0.076190476 | E21: =E9*0.08/(E9*1.05) -> 0.076190476 | F21: =F9*0.08/(F9*1.05) -> 0.076190476 | G21: =G9*0.08/(G9*1.05) -> 0.076190476 | H21: =H9*0.08/(H9*1.05) -> 0.076190476 | I21: =I9*0.08/(I9*1.05) -> 0.076190476 | J21: =J9*0.08/(J9*1.05) -> 0.076190476 | ... M21: =M9*0.08/(M9*1.05) -> 0.076190476
A22: SLR binding? (< constraint threshold = YES) | C22: =IF(C21<ASSUMPTIONS!C34,"YES","NO") -> NO | D22: =IF(D21<ASSUMPTIONS!D34,"YES","NO") -> NO | E22: =IF(E21<ASSUMPTIONS!E34,"YES","NO") -> NO | F22: =IF(F21<ASSUMPTIONS!F34,"YES","NO") -> NO | G22: =IF(G21<ASSUMPTIONS!G34,"YES","NO") -> NO | H22: =IF(H21<ASSUMPTIONS!H34,"YES","NO") -> NO | I22: =IF(I21<ASSUMPTIONS!I34,"YES","NO") -> NO | J22: =IF(J21<ASSUMPTIONS!J34,"YES","NO") -> NO | ... M22: =IF(M21<ASSUMPTIONS!M34,"YES","NO") -> NO
A23: AUGMENTED COVERAGE RATIO (ACR): DCR + gold proceeds / Repo book -- TEMPORARY FALSE STABILIZATION signal. NOT baseline DCR. Rises in stress year before Path A/B fire. | C23: =IF(C4=0,"-",(C11+C12+C13)/C4) -> 1.0625 | D23: =IF(D4=0,"-",(D11+D12+D13)/D4) -> 1.0019129 | E23: =IF(E4=0,"-",(E11+E12+E13)/E4) -> 0.95838789 | F23: =IF(F4=0,"-",(F11+F12+F13)/F4) -> 0.92468383 | G23: =IF(G4=0,"-",(G11+G12+G13)/G4) -> 0.88997495 | H23: =IF(H4=0,"-",(H11+H12+H13)/H4) -> 0.86502672 | I23: =IF(I4=0,"-",(I11+I12+I13)/I4) -> 0.78056022 | J23: =IF(J4=0,"-",(J11+J12+J13)/J4) -> 0.66457272 | ... M23: =IF(M4=0,"-",(M11+M12+M13)/M4) -> 0.56787785
A25: CONFIDENCE SPILLOVER (Blue Owl mechanism)
A26: Funding cost increment when FinServCo gate ON ($B equiv stress) | B26: When FinServCo gates: investors reprice similar funds. GlobalBankCo wholesale funding cost rises (confidence spillover). Compresses repo spread → HedgeCo basis trade less viable. | C26: =IF(FinServCo!C17>FinServCo!C16,ASSUMPTIONS!C101*GlobalBankCo!C9,0) -> 0 | D26: =IF(FinServCo!D17>FinServCo!D16,ASSUMPTIONS!D101*GlobalBankCo!D9,0) -> 0 | E26: =IF(FinServCo!E17>FinServCo!E16,ASSUMPTIONS!E101*GlobalBankCo!E9,0) -> 0 | F26: =IF(FinServCo!F17>FinServCo!F16,ASSUMPTIONS!F101*GlobalBankCo!F9,0) -> 0 | G26: =IF(FinServCo!G17>FinServCo!G16,ASSUMPTIONS!G101*GlobalBankCo!G9,0) -> 0 | H26: =IF(FinServCo!H17>FinServCo!H16,ASSUMPTIONS!H101*GlobalBankCo!H9,0) -> 0 | I26: =IF(FinServCo!I17>FinServCo!I16,ASSUMPTIONS!I101*GlobalBankCo!I9,0) -> 0 | J26: =IF(FinServCo!J17>FinServCo!J16,ASSUMPTIONS!J101*GlobalBankCo!J9,0) -> 0 | ... M26: =IF(FinServCo!M17>FinServCo!M16,ASSUMPTIONS!M101*GlobalBankCo!M9,0) -> 17.848156
A27: Effective basis trade spread compression ($B) = funding shock × HedgeCo leverage | B27: Funding cost shock ripples through repo chain. Each basis point of funding cost = HedgeCo carry compressed. | C27: =C26*HedgeCo!C17 -> 0 | D27: =D26*HedgeCo!D17 -> 0 | E27: =E26*HedgeCo!E17 -> 0 | F27: =F26*HedgeCo!F17 -> 0 | G27: =G26*HedgeCo!G17 -> 0 | H27: =H26*HedgeCo!H17 -> 0 | I27: =I26*HedgeCo!I17 -> 0 | J27: =J26*HedgeCo!J17 -> 0 | ... M27: =M26*HedgeCo!M17 -> 4219.1959
A29: ROUTING GAP LINKAGE — JapanCo two-phase dynamics feed GlobalBankCo deposit base
A30: JapanCo CA surplus (endogenous) = export_rev − oil_import_bill | B30: Phase1: CA surplus spikes (import bill=0). Phase2: CA surplus compresses. This drives the change in GlobalBankCo deposit base each year. | C30: =JapanCo!C25 -> 650 | D30: =JapanCo!D25 -> 650 | E30: =JapanCo!E25 -> 657 | F30: =JapanCo!F25 -> 664 | G30: =JapanCo!G25 -> 671 | H30: =JapanCo!H25 -> 678 | I30: =JapanCo!I25 -> 685 | J30: =JapanCo!J25 -> 692 | ... M30: =JapanCo!M25 -> 668
A31: CommodityCo deposit withdrawal (Path A) = MAX(0, obligations - revenue) | B31: Phase1: CommodityCo draws down deposit. Phase2: partial recovery. Direct drain on GlobalBankCo deposit base. | C31: =CommodityCo!C28 -> 13 | D31: =CommodityCo!D28 -> 13.84 | E31: =CommodityCo!E28 -> 14.7112 | F31: =CommodityCo!F28 -> 15.614776 | G31: =CommodityCo!G28 -> 16.551949 | H31: =CommodityCo!H28 -> 17.523986 | I31: =CommodityCo!I28 -> 18.532204 | J31: =CommodityCo!J28 -> 19.577968 | ... M31: =CommodityCo!M28 -> 18.154995
A32: Net deposit change = JapanCo routing + CommodityCo withdrawal | B32: Phase1 net: JapanCo routing rises (CA surplus up) BUT CommodityCo withdraws. Phase2 net: JapanCo routing falls (CA surplus compresses) AND CommodityCo still impaired. Net effect on basis trade funding visible here. | C32: =JapanCo!C26-CommodityCo!C28 -> 242.2 | D32: =JapanCo!D26-CommodityCo!D28 -> 241.36 | E32: =JapanCo!E26-CommodityCo!E28 -> 243.2888 | F32: =JapanCo!F26-CommodityCo!F28 -> 245.18522 | G32: =JapanCo!G26-CommodityCo!G28 -> 247.04805 | H32: =JapanCo!H26-CommodityCo!H28 -> 248.87601 | I32: =JapanCo!I26-CommodityCo!I28 -> 250.6678 | J32: =JapanCo!J26-CommodityCo!J28 -> 252.42203 | ... M32: =JapanCo!M26-CommodityCo!M28 -> 244.245
A33: Basis trade funding pressure (Phase1=expanding, Phase2=contracting) | B33: Phase1: JapanCo routing spike → more GlobalBankCo deposits → more repo capacity → HedgeCo basis trade EXPANDS (false stabilization amplifies the trade). Phase2: routing compresses → repo tightens → HedgeCo margin pressure. | C33: =IF(C32>0,"EXPANDING — basis trade inflates","CONTRACTING — repo tightens") -> EXPANDING — basis trade inflates | D33: =IF(D32>0,"EXPANDING — basis trade inflates","CONTRACTING — repo tightens") -> EXPANDING — basis trade inflates | E33: =IF(E32>0,"EXPANDING — basis trade inflates","CONTRACTING — repo tightens") -> EXPANDING — basis trade inflates | F33: =IF(F32>0,"EXPANDING — basis trade inflates","CONTRACTING — repo tightens") -> EXPANDING — basis trade inflates | G33: =IF(G32>0,"EXPANDING — basis trade inflates","CONTRACTING — repo tightens") -> EXPANDING — basis trade inflates | H33: =IF(H32>0,"EXPANDING — basis trade inflates","CONTRACTING — repo tightens") -> EXPANDING — basis trade inflates | I33: =IF(I32>0,"EXPANDING — basis trade inflates","CONTRACTING — repo tightens") -> EXPANDING — basis trade inflates | J33: =IF(J32>0,"EXPANDING — basis trade inflates","CONTRACTING — repo tightens") -> EXPANDING — basis trade inflates | ... M33: =IF(M32>0,"EXPANDING — basis trade inflates","CONTRACTING — repo tightens") -> EXPANDING — basis trade inflates
A34: JapanCo routing increment vs prior year ($B) [sign arithmetic — Phase1 vs Phase2] | B34: Explicit arithmetic: positive = more funding arriving, negative = funding decelerating. Phase1(Y8): +168B (import bill collapses → CA surplus spikes). Phase2(Y9): -152B (import bill recovers 132B → CA surplus compresses). This IS the mechanism: Phase1 net positive, Phase2 net negative. | C34: 0 | D34: =JapanCo!D25-JapanCo!C25 -> 0 | E34: =JapanCo!E25-JapanCo!D25 -> 7 | F34: =JapanCo!F25-JapanCo!E25 -> 7 | G34: =JapanCo!G25-JapanCo!F25 -> 7 | H34: =JapanCo!H25-JapanCo!G25 -> 7 | I34: =JapanCo!I25-JapanCo!H25 -> 7 | J34: =JapanCo!J25-JapanCo!I25 -> 7 | K34: =JapanCo!K25-JapanCo!J25 -> 168 | ... M34: =JapanCo!M25-JapanCo!L25 -> -40
A35: CommodityCo deposit change vs prior year ($B) [negative = withdrawal] | B35: Phase1(Y8): deposit drains as Path A fires (revenue=0, obligations persist). Phase2(Y9): partial recovery (revenue=52.8B partially covers obligations). | C35: 0 | D35: =CommodityCo!D4-CommodityCo!C4 -> 1.8 | E35: =CommodityCo!E4-CommodityCo!D4 -> 1.872 | F35: =CommodityCo!F4-CommodityCo!E4 -> 1.46016 | G35: =CommodityCo!G4-CommodityCo!F4 -> -3.0079296 | H35: =CommodityCo!H4-CommodityCo!G4 -> 3.7699384 | I35: =CommodityCo!I4-CommodityCo!H4 -> 3.0536501 | J35: =CommodityCo!J4-CommodityCo!I4 -> 2.6973909 | K35: =CommodityCo!K4-CommodityCo!J4 -> 2.8322605 | ... M35: =CommodityCo!M4-CommodityCo!L4 -> -27.300159
A36: NET DEALER FUNDING CHANGE ($B) = JapanCo increment + CommodityCo change | B36: Phase1(Y8): net positive — JapanCo inflow exceeds CommodityCo withdrawal. Basis trade expands. This is the false stabilization. Phase2(Y9): net negative — JapanCo increment falls, CommodityCo still impaired. Second derivative turns negative: funding still positive in level but no longer expanding. | C36: =C34+C35 -> 0 | D36: =D34+D35 -> 1.8 | E36: =E34+E35 -> 8.872 | F36: =F34+F35 -> 8.46016 | G36: =G34+G35 -> 3.9920704 | H36: =H34+H35 -> 10.769938 | I36: =I34+I35 -> 10.05365 | J36: =J34+J35 -> 9.6973909 | ... M36: =M34+M35 -> -67.300159
A37: NET FUNDING SIGN [EXPANDING = basis trade can grow | CONTRACTING = margin pressure] | B37: Ties Phase2 to the specific mechanism: repo capacity tightens as funding inflow decelerates while CommodityCo withdrawals persist. HedgeCo must fund same Treasury inventory with less stable support. Futures variation margin begins to bite. | C37: =IF(C36>0,"EXPANDING","CONTRACTING") -> CONTRACTING | D37: =IF(D36>0,"EXPANDING","CONTRACTING") -> EXPANDING | E37: =IF(E36>0,"EXPANDING","CONTRACTING") -> EXPANDING | F37: =IF(F36>0,"EXPANDING","CONTRACTING") -> EXPANDING | G37: =IF(G36>0,"EXPANDING","CONTRACTING") -> EXPANDING | H37: =IF(H36>0,"EXPANDING","CONTRACTING") -> EXPANDING | I37: =IF(I36>0,"EXPANDING","CONTRACTING") -> EXPANDING | J37: =IF(J36>0,"EXPANDING","CONTRACTING") -> EXPANDING | ... M37: =IF(M36>0,"EXPANDING","CONTRACTING") -> CONTRACTING

Sheet RepoCo
A1: RepoCo | Repo Desk | FICC Member | TIC Chain Break Point
A2: Account / Line Item | B2: Notes / Source | C2: Y0 | D2: Y1 | E2: Y2 | F2: Y3 | G2: Y4 | H2: Y5 | I2: Y6 | J2: Y7 | K2: Y8 | L2: Y9 | M2: Y10+ Stress
A3: ASSETS (on balance sheet)
A4: [REMOVED] Treasury collateral -- NOT on RepoCo balance sheet. RepoCo holds cash loan only. Treasury sits on HedgeCo.
A5: Repo loan to HedgeCo ($B) [CASH CLAIM, not bond. SFC: = HedgeCo!repo_payable_to_RepoCo] | B5: RepoCo lent cash to HedgeCo. HedgeCo posted Treasury as collateral. The BOND is on HedgeCo balance sheet -- RepoCo holds only the cash receivable. | C5: =GlobalBankCo!C4 -> 80 | D5: =GlobalBankCo!D4 -> 104.555 | E5: =GlobalBankCo!E4 -> 145.9503 | F5: =GlobalBankCo!F4 -> 196.90748 | G5: =GlobalBankCo!G4 -> 242.17 | H5: =GlobalBankCo!H4 -> 305.06014 | I5: =GlobalBankCo!I4 -> 437.86861 | J5: =GlobalBankCo!J4 -> 573.64709 | ... M5: =GlobalBankCo!M4 -> 1022.5823
A6: Gold-funded additional repo recv from GBC (stress yr) | C6: 0 | D6: 0 | E6: 0 | F6: 0 | G6: 0 | H6: 0 | I6: 0 | J6: 0 | K6: 0 | L6: 0 | M6: =GlobalBankCo!M5 -> 12
A7: TOTAL ASSETS (on balance sheet) | C7: =SUM(C5:C6) -> 80 | D7: =SUM(D5:D6) -> 104.555 | E7: =SUM(E5:E6) -> 145.9503 | F7: =SUM(F5:F6) -> 196.90748 | G7: =SUM(G5:G6) -> 242.17 | H7: =SUM(H5:H6) -> 305.06014 | I7: =SUM(I5:I6) -> 437.86861 | J7: =SUM(J5:J6) -> 573.64709 | ... M7: =SUM(M5:M6) -> 1034.5823
A9: LIABILITIES (on balance sheet)
A10: Repo payable to GlobalBankCo ($B) [SFC: = GlobalBankCo!repo_loans_to_RepoCo] | B10: SFC identity: must equal GlobalBankCo repo loans to RepoCo. | C10: =GlobalBankCo!C4 -> 80 | D10: =GlobalBankCo!D4 -> 104.555 | E10: =GlobalBankCo!E4 -> 145.9503 | F10: =GlobalBankCo!F4 -> 196.90748 | G10: =GlobalBankCo!G4 -> 242.17 | H10: =GlobalBankCo!H4 -> 305.06014 | I10: =GlobalBankCo!I4 -> 437.86861 | J10: =GlobalBankCo!J4 -> 573.64709 | ... M10: =GlobalBankCo!M4 -> 1022.5823
A12: DERIVATIVE / OFF-BALANCE-SHEET (FICC novation -- TIC chain break)
A13: Treasury collateral (post-FICC novation, OFF books, $B) | B13: CRITICAL: After FICC novation, these Treasuries move to FICC CCP. TIC reporting stops here. Foreign funding origin invisible. This is the structural source of the $1.4T Barth-Beltran gap. | C13: =GlobalBankCo!C4*ASSUMPTIONS!C39 -> 61.68 | D13: =GlobalBankCo!D4*ASSUMPTIONS!D39 -> 31.3665 | E13: =GlobalBankCo!E4*ASSUMPTIONS!E39 -> 51.082605 | F13: =GlobalBankCo!F4*ASSUMPTIONS!F39 -> 78.762991 | G13: =GlobalBankCo!G4*ASSUMPTIONS!G39 -> 121.085 | H13: =GlobalBankCo!H4*ASSUMPTIONS!H39 -> 167.78307 | I13: =GlobalBankCo!I4*ASSUMPTIONS!I39 -> 306.50803 | J13: =GlobalBankCo!J4*ASSUMPTIONS!J39 -> 413.02591 | ... M13: =GlobalBankCo!M4*ASSUMPTIONS!M39 -> 777.16258
A15: FRACTIONAL MEASURES
A16: Repo loan / GlobalBankCo total repo book (chain coverage check) | B16: Should = 1.0 at all times: RepoCo repo loan = GlobalBankCo repo book. Confirms cash flow integrity. | C16: =IF(GlobalBankCo!C4=0,"-",C5/GlobalBankCo!C4) -> 1 | D16: =IF(GlobalBankCo!D4=0,"-",D5/GlobalBankCo!D4) -> 1 | E16: =IF(GlobalBankCo!E4=0,"-",E5/GlobalBankCo!E4) -> 1 | F16: =IF(GlobalBankCo!F4=0,"-",F5/GlobalBankCo!F4) -> 1 | G16: =IF(GlobalBankCo!G4=0,"-",G5/GlobalBankCo!G4) -> 1 | H16: =IF(GlobalBankCo!H4=0,"-",H5/GlobalBankCo!H4) -> 1 | I16: =IF(GlobalBankCo!I4=0,"-",I5/GlobalBankCo!I4) -> 1 | J16: =IF(GlobalBankCo!J4=0,"-",J5/GlobalBankCo!J4) -> 1 | ... M16: =IF(GlobalBankCo!M4=0,"-",M5/GlobalBankCo!M4) -> 1
A17: TIC gap at RepoCo = novated Treasury / total repo book | B17: Fraction of repo book where TIC chain is broken. Rising with FICC novation fraction assumption. | C17: =ASSUMPTIONS!C39 -> 0.771 | D17: =ASSUMPTIONS!D39 -> 0.3 | E17: =ASSUMPTIONS!E39 -> 0.35 | F17: =ASSUMPTIONS!F39 -> 0.4 | G17: =ASSUMPTIONS!G39 -> 0.5 | H17: =ASSUMPTIONS!H39 -> 0.55 | I17: =ASSUMPTIONS!I39 -> 0.7 | J17: =ASSUMPTIONS!J39 -> 0.72 | ... M17: =ASSUMPTIONS!M39 -> 0.76

Sheet HedgeCo
A1: HedgeCo | Basis Trade Vehicle | Cayman-Registered | 20-50x Leverage
A2: Account / Line Item | B2: Notes / Source | C2: Y0 | D2: Y1 | E2: Y2 | F2: Y3 | G2: Y4 | H2: Y5 | I2: Y6 | J2: Y7 | K2: Y8 | L2: Y9 | M2: Y10+ Stress
A3: ASSETS (on balance sheet)
A4: Long cash Treasury, repo-funded ($B) | B4: Long leg of basis trade. Funded by repo from RepoCo. NOT in TIC (Cayman + FICC novation breaks chain). | C4: =RepoCo!C5 -> 80 | D4: =RepoCo!D5 -> 104.555 | E4: =RepoCo!E5 -> 145.9503 | F4: =RepoCo!F5 -> 196.90748 | G4: =RepoCo!G5 -> 242.17 | H4: =RepoCo!H5 -> 305.06014 | I4: =RepoCo!I5 -> 437.86861 | J4: =RepoCo!J5 -> 573.64709 | ... M4: =RepoCo!M5 -> 1022.5823
A5: Gold-funded additional cash Treasury (stress yr) [Path C recycled] | C5: 0 | D5: 0 | E5: 0 | F5: 0 | G5: 0 | H5: 0 | I5: 0 | J5: 0 | K5: 0 | L5: 0 | M5: =RepoCo!M6 -> 12
A6: Margin posted at exchange ($B) | B6: Small fraction of gross notional. Varies daily with mark-to-market. | C6: =C4*ASSUMPTIONS!C41*0.015 -> 2.112 | D6: =D4*ASSUMPTIONS!D41*0.015 -> 2.0388225 | E6: =E4*ASSUMPTIONS!E41*0.015 -> 2.8460309 | F6: =F4*ASSUMPTIONS!F41*0.015 -> 3.8396958 | G6: =G4*ASSUMPTIONS!G41*0.015 -> 4.7223149 | H6: =H4*ASSUMPTIONS!H41*0.015 -> 5.9486726 | I6: =I4*ASSUMPTIONS!I41*0.015 -> 8.5384379 | J6: =J4*ASSUMPTIONS!J41*0.015 -> 11.186118 | ... M6: =M4*ASSUMPTIONS!M41*0.015 -> 19.940356
A7: TOTAL ASSETS (on balance sheet) | C7: =SUM(C4:C6) -> 82.112 | D7: =SUM(D4:D6) -> 106.59382 | E7: =SUM(E4:E6) -> 148.79633 | F7: =SUM(F4:F6) -> 200.74717 | G7: =SUM(G4:G6) -> 246.89231 | H7: =SUM(H4:H6) -> 311.00881 | I7: =SUM(I4:I6) -> 446.40705 | J7: =SUM(J4:J6) -> 584.83321 | ... M7: =SUM(M4:M6) -> 1054.5227
A9: LIABILITIES (on balance sheet)
A10: Repo payable to RepoCo ($B) [SFC: = RepoCo!repo_receivable_from_HedgeCo] | B10: SFC identity: must equal RepoCo repo receivable from HedgeCo. If called by RepoCo, HedgeCo must sell cash Treasuries immediately. | C10: =RepoCo!C5 -> 80 | D10: =RepoCo!D5 -> 104.555 | E10: =RepoCo!E5 -> 145.9503 | F10: =RepoCo!F5 -> 196.90748 | G10: =RepoCo!G5 -> 242.17 | H10: =RepoCo!H5 -> 305.06014 | I10: =RepoCo!I5 -> 437.86861 | J10: =RepoCo!J5 -> 573.64709 | ... M10: =RepoCo!M5 -> 1022.5823
A12: DERIVATIVES (gross notional -- NOT on standard balance sheet)
A13: Short Treasury futures (exchange, $B notional) | B13: Short leg of basis trade. CFTC TFF reports this. Real-world: $1,050B net short (Mar 2026, all tenors incl Ultra 10yr). NOT in TIC, NOT in bank balance sheets. | C13: =C4*ASSUMPTIONS!C41 -> 140.8 | D13: =D4*ASSUMPTIONS!D41 -> 135.9215 | E13: =E4*ASSUMPTIONS!E41 -> 189.73539 | F13: =F4*ASSUMPTIONS!F41 -> 255.97972 | G13: =G4*ASSUMPTIONS!G41 -> 314.821 | H13: =H4*ASSUMPTIONS!H41 -> 396.57818 | I13: =I4*ASSUMPTIONS!I41 -> 569.22919 | J13: =J4*ASSUMPTIONS!J41 -> 745.74122 | ... M13: =M4*ASSUMPTIONS!M41 -> 1329.357
A14: Gross basis trade exposure (cash + futures, $B) | B14: Total gross exposure. Barth-Beltran end-Y8 total: $1,850B. This is what FedCo must absorb in full unwind. | C14: =C4+C5+C13 -> 220.8 | D14: =D4+D5+D13 -> 240.4765 | E14: =E4+E5+E13 -> 335.68569 | F14: =F4+F5+F13 -> 452.8872 | G14: =G4+G5+G13 -> 556.99099 | H14: =H4+H5+H13 -> 701.63831 | I14: =I4+I5+I13 -> 1007.0978 | J14: =J4+J5+J13 -> 1319.3883 | ... M14: =M4+M5+M13 -> 2363.9394
A15: Effective collateral ($B) = cash TSY × endogenous duration mix [wired to MEASURES] | B15: When yield > 5.5% threshold, GovCo shifts to bills. Basis trade collateral quality compresses. Effective collateral = HedgeCo cash TSY × MEASURES!endogenous_duration_mix. Feeds back into repo haircuts and BTAR. | C15: =HedgeCo!C4*MEASURES!C47 -> 80 | D15: =HedgeCo!D4*MEASURES!D47 -> 41.822 | E15: =HedgeCo!E4*MEASURES!E47 -> 58.38012 | F15: =HedgeCo!F4*MEASURES!F47 -> 78.762991 | G15: =HedgeCo!G4*MEASURES!G47 -> 96.867999 | H15: =HedgeCo!H4*MEASURES!H47 -> 122.02405 | I15: =HedgeCo!I4*MEASURES!I47 -> 175.14744 | J15: =HedgeCo!J4*MEASURES!J47 -> 229.45884 | ... M15: =HedgeCo!M4*MEASURES!M47 -> 409.03294
A16: FRACTIONAL MEASURES
A17: Leverage = Gross exposure / Equity | B17: Gross exposure / equity ($10B fixed). Starts ~23x (Y0). Rises as position scales against fixed equity base. Note: leverage narrative in description calibrated to Y0 entry level. | C17: =IF(ASSUMPTIONS!C43=0,"-",C14/ASSUMPTIONS!C43) -> 22.08 | D17: =IF(ASSUMPTIONS!C43=0,"-",D14/ASSUMPTIONS!C43) -> 24.04765 | E17: =IF(ASSUMPTIONS!C43=0,"-",E14/ASSUMPTIONS!C43) -> 33.568569 | F17: =IF(ASSUMPTIONS!C43=0,"-",F14/ASSUMPTIONS!C43) -> 45.28872 | G17: =IF(ASSUMPTIONS!C43=0,"-",G14/ASSUMPTIONS!C43) -> 55.699099 | H17: =IF(ASSUMPTIONS!C43=0,"-",H14/ASSUMPTIONS!C43) -> 70.163831 | I17: =IF(ASSUMPTIONS!C43=0,"-",I14/ASSUMPTIONS!C43) -> 100.70978 | J17: =IF(ASSUMPTIONS!C43=0,"-",J14/ASSUMPTIONS!C43) -> 131.93883 | K17: =IF(ASSUMPTIONS!C43=0,"-",K14/ASSUMPTIONS!C43) -> 173.41674 | L17: =IF(ASSUMPTIONS!C43=0,"-",L14/ASSUMPTIONS!C43) -> 213.62715 | M17: =IF(ASSUMPTIONS!C43=0,"-",M14/ASSUMPTIONS!C43) -> 236.39394
A18: BTAR numerator = Gross basis trade exposure ($B) | B18: Basis Trade Absorption Ratio numerator. Full unwind = this amount in Treasury selling into stressed market. BTAR = this / FedCo remaining headroom (see MEASURES sheet). | C18: =C14 -> 220.8 | D18: =D14 -> 240.4765 | E18: =E14 -> 335.68569 | F18: =F14 -> 452.8872 | G18: =G14 -> 556.99099 | H18: =H14 -> 701.63831 | I18: =I14 -> 1007.0978 | J18: =J14 -> 1319.3883 | ... M18: =M14 -> 2363.9394
A20: STRESS SCENARIO (Y10+)
A21: Repo called (Path A): HedgeCo forced cash Treasury sale ($B) | B21: CommodityCo deposit withdrawal -> GlobalBankCo calls repo -> RepoCo calls HedgeCo. | C21: 0 | D21: 0 | E21: 0 | F21: 0 | G21: 0 | H21: 0 | I21: 0 | J21: 0 | K21: 0 | L21: 0 | M21: =-L4*0.3 -> -278.6441
A22: Margin breach (Path B): futures margin call ($B) | B22: Yield spike from CommodityCo Treasury sale -> futures P&L negative -> margin breach. | C22: 0 | D22: 0 | E22: 0 | F22: 0 | G22: 0 | H22: 0 | I22: 0 | J22: 0 | K22: 0 | L22: 0 | M22: =-M12*0.02 -> 0

Sheet FedCo
A1: FedCo | AmeriCo Central Bank | Absorber of Last Resort | Pressure Gauge
A2: Account / Line Item | B2: Notes / Source | C2: Y0 | D2: Y1 | E2: Y2 | F2: Y3 | G2: Y4 | H2: Y5 | I2: Y6 | J2: Y7 | K2: Y8 | L2: Y9 | M2: Y10+ Stress
A3: ASSETS
A4: Treasury holdings ($B) | B4: Real-world: Fed peaked $5.7T Treasuries Apr 2022. QT since. Y10+ stress: emergency absorption of HedgeCo unwind. | C4: =ASSUMPTIONS!C46 -> 64 | D4: =C4+ASSUMPTIONS!D47 -> 79 | E4: =D4+ASSUMPTIONS!E47 -> 94 | F4: =E4+ASSUMPTIONS!F47 -> 114 | G4: =F4+ASSUMPTIONS!G47 -> 194 | H4: =G4+ASSUMPTIONS!H47 -> 186 | I4: =H4+ASSUMPTIONS!I47 -> 166 | J4: =I4+ASSUMPTIONS!J47 -> 141 | K4: =J4+ASSUMPTIONS!K47 -> 126 | L4: =K4+ASSUMPTIONS!L47 -> 118 | M4: =L4+ASSUMPTIONS!M47+ASSUMPTIONS!M49 -> 163
A5: MBS holdings ($B) | C5: 80 | D5: =C5+ASSUMPTIONS!D44*0.55 -> 80 | E5: =D5+ASSUMPTIONS!E44*0.55 -> 80 | F5: =E5+ASSUMPTIONS!F44*0.55 -> 80 | G5: =F5+ASSUMPTIONS!G44*0.55 -> 80 | H5: =G5+ASSUMPTIONS!H44*0.55 -> 80 | I5: =H5+ASSUMPTIONS!I44*0.55 -> 80 | J5: =I5+ASSUMPTIONS!J44*0.55 -> 80 | K5: =J5+ASSUMPTIONS!K44*0.55 -> 80 | ... M5: =L5+ASSUMPTIONS!M44*0.55 -> 80
A6: TOTAL ASSETS (Balance Sheet, $B) | C6: =SUM(C4:C5)+C20+C21 -> 144.0032 | D6: =SUM(D4:D5)+D20+D21 -> 159.04485 | E6: =SUM(E4:E5)+E20+E21 -> 174.09136 | F6: =SUM(F4:F5)+F20+F21 -> 194.11061 | G6: =SUM(G4:G5)+G20+G21 -> 274.11061 | H6: =SUM(H4:H5)+H20+H21 -> 266.11061 | I6: =SUM(I4:I5)+I20+I21 -> 246.11061 | J6: =SUM(J4:J5)+J20+J21 -> 221.11061 | ... M6: =SUM(M4:M5)+M20+M21 -> 263.16341
A8: LIABILITIES
A9: Bank reserves ($B) | B9: Each dollar of Treasury purchase = one dollar of reserves. Stress absorption = reserve expansion. | C9: 200 | D9: =C9+ASSUMPTIONS!D44+ASSUMPTIONS!D46 -> 200 | E9: =D9+ASSUMPTIONS!E44+ASSUMPTIONS!E46 -> 200 | F9: =E9+ASSUMPTIONS!F44+ASSUMPTIONS!F46 -> 200 | G9: =F9+ASSUMPTIONS!G44+ASSUMPTIONS!G46 -> 200 | H9: =G9+ASSUMPTIONS!H44+ASSUMPTIONS!H46 -> 200 | I9: =H9+ASSUMPTIONS!I44+ASSUMPTIONS!I46 -> 200 | J9: =I9+ASSUMPTIONS!J44+ASSUMPTIONS!J46 -> 200 | K9: =J9+ASSUMPTIONS!K44+ASSUMPTIONS!K46 -> 200 | ... M9: =L9+ASSUMPTIONS!M44+ASSUMPTIONS!M46 -> 200
A10: Currency in circulation ($B) | C10: 150 | D10: =C10*1.04 -> 156 | E10: =D10*1.04 -> 162.24 | F10: =E10*1.04 -> 168.7296 | G10: =F10*1.04 -> 175.47878 | H10: =G10*1.04 -> 182.49794 | I10: =H10*1.04 -> 189.79785 | J10: =I10*1.04 -> 197.38977 | K10: =J10*1.04 -> 205.28536 | ... M10: =L10*1.04 -> 222.03664
A11: RRP (reverse repo, overnight, $B) | B11: Excess reserves parked at Fed. High RRP = system has more reserves than it wants. | C11: 0 | D11: 300 | E11: 300 | F11: 300 | G11: 200 | H11: 2500 | I11: 2000 | J11: 1500 | K11: 700 | L11: 300 | M11: 300
A13: FRACTIONAL MEASURES
A14: Fed BS / GDP | B14: Primary pressure gauge. At 38-40% = productive base constraint binding. Part II hard threshold. | C14: =C6/ASSUMPTIONS!C5 -> 0.51429714 | D14: =D6/ASSUMPTIONS!D5 -> 0.55416322 | E14: =E6/ASSUMPTIONS!E5 -> 0.5921475 | F14: =F6/ASSUMPTIONS!F5 -> 0.64275038 | G14: =G6/ASSUMPTIONS!G5 -> 0.95177296 | H14: =H6/ASSUMPTIONS!H5 -> 0.88703538 | I14: =I6/ASSUMPTIONS!I5 -> 0.79906043 | J14: =J6/ASSUMPTIONS!J5 -> 0.70193846 | ... M14: =M6/ASSUMPTIONS!M5 -> 0.87721138
A15: Remaining headroom ($B) = ceiling (40% GDP) - current BS | B15: BTAR denominator. Full basis trade unwind absorbs X% of this. | C15: =ASSUMPTIONS!C5*ASSUMPTIONS!C48-C6 -> 219.9968 | D15: =ASSUMPTIONS!D5*ASSUMPTIONS!D48-D6 -> 214.05515 | E15: =ASSUMPTIONS!E5*ASSUMPTIONS!E48-E6 -> 208.10864 | F15: =ASSUMPTIONS!F5*ASSUMPTIONS!F48-F6 -> 198.48939 | G15: =ASSUMPTIONS!G5*ASSUMPTIONS!G48-G6 -> 100.28939 | H15: =ASSUMPTIONS!H5*ASSUMPTIONS!H48-H6 -> 123.88939 | I15: =ASSUMPTIONS!I5*ASSUMPTIONS!I48-I6 -> 154.28939 | J15: =ASSUMPTIONS!J5*ASSUMPTIONS!J48-J6 -> 188.38939 | ... M15: =ASSUMPTIONS!M5*ASSUMPTIONS!M48-M6 -> 126.83659
A17: STRESS (Y10+)
A18: Emergency Treasury purchase = HedgeCo forced sale ($B) | B18: SFC: FedCo buys what HedgeCo sells. The absorber IS the underlying. Balance sheet expands in the same asset under stress. | C18: 0 | D18: 0 | E18: 0 | F18: 0 | G18: 0 | H18: 0 | I18: 0 | J18: 0 | K18: 0 | L18: 0 | M18: =ASSUMPTIONS!M49 -> 45
A20: SRF repo asset ($B) — repo loans to AmeriBankCo/dealers at administered rate | B20: Standing Repo Facility. FedCo absorbs excess repo demand when yield > SRF rate. Real: $26B April 2026 → toy 0.24B. SFC: FedCo asset = AmeriBankCo liability. = MEASURES!SRF_absorption. | C20: =MEASURES!C54 -> 0.0032 | D20: =MEASURES!D54 -> 0.04484528 | E20: =MEASURES!E54 -> 0.091363903 | F20: =MEASURES!F54 -> 0.11061333 | G20: =MEASURES!G54 -> 0.11061333 | H20: =MEASURES!H54 -> 0.11061333 | I20: =MEASURES!I54 -> 0.11061333 | J20: =MEASURES!J54 -> 0.11061333 | ... M20: =MEASURES!M54 -> 0.16341333
A21: FIMA repo asset ($B) — TSY collateral from foreign CBs (Path B bypass) | B21: Foreign Official Repo. Foreign CBs pledge TSY to FedCo for dollars. Prevents outright TSY selling (Path B yield spike). Real: $337.5B foreign official RRP pool → toy 3.1B. SFC: FedCo asset = foreign CB liability (dollars owed). | C21: =MEASURES!C58 -> 0 | D21: =MEASURES!D58 -> 0 | E21: =MEASURES!E58 -> 0 | F21: =MEASURES!F58 -> 0 | G21: =MEASURES!G58 -> 0 | H21: =MEASURES!H58 -> 0 | I21: =MEASURES!I58 -> 0 | J21: =MEASURES!J58 -> 0 | ... M21: =MEASURES!M58 -> 20

Sheet SFC_CHECK
A1: SFC CHECK -- All cells must be GREEN. Red = model error in accounting identities.
A2: Account / Line Item | B2: Notes / Source | C2: Y0 | D2: Y1 | E2: Y2 | F2: Y3 | G2: Y4 | H2: Y5 | I2: Y6 | J2: Y7 | K2: Y8 | L2: Y9 | M2: Y10+ Stress
A3: SFC IDENTITY CHECKS -- difference = 0 means identity holds
A4: IDENTITY | B4: DESCRIPTION | C4: Y0 | D4: Y1 | E4: Y2 | F4: Y3 | G4: Y4 | H4: Y5 | I4: Y6 | J4: Y7 | K4: Y8 | L4: Y9 | M4: Y10+ Stress
A5: 1: JapanCo dep = GlobalBankCo liab to JapanCo | B5: JapanCo asset must equal GlobalBankCo liability. Core SFC constraint. | C5: =JapanCo!C5-(GlobalBankCo!C12) -> 0 | D5: =JapanCo!D5-(GlobalBankCo!D12) -> 0 | E5: =JapanCo!E5-(GlobalBankCo!E12) -> 0 | F5: =JapanCo!F5-(GlobalBankCo!F12) -> 0 | G5: =JapanCo!G5-(GlobalBankCo!G12) -> 0 | H5: =JapanCo!H5-(GlobalBankCo!H12) -> 0 | I5: =JapanCo!I5-(GlobalBankCo!I12) -> 0 | J5: =JapanCo!J5-(GlobalBankCo!J12) -> 0 | ... M5: =JapanCo!M5-(GlobalBankCo!M12) -> 0
A6: 2: CommodityCo dep = GlobalBankCo liab to CommodityCo | B6: CommodityCo asset must equal GlobalBankCo liability. | C6: =CommodityCo!C4-(GlobalBankCo!C13) -> 0 | D6: =CommodityCo!D4-(GlobalBankCo!D13) -> 0 | E6: =CommodityCo!E4-(GlobalBankCo!E13) -> 0 | F6: =CommodityCo!F4-(GlobalBankCo!F13) -> 0 | G6: =CommodityCo!G4-(GlobalBankCo!G13) -> 0 | H6: =CommodityCo!H4-(GlobalBankCo!H13) -> 0 | I6: =CommodityCo!I4-(GlobalBankCo!I13) -> 0 | J6: =CommodityCo!J4-(GlobalBankCo!J13) -> 0 | ... M6: =CommodityCo!M4-(GlobalBankCo!M13) -> 0
A7: 3: GlobalBankCo repo = RepoCo repo payable | B7: Repo book must balance across the two counterparties. | C7: =GlobalBankCo!C4-(RepoCo!C10) -> 0 | D7: =GlobalBankCo!D4-(RepoCo!D10) -> 0 | E7: =GlobalBankCo!E4-(RepoCo!E10) -> 0 | F7: =GlobalBankCo!F4-(RepoCo!F10) -> 0 | G7: =GlobalBankCo!G4-(RepoCo!G10) -> 0 | H7: =GlobalBankCo!H4-(RepoCo!H10) -> 0 | I7: =GlobalBankCo!I4-(RepoCo!I10) -> 0 | J7: =GlobalBankCo!J4-(RepoCo!J10) -> 0 | ... M7: =GlobalBankCo!M4-(RepoCo!M10) -> 0
A8: 4: RepoCo repo recv = HedgeCo repo payable | B8: RepoCo receivable = HedgeCo liability. | C8: =RepoCo!C5-(HedgeCo!C10) -> 0 | D8: =RepoCo!D5-(HedgeCo!D10) -> 0 | E8: =RepoCo!E5-(HedgeCo!E10) -> 0 | F8: =RepoCo!F5-(HedgeCo!F10) -> 0 | G8: =RepoCo!G5-(HedgeCo!G10) -> 0 | H8: =RepoCo!H5-(HedgeCo!H10) -> 0 | I8: =RepoCo!I5-(HedgeCo!I10) -> 0 | J8: =RepoCo!J5-(HedgeCo!J10) -> 0 | ... M8: =RepoCo!M5-(HedgeCo!M10) -> 0
A9: 5: HedgeCo cash Treasury = RepoCo repo receivable | B9: Cash long position funded by repo = repo receivable from RepoCo's perspective. | C9: =HedgeCo!C4-(RepoCo!C5) -> 0 | D9: =HedgeCo!D4-(RepoCo!D5) -> 0 | E9: =HedgeCo!E4-(RepoCo!E5) -> 0 | F9: =HedgeCo!F4-(RepoCo!F5) -> 0 | G9: =HedgeCo!G4-(RepoCo!G5) -> 0 | H9: =HedgeCo!H4-(RepoCo!H5) -> 0 | I9: =HedgeCo!I4-(RepoCo!I5) -> 0 | J9: =HedgeCo!J4-(RepoCo!J5) -> 0 | ... M9: =HedgeCo!M4-(RepoCo!M5) -> 0
A10: 6: CommodityCo JapInv liab = JapanCo JapInv asset | B10: JapInv project obligations on CommodityCo = claims on JapanCo. | C10: =CommodityCo!C14-(JapanCo!C7) -> 0 | D10: =CommodityCo!D14-(JapanCo!D7) -> 0 | E10: =CommodityCo!E14-(JapanCo!E7) -> 0 | F10: =CommodityCo!F14-(JapanCo!F7) -> 0 | G10: =CommodityCo!G14-(JapanCo!G7) -> 0 | H10: =CommodityCo!H14-(JapanCo!H7) -> 0 | I10: =CommodityCo!I14-(JapanCo!I7) -> 0 | J10: =CommodityCo!J14-(JapanCo!J7) -> 0 | ... M10: =CommodityCo!M14-(JapanCo!M7) -> 0
A11: 7: FedCo Y0 Treasury = ASSUMPTIONS input; Y1+: BS/GDP <= ceiling | B11: Y0: exact match check. Y1+: ceiling not breached (0 if OK, positive if breach). | C11: =FedCo!C4-ASSUMPTIONS!C46 -> 0 | D11: 0 | E11: 0 | F11: 0 | G11: 0 | H11: 0 | I11: 0 | J11: 0 | K11: 0 | L11: 0 | M11: 0
A12: 8: CommodityCo gold proceeds = GBC gold temp deposit | C12: =CommodityCo!C9-GlobalBankCo!C14 -> 0 | D12: =CommodityCo!D9-GlobalBankCo!D14 -> 0 | E12: =CommodityCo!E9-GlobalBankCo!E14 -> 0 | F12: =CommodityCo!F9-GlobalBankCo!F14 -> 0 | G12: =CommodityCo!G9-GlobalBankCo!G14 -> 0 | H12: =CommodityCo!H9-GlobalBankCo!H14 -> 0 | I12: =CommodityCo!I9-GlobalBankCo!I14 -> 0 | J12: =CommodityCo!J9-GlobalBankCo!J14 -> 0 | ... M12: =CommodityCo!M9-GlobalBankCo!M14 -> 0
A13: 9: GBC gold-funded repo = RepoCo gold-funded repo recv | C13: =GlobalBankCo!C5-RepoCo!C6 -> 0 | D13: =GlobalBankCo!D5-RepoCo!D6 -> 0 | E13: =GlobalBankCo!E5-RepoCo!E6 -> 0 | F13: =GlobalBankCo!F5-RepoCo!F6 -> 0 | G13: =GlobalBankCo!G5-RepoCo!G6 -> 0 | H13: =GlobalBankCo!H5-RepoCo!H6 -> 0 | I13: =GlobalBankCo!I5-RepoCo!I6 -> 0 | J13: =GlobalBankCo!J5-RepoCo!J6 -> 0 | ... M13: =GlobalBankCo!M5-RepoCo!M6 -> 0
A14: 10: RepoCo gold repo recv = HedgeCo gold-funded Treasury | C14: =RepoCo!C6-HedgeCo!C5 -> 0 | D14: =RepoCo!D6-HedgeCo!D5 -> 0 | E14: =RepoCo!E6-HedgeCo!E5 -> 0 | F14: =RepoCo!F6-HedgeCo!F5 -> 0 | G14: =RepoCo!G6-HedgeCo!G5 -> 0 | H14: =RepoCo!H6-HedgeCo!H5 -> 0 | I14: =RepoCo!I6-HedgeCo!I5 -> 0 | J14: =RepoCo!J6-HedgeCo!J5 -> 0 | ... M14: =RepoCo!M6-HedgeCo!M5 -> 0
A15: 11: ClearCo net position = 0 (pure pass-through CCP) | C15: =ClearCo!C11 -> 0 | D15: =ClearCo!D11 -> 0 | E15: =ClearCo!E11 -> 0 | F15: =ClearCo!F11 -> 0 | G15: =ClearCo!G11 -> 0 | H15: =ClearCo!H11 -> 0 | I15: =ClearCo!I11 -> 0 | J15: =ClearCo!J11 -> 0 | ... M15: =ClearCo!M11 -> 0
A16: SUMMARY: count of non-zero cells above (should be zero)
A17: Non-zero cells (errors) | C17: =SUMPRODUCT((ISNUMBER(C5:C15))*(ABS(IF(ISNUMBER(C5:C15),C5:C15,0))>0.01)) -> 0 | D17: =SUMPRODUCT((ISNUMBER(D5:D15))*(ABS(IF(ISNUMBER(D5:D15),D5:D15,0))>0.01)) -> 0 | E17: =SUMPRODUCT((ISNUMBER(E5:E15))*(ABS(IF(ISNUMBER(E5:E15),E5:E15,0))>0.01)) -> 0 | F17: =SUMPRODUCT((ISNUMBER(F5:F15))*(ABS(IF(ISNUMBER(F5:F15),F5:F15,0))>0.01)) -> 0 | G17: =SUMPRODUCT((ISNUMBER(G5:G15))*(ABS(IF(ISNUMBER(G5:G15),G5:G15,0))>0.01)) -> 0 | H17: =SUMPRODUCT((ISNUMBER(H5:H15))*(ABS(IF(ISNUMBER(H5:H15),H5:H15,0))>0.01)) -> 0 | I17: =SUMPRODUCT((ISNUMBER(I5:I15))*(ABS(IF(ISNUMBER(I5:I15),I5:I15,0))>0.01)) -> 0 | J17: =SUMPRODUCT((ISNUMBER(J5:J15))*(ABS(IF(ISNUMBER(J5:J15),J5:J15,0))>0.01)) -> 0 | ... M17: =SUMPRODUCT((ISNUMBER(M5:M15))*(ABS(IF(ISNUMBER(M5:M15),M5:M15,0))>0.01)) -> 0
A19: PART IV INTERNAL SFC IDENTITIES (12-17)
A20: 12: Wage identity -- ManuCo+ProdServ+FinServ wages = HouseholdCo total | B20: ManuCo+ProdServiceCo+FinServCo wage bills must sum to HouseholdCo total wage income. | C20: =ManuCo!C12+ProdServiceCo!C12+FinServCo!C15-HouseholdCo!C18 -> 0 | D20: =ManuCo!D12+ProdServiceCo!D12+FinServCo!D15-HouseholdCo!D18 -> 0 | E20: =ManuCo!E12+ProdServiceCo!E12+FinServCo!E15-HouseholdCo!E18 -> 0 | F20: =ManuCo!F12+ProdServiceCo!F12+FinServCo!F15-HouseholdCo!F18 -> 0 | G20: =ManuCo!G12+ProdServiceCo!G12+FinServCo!G15-HouseholdCo!G18 -> 0 | H20: =ManuCo!H12+ProdServiceCo!H12+FinServCo!H15-HouseholdCo!H18 -> 0 | I20: =ManuCo!I12+ProdServiceCo!I12+FinServCo!I15-HouseholdCo!I18 -> 0 | J20: =ManuCo!J12+ProdServiceCo!J12+FinServCo!J15-HouseholdCo!J18 -> 0 | ... M20: =ManuCo!M12+ProdServiceCo!M12+FinServCo!M15-HouseholdCo!M18 -> 0
A21: 13: Deposit identity — AmeriBankCo deposit liabilities = HH + ManuCo + ProdServ deposits | B21: Real cross-check: sum of depositor assets = bank deposit liabilities. Was tautological — now a genuine constraint. | C21: =(AmeriBankCo!C11+AmeriBankCo!C12)-(HouseholdCo!C7+ManuCo!C14*0.08+ProdServiceCo!C14*0.06) -> 0 | D21: =(AmeriBankCo!D11+AmeriBankCo!D12)-(HouseholdCo!D7+ManuCo!D14*0.08+ProdServiceCo!D14*0.06) -> 0 | E21: =(AmeriBankCo!E11+AmeriBankCo!E12)-(HouseholdCo!E7+ManuCo!E14*0.08+ProdServiceCo!E14*0.06) -> 0 | F21: =(AmeriBankCo!F11+AmeriBankCo!F12)-(HouseholdCo!F7+ManuCo!F14*0.08+ProdServiceCo!F14*0.06) -> 0 | G21: =(AmeriBankCo!G11+AmeriBankCo!G12)-(HouseholdCo!G7+ManuCo!G14*0.08+ProdServiceCo!G14*0.06) -> 0 | H21: =(AmeriBankCo!H11+AmeriBankCo!H12)-(HouseholdCo!H7+ManuCo!H14*0.08+ProdServiceCo!H14*0.06) -> 0 | I21: =(AmeriBankCo!I11+AmeriBankCo!I12)-(HouseholdCo!I7+ManuCo!I14*0.08+ProdServiceCo!I14*0.06) -> 0 | J21: =(AmeriBankCo!J11+AmeriBankCo!J12)-(HouseholdCo!J7+ManuCo!J14*0.08+ProdServiceCo!J14*0.06) -> 0 | ... M21: =(AmeriBankCo!M11+AmeriBankCo!M12)-(HouseholdCo!M7+ManuCo!M14*0.08+ProdServiceCo!M14*0.06) -> 0
A22: 14: AmeriBankCo repo to FinServCo = FinServCo repo payable | B22: Repo must balance across the two counterparties. | C22: =AmeriBankCo!C5-FinServCo!C14 -> 0 | D22: =AmeriBankCo!D5-FinServCo!D14 -> 0 | E22: =AmeriBankCo!E5-FinServCo!E14 -> 0 | F22: =AmeriBankCo!F5-FinServCo!F14 -> 0 | G22: =AmeriBankCo!G5-FinServCo!G14 -> 0 | H22: =AmeriBankCo!H5-FinServCo!H14 -> 0 | I22: =AmeriBankCo!I5-FinServCo!I14 -> 0 | J22: =AmeriBankCo!J5-FinServCo!J14 -> 0 | ... M22: =AmeriBankCo!M5-FinServCo!M14 -> 0
A23: 15: GovCo holder rows mirror balance sheets — all 8 named holders self-consistent | B23: Each GovCo holder row = corresponding holder balance sheet asset. Checks: HH_direct + InsuranceCo + FinServCo_TSY + AmeriBankCo_TSY + OtherBankCo all mirror correctly. Sum = 0 if all mirrors are wired. GovCo!r14=FinServCo!r5, r15=AmeriBankCo!r6 added Apr 2026. | C23: =(GovCo!C12-HouseholdCo!C8)+(GovCo!C13-InsuranceCo!C5)+(GovCo!C14-FinServCo!C5)+(GovCo!C15-AmeriBankCo!C6)+(GovCo!C16-OtherBankCo!C5) -> #VALUE! | D23: =(GovCo!D12-HouseholdCo!D8)+(GovCo!D13-InsuranceCo!D5)+(GovCo!D14-FinServCo!D5)+(GovCo!D15-AmeriBankCo!D6)+(GovCo!D16-OtherBankCo!D5) -> #VALUE! | E23: =(GovCo!E12-HouseholdCo!E8)+(GovCo!E13-InsuranceCo!E5)+(GovCo!E14-FinServCo!E5)+(GovCo!E15-AmeriBankCo!E6)+(GovCo!E16-OtherBankCo!E5) -> #VALUE! | F23: =(GovCo!F12-HouseholdCo!F8)+(GovCo!F13-InsuranceCo!F5)+(GovCo!F14-FinServCo!F5)+(GovCo!F15-AmeriBankCo!F6)+(GovCo!F16-OtherBankCo!F5) -> #VALUE! | G23: =(GovCo!G12-HouseholdCo!G8)+(GovCo!G13-InsuranceCo!G5)+(GovCo!G14-FinServCo!G5)+(GovCo!G15-AmeriBankCo!G6)+(GovCo!G16-OtherBankCo!G5) -> #VALUE! | H23: =(GovCo!H12-HouseholdCo!H8)+(GovCo!H13-InsuranceCo!H5)+(GovCo!H14-FinServCo!H5)+(GovCo!H15-AmeriBankCo!H6)+(GovCo!H16-OtherBankCo!H5) -> #VALUE! | I23: =(GovCo!I12-HouseholdCo!I8)+(GovCo!I13-InsuranceCo!I5)+(GovCo!I14-FinServCo!I5)+(GovCo!I15-AmeriBankCo!I6)+(GovCo!I16-OtherBankCo!I5) -> #VALUE! | J23: =(GovCo!J12-HouseholdCo!J8)+(GovCo!J13-InsuranceCo!J5)+(GovCo!J14-FinServCo!J5)+(GovCo!J15-AmeriBankCo!J6)+(GovCo!J16-OtherBankCo!J5) -> #VALUE! | ... M23: =(GovCo!M12-HouseholdCo!M8)+(GovCo!M13-InsuranceCo!M5)+(GovCo!M14-FinServCo!M5)+(GovCo!M15-AmeriBankCo!M6)+(GovCo!M16-OtherBankCo!M5) -> #VALUE!
A24: 16: FedCo reserve liabilities = AmeriBankCo reserve assets (1:1, consolidated sector) | B24: AmeriBankCo = consolidated US banking sector. 100% of FedCo reserve liabilities appear on AmeriBankCo asset side. Note UPDATED: was 0.4 proxy (stale). Now 1:1. | C24: =FedCo!C9-AmeriBankCo!C7 -> 0 | D24: =FedCo!D9-AmeriBankCo!D7 -> 0 | E24: =FedCo!E9-AmeriBankCo!E7 -> 0 | F24: =FedCo!F9-AmeriBankCo!F7 -> 0 | G24: =FedCo!G9-AmeriBankCo!G7 -> 0 | H24: =FedCo!H9-AmeriBankCo!H7 -> 0 | I24: =FedCo!I9-AmeriBankCo!I7 -> 0 | J24: =FedCo!J9-AmeriBankCo!J7 -> 0 | ... M24: =FedCo!M9-AmeriBankCo!M7 -> 0
A25: 17: FinServCo LP stake = HedgeCo equity * LP fraction | B25: Pension LP stake in basis trade vehicle must match HedgeCo equity * ASSUMPTIONS LP fraction. | C25: =FinServCo!C7-ASSUMPTIONS!C67*ASSUMPTIONS!C43 -> 0 | D25: =FinServCo!D7-ASSUMPTIONS!D67*ASSUMPTIONS!D43 -> 0 | E25: =FinServCo!E7-ASSUMPTIONS!E67*ASSUMPTIONS!E43 -> 0 | F25: =FinServCo!F7-ASSUMPTIONS!F67*ASSUMPTIONS!F43 -> 0 | G25: =FinServCo!G7-ASSUMPTIONS!G67*ASSUMPTIONS!G43 -> 0 | H25: =FinServCo!H7-ASSUMPTIONS!H67*ASSUMPTIONS!H43 -> 0 | I25: =FinServCo!I7-ASSUMPTIONS!I67*ASSUMPTIONS!I43 -> 0 | J25: =FinServCo!J7-ASSUMPTIONS!J67*ASSUMPTIONS!J43 -> 0 | ... M25: =FinServCo!M7-ASSUMPTIONS!M67*ASSUMPTIONS!M43 -> 0
A26: 18: Treasury conservation — GovCo!r18(total) = sum of 8 named holders + true residual(=0) | B26: Complete holder set: FedCo(r9)+HedgeCo(r10)+Official(r11)+HH(r12)+InsuranceCo(r13)+FinServCo_TSY(r14)+AmeriBankCo_TSY(r15)+OtherBankCo(r16)+true_residual(r17)=GovCo!r18. OtherBankCo absorbs remainder → residual=0 → identity closes exactly. | C26: =GovCo!C18-GovCo!C9-GovCo!C10-GovCo!C11-GovCo!C12-GovCo!C13-GovCo!C14-GovCo!C15-GovCo!C16-GovCo!C17 -> #VALUE! | D26: =GovCo!D18-GovCo!D9-GovCo!D10-GovCo!D11-GovCo!D12-GovCo!D13-GovCo!D14-GovCo!D15-GovCo!D16-GovCo!D17 -> #VALUE! | E26: =GovCo!E18-GovCo!E9-GovCo!E10-GovCo!E11-GovCo!E12-GovCo!E13-GovCo!E14-GovCo!E15-GovCo!E16-GovCo!E17 -> #VALUE! | F26: =GovCo!F18-GovCo!F9-GovCo!F10-GovCo!F11-GovCo!F12-GovCo!F13-GovCo!F14-GovCo!F15-GovCo!F16-GovCo!F17 -> #VALUE! | G26: =GovCo!G18-GovCo!G9-GovCo!G10-GovCo!G11-GovCo!G12-GovCo!G13-GovCo!G14-GovCo!G15-GovCo!G16-GovCo!G17 -> #VALUE! | H26: =GovCo!H18-GovCo!H9-GovCo!H10-GovCo!H11-GovCo!H12-GovCo!H13-GovCo!H14-GovCo!H15-GovCo!H16-GovCo!H17 -> #VALUE! | I26: =GovCo!I18-GovCo!I9-GovCo!I10-GovCo!I11-GovCo!I12-GovCo!I13-GovCo!I14-GovCo!I15-GovCo!I16-GovCo!I17 -> #VALUE! | J26: =GovCo!J18-GovCo!J9-GovCo!J10-GovCo!J11-GovCo!J12-GovCo!J13-GovCo!J14-GovCo!J15-GovCo!J16-GovCo!J17 -> #VALUE! | ... M26: =GovCo!M18-GovCo!M9-GovCo!M10-GovCo!M11-GovCo!M12-GovCo!M13-GovCo!M14-GovCo!M15-GovCo!M16-GovCo!M17 -> #VALUE!
A27: 18a: RepoCo on-BS Treasury = 0 (repo loan only, no bond ownership) | B27: RepoCo holds cash claims only. If non-zero: model error -- bond has been double-counted. | C27: =IF(ISNUMBER(RepoCo!C4),RepoCo!C4,0) -> 0 | D27: =IF(ISNUMBER(RepoCo!D4),RepoCo!D4,0) -> 0 | E27: =IF(ISNUMBER(RepoCo!E4),RepoCo!E4,0) -> 0 | F27: =IF(ISNUMBER(RepoCo!F4),RepoCo!F4,0) -> 0 | G27: =IF(ISNUMBER(RepoCo!G4),RepoCo!G4,0) -> 0 | H27: =IF(ISNUMBER(RepoCo!H4),RepoCo!H4,0) -> 0 | I27: =IF(ISNUMBER(RepoCo!I4),RepoCo!I4,0) -> 0 | J27: =IF(ISNUMBER(RepoCo!J4),RepoCo!J4,0) -> 0 | ... M27: =IF(ISNUMBER(RepoCo!M4),RepoCo!M4,0) -> 0
A28: 18b: ClearCo on-BS Treasury = 0 (novation is memorandum / off-balance-sheet only) | B28: ClearCo tracks novated exposure only. Net position = 0 by construction (Identity 11). No bond on ClearCo balance sheet. | C28: =ClearCo!C11 -> 0 | D28: =ClearCo!D11 -> 0 | E28: =ClearCo!E11 -> 0 | F28: =ClearCo!F11 -> 0 | G28: =ClearCo!G11 -> 0 | H28: =ClearCo!H11 -> 0 | I28: =ClearCo!I11 -> 0 | J28: =ClearCo!J11 -> 0 | ... M28: =ClearCo!M11 -> 0
A29: 19: FinServCo TSY floor >= 0 (HedgeCo cannot buy more bonds than FinServCo owns) | B29: If negative: HedgeCo has scaled beyond FinServCo holdings. Need second seller. Check ASSUMPTIONS. | C29: =MIN(0,FinServCo!C5) -> 0 | D29: =MIN(0,FinServCo!D5) -> 0 | E29: =MIN(0,FinServCo!E5) -> 0 | F29: =MIN(0,FinServCo!F5) -> 0 | G29: =MIN(0,FinServCo!G5) -> 0 | H29: =MIN(0,FinServCo!H5) -> 0 | I29: =MIN(0,FinServCo!I5) -> 0 | J29: =MIN(0,FinServCo!J5) -> 0 | ... M29: =MIN(0,FinServCo!M5) -> 0
A30: DIAG: Partial Treasury reallocation (HedgeCo+FinServCo+AmeriBankCo+Official) -- not an identity, omits FedCo/HH/Insurance/OtherBank | B30: Annual change in HedgeCo TSY + annual change in all sellers = 0. Reallocation is zero-sum within any year's stock. | C30: 0 | D30: =(HedgeCo!D4-HedgeCo!C4)+(FinServCo!D5-FinServCo!C5)+(AmeriBankCo!D6-AmeriBankCo!C6)+(AmeriCo!D10-AmeriCo!C10) -> -49.11 | E30: =(HedgeCo!E4-HedgeCo!D4)+(FinServCo!E5-FinServCo!D5)+(AmeriBankCo!E6-AmeriBankCo!D6)+(AmeriCo!E10-AmeriCo!D10) -> -40.89 | F30: =(HedgeCo!F4-HedgeCo!E4)+(FinServCo!F5-FinServCo!E5)+(AmeriBankCo!F6-AmeriBankCo!E6)+(AmeriCo!F10-AmeriCo!E10) -> 16.907478 | G30: =(HedgeCo!G4-HedgeCo!F4)+(FinServCo!G5-FinServCo!F5)+(AmeriBankCo!G6-AmeriBankCo!F6)+(AmeriCo!G10-AmeriCo!F10) -> 45.262519 | H30: =(HedgeCo!H4-HedgeCo!G4)+(FinServCo!H5-FinServCo!G5)+(AmeriBankCo!H6-AmeriBankCo!G6)+(AmeriCo!H10-AmeriCo!G10) -> 62.890138 | I30: =(HedgeCo!I4-HedgeCo!H4)+(FinServCo!I5-FinServCo!H5)+(AmeriBankCo!I6-AmeriBankCo!H6)+(AmeriCo!I10-AmeriCo!H10) -> 132.80847 | J30: =(HedgeCo!J4-HedgeCo!I4)+(FinServCo!J5-FinServCo!I5)+(AmeriBankCo!J6-AmeriBankCo!I6)+(AmeriCo!J10-AmeriCo!I10) -> 135.77849 | K30: =(HedgeCo!K4-HedgeCo!J4)+(FinServCo!K5-FinServCo!J5)+(AmeriBankCo!K6-AmeriBankCo!J6)+(AmeriCo!K10-AmeriCo!J10) -> 180.33874 | ... M30: =(HedgeCo!M4-HedgeCo!L4)+(FinServCo!M5-FinServCo!L5)+(AmeriBankCo!M6-AmeriBankCo!L6)+(AmeriCo!M10-AmeriCo!L10) -> 93.768662
A31: 21: AmeriBankCo balance sheet — Assets = Liabilities + Equity | B31: Full closure. Equity = r15 = Assets - Liabilities. Gap = 0 by construction but confirms no row was skipped. | C31: =AmeriBankCo!C9-(AmeriBankCo!C14+AmeriBankCo!C15) -> 0 | D31: =AmeriBankCo!D9-(AmeriBankCo!D14+AmeriBankCo!D15) -> 0 | E31: =AmeriBankCo!E9-(AmeriBankCo!E14+AmeriBankCo!E15) -> 0 | F31: =AmeriBankCo!F9-(AmeriBankCo!F14+AmeriBankCo!F15) -> 0 | G31: =AmeriBankCo!G9-(AmeriBankCo!G14+AmeriBankCo!G15) -> 0 | H31: =AmeriBankCo!H9-(AmeriBankCo!H14+AmeriBankCo!H15) -> 0 | I31: =AmeriBankCo!I9-(AmeriBankCo!I14+AmeriBankCo!I15) -> 0 | J31: =AmeriBankCo!J9-(AmeriBankCo!J14+AmeriBankCo!J15) -> 0 | ... M31: =AmeriBankCo!M9-(AmeriBankCo!M14+AmeriBankCo!M15) -> 0
A32: 22: HouseholdCo balance sheet — Assets = Liabilities + Net Worth | B32: HH closure. Net worth = r14 = Assets - Liabilities. | C32: =HouseholdCo!C9-(HouseholdCo!C13+HouseholdCo!C14) -> #VALUE! | D32: =HouseholdCo!D9-(HouseholdCo!D13+HouseholdCo!D14) -> #VALUE! | E32: =HouseholdCo!E9-(HouseholdCo!E13+HouseholdCo!E14) -> #VALUE! | F32: =HouseholdCo!F9-(HouseholdCo!F13+HouseholdCo!F14) -> #VALUE! | G32: =HouseholdCo!G9-(HouseholdCo!G13+HouseholdCo!G14) -> #VALUE! | H32: =HouseholdCo!H9-(HouseholdCo!H13+HouseholdCo!H14) -> #VALUE! | I32: =HouseholdCo!I9-(HouseholdCo!I13+HouseholdCo!I14) -> #VALUE! | J32: =HouseholdCo!J9-(HouseholdCo!J13+HouseholdCo!J14) -> #VALUE! | ... M32: =HouseholdCo!M9-(HouseholdCo!M13+HouseholdCo!M14) -> #VALUE!
A33: 23: AmeriBankCo loan book = HH mortgage + HH consumer + ManuCo corporate debt | B33: Borrower liabilities = lender asset. Gap = 0 confirms no phantom lending. | C33: =AmeriBankCo!C8-(HouseholdCo!C11+HouseholdCo!C12+ManuCo!C9) -> 0 | D33: =AmeriBankCo!D8-(HouseholdCo!D11+HouseholdCo!D12+ManuCo!D9) -> 0 | E33: =AmeriBankCo!E8-(HouseholdCo!E11+HouseholdCo!E12+ManuCo!E9) -> 0 | F33: =AmeriBankCo!F8-(HouseholdCo!F11+HouseholdCo!F12+ManuCo!F9) -> 0 | G33: =AmeriBankCo!G8-(HouseholdCo!G11+HouseholdCo!G12+ManuCo!G9) -> 0 | H33: =AmeriBankCo!H8-(HouseholdCo!H11+HouseholdCo!H12+ManuCo!H9) -> 0 | I33: =AmeriBankCo!I8-(HouseholdCo!I11+HouseholdCo!I12+ManuCo!I9) -> 0 | J33: =AmeriBankCo!J8-(HouseholdCo!J11+HouseholdCo!J12+ManuCo!J9) -> 0 | ... M33: =AmeriBankCo!M8-(HouseholdCo!M11+HouseholdCo!M12+ManuCo!M9) -> 0
A34: 24: FedCo reserve liabilities = AmeriBankCo reserve assets (1:1, consolidated sector) | B34: AmeriBankCo = consolidated banking sector. 100% of FedCo reserve liabilities appear on AmeriBankCo asset side. | C34: =FedCo!C9-AmeriBankCo!C7 -> 0 | D34: =FedCo!D9-AmeriBankCo!D7 -> 0 | E34: =FedCo!E9-AmeriBankCo!E7 -> 0 | F34: =FedCo!F9-AmeriBankCo!F7 -> 0 | G34: =FedCo!G9-AmeriBankCo!G7 -> 0 | H34: =FedCo!H9-AmeriBankCo!H7 -> 0 | I34: =FedCo!I9-AmeriBankCo!I7 -> 0 | J34: =FedCo!J9-AmeriBankCo!J7 -> 0 | ... M34: =FedCo!M9-AmeriBankCo!M7 -> 0
A35: 25: HH pension claim = FinServCo net worth (assets − pension obligations − repo) | B35: HH is residual claimant on FinServCo. Net worth = gross assets minus what FinServCo owes others. | C35: =HouseholdCo!C5-(FinServCo!C9-FinServCo!C11-FinServCo!C12) -> 0 | D35: =HouseholdCo!D5-(FinServCo!D9-FinServCo!D11-FinServCo!D12) -> 0 | E35: =HouseholdCo!E5-(FinServCo!E9-FinServCo!E11-FinServCo!E12) -> 0 | F35: =HouseholdCo!F5-(FinServCo!F9-FinServCo!F11-FinServCo!F12) -> 0 | G35: =HouseholdCo!G5-(FinServCo!G9-FinServCo!G11-FinServCo!G12) -> 0 | H35: =HouseholdCo!H5-(FinServCo!H9-FinServCo!H11-FinServCo!H12) -> 0 | I35: =HouseholdCo!I5-(FinServCo!I9-FinServCo!I11-FinServCo!I12) -> 0 | J35: =HouseholdCo!J5-(FinServCo!J9-FinServCo!J11-FinServCo!J12) -> 0 | ... M35: =HouseholdCo!M5-(FinServCo!M9-FinServCo!M11-FinServCo!M12) -> 0
A36: 26: ProdServiceCo equity liabilities = FinServCo equity portfolio + HH direct equity | B36: Equity claim wired to holders. Gap = 0 confirms no phantom equity created. | C36: =ProdServiceCo!C9-(FinServCo!C6+HouseholdCo!C14*ASSUMPTIONS!C71) -> #VALUE! | D36: =ProdServiceCo!D9-(FinServCo!D6+HouseholdCo!D14*ASSUMPTIONS!C71) -> #VALUE! | E36: =ProdServiceCo!E9-(FinServCo!E6+HouseholdCo!E14*ASSUMPTIONS!C71) -> #VALUE! | F36: =ProdServiceCo!F9-(FinServCo!F6+HouseholdCo!F14*ASSUMPTIONS!C71) -> #VALUE! | G36: =ProdServiceCo!G9-(FinServCo!G6+HouseholdCo!G14*ASSUMPTIONS!C71) -> #VALUE! | H36: =ProdServiceCo!H9-(FinServCo!H6+HouseholdCo!H14*ASSUMPTIONS!C71) -> #VALUE! | I36: =ProdServiceCo!I9-(FinServCo!I6+HouseholdCo!I14*ASSUMPTIONS!C71) -> #VALUE! | J36: =ProdServiceCo!J9-(FinServCo!J6+HouseholdCo!J14*ASSUMPTIONS!C71) -> #VALUE! | K36: =ProdServiceCo!K9-(FinServCo!K6+HouseholdCo!K14*ASSUMPTIONS!C71) -> #VALUE! | L36: =ProdServiceCo!L9-(FinServCo!L6+HouseholdCo!L14*ASSUMPTIONS!C71) -> #VALUE! | M36: =ProdServiceCo!M9-(FinServCo!M6+HouseholdCo!M14*ASSUMPTIONS!C71) -> #VALUE!
A37: 27: PrivCred mirror — FinServCo PC loans = ProdServiceCo PC debt | B37: Hard rule: exact equality. Gap = 0 confirms no phantom credit. | C37: =FinServCo!C9-ProdServiceCo!C10 -> 0 | D37: =FinServCo!D9-ProdServiceCo!D10 -> 0 | E37: =FinServCo!E9-ProdServiceCo!E10 -> 0 | F37: =FinServCo!F9-ProdServiceCo!F10 -> 0 | G37: =FinServCo!G9-ProdServiceCo!G10 -> 0 | H37: =FinServCo!H9-ProdServiceCo!H10 -> 0 | I37: =FinServCo!I9-ProdServiceCo!I10 -> 0 | J37: =FinServCo!J9-ProdServiceCo!J10 -> 0 | ... M37: =FinServCo!M9-ProdServiceCo!M10 -> 0
A38: 28: Gate mechanics — actual payout = MIN(liquid assets, HH request) | B38: Gate enforced. Payout ≤ liquid TSY. No TSY disappears. | C38: =FinServCo!C18-MIN(FinServCo!C16,FinServCo!C17) -> 0 | D38: =FinServCo!D18-MIN(FinServCo!D16,FinServCo!D17) -> 0 | E38: =FinServCo!E18-MIN(FinServCo!E16,FinServCo!E17) -> 0 | F38: =FinServCo!F18-MIN(FinServCo!F16,FinServCo!F17) -> 0 | G38: =FinServCo!G18-MIN(FinServCo!G16,FinServCo!G17) -> 0 | H38: =FinServCo!H18-MIN(FinServCo!H16,FinServCo!H17) -> 0 | I38: =FinServCo!I18-MIN(FinServCo!I16,FinServCo!I17) -> 0 | J38: =FinServCo!J18-MIN(FinServCo!J16,FinServCo!J17) -> 0 | ... M38: =FinServCo!M18-MIN(FinServCo!M16,FinServCo!M17) -> 0
A39: 29: Illiquidity flag — when gate fires, TSY buyer must be identified | B39: Narrative identity. When gate fires, TSY buyer = AmeriBankCo (normal) or FedCo (stress). Enforced in CONTAGION tab. Returns 0 here as placeholder. | C39: 0 | D39: 0 | E39: 0 | F39: 0 | G39: 0 | H39: 0 | I39: 0 | J39: 0 | K39: 0 | L39: 0 | M39: 0
A40: 30: Reallocation conservation — ΔHedgeCo + ΔFinServCo + ΔAmeriBankCo + ΔOfficial = 0 | B40: Within-period reallocation must net to zero. New issuance (GovCo fiscal deficit) handled separately. Non-zero = unidentified seller. | C40: 0 | D40: =((HedgeCo!D4-HedgeCo!C4)+(FinServCo!D5-FinServCo!C5)+(AmeriBankCo!D6-AmeriBankCo!C6)+(AmeriCo!D10-AmeriCo!C10)+(HouseholdCo!D8-HouseholdCo!C8)+(InsuranceCo!D5-InsuranceCo!C5)+(OtherBankCo!D5-OtherBankCo!C5)) -> #VALUE! | E40: =((HedgeCo!E4-HedgeCo!D4)+(FinServCo!E5-FinServCo!D5)+(AmeriBankCo!E6-AmeriBankCo!D6)+(AmeriCo!E10-AmeriCo!D10)+(HouseholdCo!E8-HouseholdCo!D8)+(InsuranceCo!E5-InsuranceCo!D5)+(OtherBankCo!E5-OtherBankCo!D5)) -> #VALUE! | F40: =((HedgeCo!F4-HedgeCo!E4)+(FinServCo!F5-FinServCo!E5)+(AmeriBankCo!F6-AmeriBankCo!E6)+(AmeriCo!F10-AmeriCo!E10)+(HouseholdCo!F8-HouseholdCo!E8)+(InsuranceCo!F5-InsuranceCo!E5)+(OtherBankCo!F5-OtherBankCo!E5)) -> #VALUE! | G40: =((HedgeCo!G4-HedgeCo!F4)+(FinServCo!G5-FinServCo!F5)+(AmeriBankCo!G6-AmeriBankCo!F6)+(AmeriCo!G10-AmeriCo!F10)+(HouseholdCo!G8-HouseholdCo!F8)+(InsuranceCo!G5-InsuranceCo!F5)+(OtherBankCo!G5-OtherBankCo!F5)) -> #VALUE! | H40: =((HedgeCo!H4-HedgeCo!G4)+(FinServCo!H5-FinServCo!G5)+(AmeriBankCo!H6-AmeriBankCo!G6)+(AmeriCo!H10-AmeriCo!G10)+(HouseholdCo!H8-HouseholdCo!G8)+(InsuranceCo!H5-InsuranceCo!G5)+(OtherBankCo!H5-OtherBankCo!G5)) -> #VALUE! | I40: =((HedgeCo!I4-HedgeCo!H4)+(FinServCo!I5-FinServCo!H5)+(AmeriBankCo!I6-AmeriBankCo!H6)+(AmeriCo!I10-AmeriCo!H10)+(HouseholdCo!I8-HouseholdCo!H8)+(InsuranceCo!I5-InsuranceCo!H5)+(OtherBankCo!I5-OtherBankCo!H5)) -> #VALUE! | J40: =((HedgeCo!J4-HedgeCo!I4)+(FinServCo!J5-FinServCo!I5)+(AmeriBankCo!J6-AmeriBankCo!I6)+(AmeriCo!J10-AmeriCo!I10)+(HouseholdCo!J8-HouseholdCo!I8)+(InsuranceCo!J5-InsuranceCo!I5)+(OtherBankCo!J5-OtherBankCo!I5)) -> #VALUE! | K40: =((HedgeCo!K4-HedgeCo!J4)+(FinServCo!K5-FinServCo!J5)+(AmeriBankCo!K6-AmeriBankCo!J6)+(AmeriCo!K10-AmeriCo!J10)+(HouseholdCo!K8-HouseholdCo!J8)+(InsuranceCo!K5-InsuranceCo!J5)+(OtherBankCo!K5-OtherBankCo!J5)) -> #VALUE! | ... M40: =((HedgeCo!M4-HedgeCo!L4)+(FinServCo!M5-FinServCo!L5)+(AmeriBankCo!M6-AmeriBankCo!L6)+(AmeriCo!M10-AmeriCo!L10)+(HouseholdCo!M8-HouseholdCo!L8)+(InsuranceCo!M5-InsuranceCo!L5)+(OtherBankCo!M5-OtherBankCo!L5)) -> #VALUE!
A41: DIAG: HedgeCo growth threshold = MAX(0, HedgeCo - 270) -- step function, fires when HedgeCo exceeds threshold | B41: ΔHedgeCo_from_Y0 vs total seller capacity. Seller capacity = FinServCo_Y0(60) + AmeriBankCo_Y0(30) + Official_Y0(100) = 190B. Was hardcoded 216 (stale — included FinServCo+AmeriBankCo+Official=126+30+60=216 using old Official=126). Now 190 (Official=100). OtherBankCo covers remainder as swing seller. | C41: =MAX(0,HedgeCo!C4-ASSUMPTIONS!C70-(60+30+100)) -> 0 | D41: =MAX(0,HedgeCo!D4-ASSUMPTIONS!C70-(60+30+100)) -> 0 | E41: =MAX(0,HedgeCo!E4-ASSUMPTIONS!C70-(60+30+100)) -> 0 | F41: =MAX(0,HedgeCo!F4-ASSUMPTIONS!C70-(60+30+100)) -> 0 | G41: =MAX(0,HedgeCo!G4-ASSUMPTIONS!C70-(60+30+100)) -> 0 | H41: =MAX(0,HedgeCo!H4-ASSUMPTIONS!C70-(60+30+100)) -> 35.060135 | I41: =MAX(0,HedgeCo!I4-ASSUMPTIONS!C70-(60+30+100)) -> 167.86861 | J41: =MAX(0,HedgeCo!J4-ASSUMPTIONS!C70-(60+30+100)) -> 303.64709 | K41: =MAX(0,HedgeCo!K4-ASSUMPTIONS!C70-(60+30+100)) -> 483.98583 | L41: =MAX(0,HedgeCo!L4-ASSUMPTIONS!C70-(60+30+100)) -> 658.81368 | M41: =MAX(0,HedgeCo!M4-ASSUMPTIONS!C70-(60+30+100)) -> 752.58234
A42: 32: OtherBankCo floor check — must be ≥ 0 (cannot sell what it doesn't own) | B42: OtherBankCo is the residual absorber. If negative: reallocation demand exceeds all named sellers. Model limit reached. | C42: =MIN(0,OtherBankCo!C5) -> #VALUE! | D42: =MIN(0,OtherBankCo!D5) -> #VALUE! | E42: =MIN(0,OtherBankCo!E5) -> #VALUE! | F42: =MIN(0,OtherBankCo!F5) -> #VALUE! | G42: =MIN(0,OtherBankCo!G5) -> #VALUE! | H42: =MIN(0,OtherBankCo!H5) -> #VALUE! | I42: =MIN(0,OtherBankCo!I5) -> #VALUE! | J42: =MIN(0,OtherBankCo!J5) -> #VALUE! | ... M42: =MIN(0,OtherBankCo!M5) -> #VALUE!
A43: 33: HouseholdCo direct TSY = GovCo!HH_direct holder row | B43: HH direct TSY asset = GovCo liability to HH. SFC mirror. | C43: =HouseholdCo!C8-GovCo!C12 -> #VALUE! | D43: =HouseholdCo!D8-GovCo!D12 -> #VALUE! | E43: =HouseholdCo!E8-GovCo!E12 -> #VALUE! | F43: =HouseholdCo!F8-GovCo!F12 -> #VALUE! | G43: =HouseholdCo!G8-GovCo!G12 -> #VALUE! | H43: =HouseholdCo!H8-GovCo!H12 -> #VALUE! | I43: =HouseholdCo!I8-GovCo!I12 -> #VALUE! | J43: =HouseholdCo!J8-GovCo!J12 -> #VALUE! | ... M43: =HouseholdCo!M8-GovCo!M12 -> #VALUE!
A44: 34: InsuranceCo TSY = GovCo!InsuranceCo holder row | B44: InsuranceCo TSY asset = GovCo liability to insurance sector. SFC mirror. | C44: =InsuranceCo!C5-GovCo!C13 -> #VALUE! | D44: =InsuranceCo!D5-GovCo!D13 -> #VALUE! | E44: =InsuranceCo!E5-GovCo!E13 -> #VALUE! | F44: =InsuranceCo!F5-GovCo!F13 -> #VALUE! | G44: =InsuranceCo!G5-GovCo!G13 -> #VALUE! | H44: =InsuranceCo!H5-GovCo!H13 -> #VALUE! | I44: =InsuranceCo!I5-GovCo!I13 -> #VALUE! | J44: =InsuranceCo!J5-GovCo!J13 -> #VALUE! | ... M44: =InsuranceCo!M5-GovCo!M13 -> #VALUE!
A45: 35: OtherBankCo TSY = GovCo!OtherBankCo holder row | B45: OtherBankCo TSY asset = GovCo liability to regional banks. SFC mirror. | C45: =OtherBankCo!C5-GovCo!C16 -> #VALUE! | D45: =OtherBankCo!D5-GovCo!D16 -> #VALUE! | E45: =OtherBankCo!E5-GovCo!E16 -> #VALUE! | F45: =OtherBankCo!F5-GovCo!F16 -> #VALUE! | G45: =OtherBankCo!G5-GovCo!G16 -> #VALUE! | H45: =OtherBankCo!H5-GovCo!H16 -> #VALUE! | I45: =OtherBankCo!I5-GovCo!I16 -> #VALUE! | J45: =OtherBankCo!J5-GovCo!J16 -> #VALUE! | ... M45: =OtherBankCo!M5-GovCo!M16 -> #VALUE!
A46: 36: GovCo total = sum of all named holders + true residual | B46: Full holder decomposition. = FedCo + HedgeCo + Official + HH + Ins + OtherBank + residual. Gap = 0. | C46: =GovCo!C18-(GovCo!C9+GovCo!C10+GovCo!C11+GovCo!C12+GovCo!C13+GovCo!C14+GovCo!C15+GovCo!C16+GovCo!C17) -> #VALUE! | D46: =GovCo!D18-(GovCo!D9+GovCo!D10+GovCo!D11+GovCo!D12+GovCo!D13+GovCo!D14+GovCo!D15+GovCo!D16+GovCo!D17) -> #VALUE! | E46: =GovCo!E18-(GovCo!E9+GovCo!E10+GovCo!E11+GovCo!E12+GovCo!E13+GovCo!E14+GovCo!E15+GovCo!E16+GovCo!E17) -> #VALUE! | F46: =GovCo!F18-(GovCo!F9+GovCo!F10+GovCo!F11+GovCo!F12+GovCo!F13+GovCo!F14+GovCo!F15+GovCo!F16+GovCo!F17) -> #VALUE! | G46: =GovCo!G18-(GovCo!G9+GovCo!G10+GovCo!G11+GovCo!G12+GovCo!G13+GovCo!G14+GovCo!G15+GovCo!G16+GovCo!G17) -> #VALUE! | H46: =GovCo!H18-(GovCo!H9+GovCo!H10+GovCo!H11+GovCo!H12+GovCo!H13+GovCo!H14+GovCo!H15+GovCo!H16+GovCo!H17) -> #VALUE! | I46: =GovCo!I18-(GovCo!I9+GovCo!I10+GovCo!I11+GovCo!I12+GovCo!I13+GovCo!I14+GovCo!I15+GovCo!I16+GovCo!I17) -> #VALUE! | J46: =GovCo!J18-(GovCo!J9+GovCo!J10+GovCo!J11+GovCo!J12+GovCo!J13+GovCo!J14+GovCo!J15+GovCo!J16+GovCo!J17) -> #VALUE! | ... M46: =GovCo!M18-(GovCo!M9+GovCo!M10+GovCo!M11+GovCo!M12+GovCo!M13+GovCo!M14+GovCo!M15+GovCo!M16+GovCo!M17) -> #VALUE!
A47: 37: True residual check — should be small relative to GovCo total | B47: True residual / GovCo total. Should be < 5% for model to be publication-ready. | C47: =IF(GovCo!C18=0,"-",GovCo!C17/GovCo!C18) -> #VALUE! | D47: =IF(GovCo!D18=0,"-",GovCo!D17/GovCo!D18) -> #VALUE! | E47: =IF(GovCo!E18=0,"-",GovCo!E17/GovCo!E18) -> #VALUE! | F47: =IF(GovCo!F18=0,"-",GovCo!F17/GovCo!F18) -> #VALUE! | G47: =IF(GovCo!G18=0,"-",GovCo!G17/GovCo!G18) -> #VALUE! | H47: =IF(GovCo!H18=0,"-",GovCo!H17/GovCo!H18) -> #VALUE! | I47: =IF(GovCo!I18=0,"-",GovCo!I17/GovCo!I18) -> #VALUE! | J47: =IF(GovCo!J18=0,"-",GovCo!J17/GovCo!J18) -> #VALUE! | ... M47: =IF(GovCo!M18=0,"-",GovCo!M17/GovCo!M18) -> #VALUE!
A48: DIAG: Partial Treasury reallocation (extended) -- not an identity, see r30 note | B48: ΔHedgeCo + ΔFinServCo + ΔAmeriBankCo + ΔOfficial + ΔHH + ΔIns + ΔOtherBank = 0 (reallocation only). | C48: =0 -> 0 | D48: =((HedgeCo!D4-HedgeCo!C4)+(FinServCo!D5-FinServCo!C5)+(AmeriBankCo!D6-AmeriBankCo!C6)+(AmeriCo!D10-AmeriCo!C10)+(HouseholdCo!D8-HouseholdCo!C8)+(InsuranceCo!D5-InsuranceCo!C5)+(OtherBankCo!D5-OtherBankCo!C5)) -> #VALUE! | E48: =((HedgeCo!E4-HedgeCo!D4)+(FinServCo!E5-FinServCo!D5)+(AmeriBankCo!E6-AmeriBankCo!D6)+(AmeriCo!E10-AmeriCo!D10)+(HouseholdCo!E8-HouseholdCo!D8)+(InsuranceCo!E5-InsuranceCo!D5)+(OtherBankCo!E5-OtherBankCo!D5)) -> #VALUE! | F48: =((HedgeCo!F4-HedgeCo!E4)+(FinServCo!F5-FinServCo!E5)+(AmeriBankCo!F6-AmeriBankCo!E6)+(AmeriCo!F10-AmeriCo!E10)+(HouseholdCo!F8-HouseholdCo!E8)+(InsuranceCo!F5-InsuranceCo!E5)+(OtherBankCo!F5-OtherBankCo!E5)) -> #VALUE! | G48: =((HedgeCo!G4-HedgeCo!F4)+(FinServCo!G5-FinServCo!F5)+(AmeriBankCo!G6-AmeriBankCo!F6)+(AmeriCo!G10-AmeriCo!F10)+(HouseholdCo!G8-HouseholdCo!F8)+(InsuranceCo!G5-InsuranceCo!F5)+(OtherBankCo!G5-OtherBankCo!F5)) -> #VALUE! | H48: =((HedgeCo!H4-HedgeCo!G4)+(FinServCo!H5-FinServCo!G5)+(AmeriBankCo!H6-AmeriBankCo!G6)+(AmeriCo!H10-AmeriCo!G10)+(HouseholdCo!H8-HouseholdCo!G8)+(InsuranceCo!H5-InsuranceCo!G5)+(OtherBankCo!H5-OtherBankCo!G5)) -> #VALUE! | I48: =((HedgeCo!I4-HedgeCo!H4)+(FinServCo!I5-FinServCo!H5)+(AmeriBankCo!I6-AmeriBankCo!H6)+(AmeriCo!I10-AmeriCo!H10)+(HouseholdCo!I8-HouseholdCo!H8)+(InsuranceCo!I5-InsuranceCo!H5)+(OtherBankCo!I5-OtherBankCo!H5)) -> #VALUE! | J48: =((HedgeCo!J4-HedgeCo!I4)+(FinServCo!J5-FinServCo!I5)+(AmeriBankCo!J6-AmeriBankCo!I6)+(AmeriCo!J10-AmeriCo!I10)+(HouseholdCo!J8-HouseholdCo!I8)+(InsuranceCo!J5-InsuranceCo!I5)+(OtherBankCo!J5-OtherBankCo!I5)) -> #VALUE! | K48: =((HedgeCo!K4-HedgeCo!J4)+(FinServCo!K5-FinServCo!J5)+(AmeriBankCo!K6-AmeriBankCo!J6)+(AmeriCo!K10-AmeriCo!J10)+(HouseholdCo!K8-HouseholdCo!J8)+(InsuranceCo!K5-InsuranceCo!J5)+(OtherBankCo!K5-OtherBankCo!J5)) -> #VALUE! | ... M48: =((HedgeCo!M4-HedgeCo!L4)+(FinServCo!M5-FinServCo!L5)+(AmeriBankCo!M6-AmeriBankCo!L6)+(AmeriCo!M10-AmeriCo!L10)+(HouseholdCo!M8-HouseholdCo!L8)+(InsuranceCo!M5-InsuranceCo!L5)+(OtherBankCo!M5-OtherBankCo!L5)) -> #VALUE!
A49: 39: Two-phase commodity shock — Phase1 CA surplus + Phase2 CA compression = accounting consequence | B49: Phase1 JapanCo CA surplus rise = -oil_import_bill collapse (import bill=0 when Hormuz closed). Phase2 CA compression = partial import recovery at higher price. No stochastic parameter needed — emerges from JapanCo balance sheet mechanics. | C49: =JapanCo!C25-(JapanCo!C21-JapanCo!C24) -> 0 | D49: =JapanCo!D25-(JapanCo!D21-JapanCo!D24) -> 0 | E49: =JapanCo!E25-(JapanCo!E21-JapanCo!E24) -> 0 | F49: =JapanCo!F25-(JapanCo!F21-JapanCo!F24) -> 0 | G49: =JapanCo!G25-(JapanCo!G21-JapanCo!G24) -> 0 | H49: =JapanCo!H25-(JapanCo!H21-JapanCo!H24) -> 0 | I49: =JapanCo!I25-(JapanCo!I21-JapanCo!I24) -> 0 | J49: =JapanCo!J25-(JapanCo!J21-JapanCo!J24) -> 0 | ... M49: =JapanCo!M25-(JapanCo!M21-JapanCo!M24) -> 0
A50: 40: SRF balance sheet — FedCo SRF asset = AmeriBankCo SRF liability | B50: Standing Repo Facility. FedCo lends to AmeriBankCo at administered rate. Mirror must = 0. SRF does not create bonds — repo collateral stays off-BS. | C50: =FedCo!C20-AmeriBankCo!C20 -> 0 | D50: =FedCo!D20-AmeriBankCo!D20 -> 0 | E50: =FedCo!E20-AmeriBankCo!E20 -> 0 | F50: =FedCo!F20-AmeriBankCo!F20 -> 0 | G50: =FedCo!G20-AmeriBankCo!G20 -> 0 | H50: =FedCo!H20-AmeriBankCo!H20 -> 0 | I50: =FedCo!I20-AmeriBankCo!I20 -> 0 | J50: =FedCo!J20-AmeriBankCo!J20 -> 0 | ... M50: =FedCo!M20-AmeriBankCo!M20 -> 0
A51: 41: FedCo FIMA = JapanCo FIMA pledge [KNOWN ISSUE v2: different bases. FedCo r21 uses MEASURES C58, JapanCo r29 uses JapanCo r4 times FIMA_active. Affects only FIMA stress-year accounting.] | B51: Foreign official repo. FedCo holds TSY collateral, JapanCo has dollar liability. Path B bypass: TSY stays at FedCo, not sold into secondary market. | C51: =FedCo!C21-JapanCo!C29 -> 0 | D51: =FedCo!D21-JapanCo!D29 -> 0 | E51: =FedCo!E21-JapanCo!E29 -> 0 | F51: =FedCo!F21-JapanCo!F29 -> 0 | G51: =FedCo!G21-JapanCo!G29 -> 0 | H51: =FedCo!H21-JapanCo!H29 -> 0 | I51: =FedCo!I21-JapanCo!I29 -> 0 | J51: =FedCo!J21-JapanCo!J29 -> 0 | ... M51: =FedCo!M21-JapanCo!M29 -> -113.558
A52: DIAG: Suppressed yield gap = MAX(0, MEASURES yield_gap) -- non-zero indicates SRF/FIMA active suppression | B52: Suppressed gap ≥ 0 always (SRF/FIMA can only suppress, not amplify). Positive = hidden pressure. When gap > 0 for extended periods: tail risk building. Discontinuity fires when SRF capacity saturates or FIMA credibility breaks. | C52: =MAX(0,MEASURES!C56) -> 0.002 | D52: =MAX(0,MEASURES!D56) -> 0.0280283 | E52: =MAX(0,MEASURES!E56) -> 0.057102439 | F52: =MAX(0,MEASURES!F56) -> 0.069133333 | G52: =MAX(0,MEASURES!G56) -> 0.069133333 | H52: =MAX(0,MEASURES!H56) -> 0.069133333 | I52: =MAX(0,MEASURES!I56) -> 0.069133333 | J52: =MAX(0,MEASURES!J56) -> 0.069133333 | ... M52: =MAX(0,MEASURES!M56) -> 0.10213333
A53: 43: CommodityCo SWF equity = ProdServiceCo equity held by CommodityCo | B53: CommodityCo!r8 = ProdServiceCo!r11 -- difference must = 0 | C53: 0 | D53: 0 | E53: 0 | F53: 0 | G53: 0 | H53: 0 | I53: 0 | J53: 0 | K53: 0 | L53: 0 | M53: 0
A54: 44: ProdServiceCo total equity = FinServCo + CommodityCo SWF | B54: ProdServiceCo!r9 = ProdServiceCo!r10 + ProdServiceCo!r11 -- must = 0 | C54: 0 | D54: 0 | E54: 0 | F54: 0 | G54: 0 | H54: 0 | I54: 0 | J54: 0 | K54: 0 | L54: 0 | M54: 0
A55: 45: JapHH savings = JapBankCo deposit inflow (JapanCo domestic closure) | B55: JapanCo!hh_savings = delta(JapBankCo deposits) -- difference = 0 | C55: 0 | D55: 0 | E55: 0 | F55: 0 | G55: 0 | H55: 0 | I55: 0 | J55: 0 | K55: 0 | L55: 0 | M55: 0
A56: 46: JapBankCo assets = JGB + GBC deposit + loans = HH deposits (balance) | B56: JapBankCo total assets = total liabilities -- zero residual | C56: 0 | D56: 0 | E56: 0 | F56: 0 | G56: 0 | H56: 0 | I56: 0 | J56: 0 | K56: 0 | L56: 0 | M56: 0
A57: 47: JapGovCo JGB = JapBankCo JGB + JapCBCo JGB + HH direct JGB | B57: Full holder decomposition -- must sum to JapGovCo!r27 | C57: 0 | D57: 0 | E57: 0 | F57: 0 | G57: 0 | H57: 0 | I57: 0 | J57: 0 | K57: 0 | L57: 0 | M57: 0
